Workbook

Sheet Editable assumptions
A1: Editable assumptions
A2: AgentBisect — Financial Model · Main Scenario
A4: Variable / dimension | B4: Value
A5: Model cost per investigation | B5: =0.25 -> 0.25
A6: Compute cost per investigation | B6: =0.05 -> 0.05
A7: Compute minutes per investigation | B7: =10 -> 10
A8: Fixed hosting | B8: =300 -> 300
A9: Founder monthly salary | B9: =8000 -> 8000
A10: Unpaid founder months | B10: =6 -> 6
A11: Starting cash | B11: =25000 -> 25000
A12: Opening paying teams | B12: =0 -> 0
A13: Net new teams per month | B13: =5 -> 5
A14: Free repos | B14: =50 -> 50
A15: Forecast months | B15: =24 -> 24
A16: Forecast start | B16: =DATE(2026,10,1) -> 46296
A17: Month 12 paying team target | B17: ='Editable assumptions'!B12+'Editable assumptions'!B13*12 -> 60

Sheet Unit economics by plan
A1: Unit economics by plan
A2: AgentBisect — Financial Model · Main Scenario
A4: Variable / dimension | B4: Monthly price per repo | C4: Included investigations | D4: Average investigations | E4: Overage price | F4: Revenue per repo | G4: Investigation unit cost | H4: Variable cost per repo | I4: Contribution per repo | J4: Contribution margin | K4: Compute hours per repo
A5: Free | B5: =0 -> 0 | C5: =10 -> 10 | D5: =10 -> 10 | E5: =0 -> 0 | F5: ='Unit economics by plan'!B5+MAX('Unit economics by plan'!D5-'Unit economics by plan'!C5,0)*'Unit economics by plan'!E5 -> 0 | G5: ='Editable assumptions'!B5+'Editable assumptions'!B6 -> 0.3 | H5: ='Unit economics by plan'!D5*'Unit economics by plan'!G5 -> 3 | I5: ='Unit economics by plan'!F5-'Unit economics by plan'!H5 -> -3 | J5: =IFERROR('Unit economics by plan'!I5/'Unit economics by plan'!F5,"") | K5: ='Unit economics by plan'!D5*'Editable assumptions'!B7/60 -> 1.6666667
A6: Team | B6: =99 -> 99 | C6: =100 -> 100 | D6: =60 -> 60 | E6: =1 -> 1 | F6: ='Unit economics by plan'!B6+MAX('Unit economics by plan'!D6-'Unit economics by plan'!C6,0)*'Unit economics by plan'!E6 -> 99 | G6: ='Editable assumptions'!B5+'Editable assumptions'!B6 -> 0.3 | H6: ='Unit economics by plan'!D6*'Unit economics by plan'!G6 -> 18 | I6: ='Unit economics by plan'!F6-'Unit economics by plan'!H6 -> 81 | J6: =IFERROR('Unit economics by plan'!I6/'Unit economics by plan'!F6,"") -> 0.81818182 | K6: ='Unit economics by plan'!D6*'Editable assumptions'!B7/60 -> 10

Sheet Monthly forecast and cash
A1: Monthly forecast and cash
A2: AgentBisect — Financial Model · Main Scenario
A4: Variable / dimension | B4: 2026-09 | C4: 2026-10 | D4: 2026-11 | E4: 2026-12 | F4: 2027-01 | G4: 2027-02 | H4: 2027-03 | I4: 2027-04 | J4: 2027-05 | K4: 2027-06 | L4: 2027-07 | M4: 2027-08 | N4: 2027-09 | O4: 2027-10 | P4: 2027-11 | Q4: 2027-12 | R4: 2028-01 | S4: 2028-02 | T4: 2028-03 | U4: 2028-04 | V4: 2028-05 | W4: 2028-06 | X4: 2028-07 | Y4: 2028-08 | Z4: 2028-09
A5: Forecast month number | B5: 0 | C5: =DATEDIF('Editable assumptions'!B16,DATE(2026,10,1),"M")+1 -> 1 | D5: =DATEDIF('Editable assumptions'!B16,DATE(2026,11,1),"M")+1 -> 2 | E5: =DATEDIF('Editable assumptions'!B16,DATE(2026,12,1),"M")+1 -> 3 | F5: =DATEDIF('Editable assumptions'!B16,DATE(2027,1,1),"M")+1 -> 4 | G5: =DATEDIF('Editable assumptions'!B16,DATE(2027,2,1),"M")+1 -> 5 | H5: =DATEDIF('Editable assumptions'!B16,DATE(2027,3,1),"M")+1 -> 6 | I5: =DATEDIF('Editable assumptions'!B16,DATE(2027,4,1),"M")+1 -> 7 | J5: =DATEDIF('Editable assumptions'!B16,DATE(2027,5,1),"M")+1 -> 8 | K5: =DATEDIF('Editable assumptions'!B16,DATE(2027,6,1),"M")+1 -> 9 | L5: =DATEDIF('Editable assumptions'!B16,DATE(2027,7,1),"M")+1 -> 10 | M5: =DATEDIF('Editable assumptions'!B16,DATE(2027,8,1),"M")+1 -> 11 | N5: =DATEDIF('Editable assumptions'!B16,DATE(2027,9,1),"M")+1 -> 12 | O5: =DATEDIF('Editable assumptions'!B16,DATE(2027,10,1),"M")+1 -> 13 | P5: =DATEDIF('Editable assumptions'!B16,DATE(2027,11,1),"M")+1 -> 14 | Q5: =DATEDIF('Editable assumptions'!B16,DATE(2027,12,1),"M")+1 -> 15 | R5: =DATEDIF('Editable assumptions'!B16,DATE(2028,1,1),"M")+1 -> 16 | S5: =DATEDIF('Editable assumptions'!B16,DATE(2028,2,1),"M")+1 -> 17 | T5: =DATEDIF('Editable assumptions'!B16,DATE(2028,3,1),"M")+1 -> 18 | U5: =DATEDIF('Editable assumptions'!B16,DATE(2028,4,1),"M")+1 -> 19 | V5: =DATEDIF('Editable assumptions'!B16,DATE(2028,5,1),"M")+1 -> 20 | W5: =DATEDIF('Editable assumptions'!B16,DATE(2028,6,1),"M")+1 -> 21 | X5: =DATEDIF('Editable assumptions'!B16,DATE(2028,7,1),"M")+1 -> 22 | Y5: =DATEDIF('Editable assumptions'!B16,DATE(2028,8,1),"M")+1 -> 23 | Z5: =DATEDIF('Editable assumptions'!B16,DATE(2028,9,1),"M")+1 -> 24
A6: Monthly net new teams | B6: 0 | C6: =IF('Editable assumptions'!B13="","",'Editable assumptions'!B13) -> 5 | D6: =IF('Monthly forecast and cash'!C6="","",'Monthly forecast and cash'!C6) -> 5 | E6: =IF('Monthly forecast and cash'!D6="","",'Monthly forecast and cash'!D6) -> 5 | F6: =IF('Monthly forecast and cash'!E6="","",'Monthly forecast and cash'!E6) -> 5 | G6: =IF('Monthly forecast and cash'!F6="","",'Monthly forecast and cash'!F6) -> 5 | H6: =IF('Monthly forecast and cash'!G6="","",'Monthly forecast and cash'!G6) -> 5 | I6: =IF('Monthly forecast and cash'!H6="","",'Monthly forecast and cash'!H6) -> 5 | J6: =IF('Monthly forecast and cash'!I6="","",'Monthly forecast and cash'!I6) -> 5 | K6: =IF('Monthly forecast and cash'!J6="","",'Monthly forecast and cash'!J6) -> 5 | ... Z6: =IF('Monthly forecast and cash'!Y6="","",'Monthly forecast and cash'!Y6) -> 5
A7: Paying teams | B7: 0 | C7: =IF(IF(IF(IF(ISERROR('Monthly forecast and cash'!C5=1),'Monthly forecast and cash'!C5=1,IF('Monthly forecast and cash'!C5="","",'Monthly forecast and cash'!C5=1))="",FALSE,IF(ISERROR('Monthly forecast and cash'!C5=1),'Monthly forecast and cash'!C5=1,IF('Monthly forecast and cash'!C5="","",'Monthly forecast and cash'!C5=1))),IF('Editable assumptions'!B12="","",'Editable assumptions'!B12),IF('Monthly forecast and cash'!B7="","",'Monthly forecast and cash'!B7))="",0,IF(IF(IF(ISERROR('Monthly forecast and cash'!C5=1),'Monthly forecast and cash'!C5=1,IF('Monthly forecast and cash'!C5="","",'Monthly forecast and cash'!C5=1))="",FALSE,IF(ISERROR('Monthly forecast and cash'!C5=1),'Monthly forecast and cash'!C5=1,IF('Monthly forecast and cash'!C5="","",'Monthly forecast and cash'!C5=1))),IF('Editable assumptions'!B12="","",'Editable assumptions'!B12),IF('Monthly forecast and cash'!B7="","",'Monthly forecast and cash'!B7)))+'Monthly forecast and cash'!C6 -> 5 | D7: =IF(IF(IF(IF(ISERROR('Monthly forecast and cash'!D5=1),'Monthly forecast and cash'!D5=1,IF('Monthly forecast and cash'!D5="","",'Monthly forecast and cash'!D5=1))="",FALSE,IF(ISERROR('Monthly forecast and cash'!D5=1),'Monthly forecast and cash'!D5=1,IF('Monthly forecast and cash'!D5="","",'Monthly forecast and cash'!D5=1))),IF('Editable assumptions'!B12="","",'Editable assumptions'!B12),IF('Monthly forecast and cash'!C7="","",'Monthly forecast and cash'!C7))="",0,IF(IF(IF(ISERROR('Monthly forecast and cash'!D5=1),'Monthly forecast and cash'!D5=1,IF('Monthly forecast and cash'!D5="","",'Monthly forecast and cash'!D5=1))="",FALSE,IF(ISERROR('Monthly forecast and cash'!D5=1),'Monthly forecast and cash'!D5=1,IF('Monthly forecast and cash'!D5="","",'Monthly forecast and cash'!D5=1))),IF('Editable assumptions'!B12="","",'Editable assumptions'!B12),IF('Monthly forecast and cash'!C7="","",'Monthly forecast and cash'!C7)))+'Monthly forecast and cash'!D6 -> 10 | E7: =IF(IF(IF(IF(ISERROR('Monthly forecast and cash'!E5=1),'Monthly forecast and cash'!E5=1,IF('Monthly forecast and cash'!E5="","",'Monthly forecast and cash'!E5=1))="",FALSE,IF(ISERROR('Monthly forecast and cash'!E5=1),'Monthly forecast and cash'!E5=1,IF('Monthly forecast and cash'!E5="","",'Monthly forecast and cash'!E5=1))),IF('Editable assumptions'!B12="","",'Editable assumptions'!B12),IF('Monthly forecast and cash'!D7="","",'Monthly forecast and cash'!D7))="",0,IF(IF(IF(ISERROR('Monthly forecast and cash'!E5=1),'Monthly forecast and cash'!E5=1,IF('Monthly forecast and cash'!E5="","",'Monthly forecast and cash'!E5=1))="",FALSE,IF(ISERROR('Monthly forecast and cash'!E5=1),'Monthly forecast and cash'!E5=1,IF('Monthly forecast and cash'!E5="","",'Monthly forecast and cash'!E5=1))),IF('Editable assumptions'!B12="","",'Editable assumptions'!B12),IF('Monthly forecast and cash'!D7="","",'Monthly forecast and cash'!D7)))+'Monthly forecast and cash'!E6 -> 15 | F7: =IF(IF(IF(IF(ISERROR('Monthly forecast and cash'!F5=1),'Monthly forecast and cash'!F5=1,IF('Monthly forecast and cash'!F5="","",'Monthly forecast and cash'!F5=1))="",FALSE,IF(ISERROR('Monthly forecast and cash'!F5=1),'Monthly forecast and cash'!F5=1,IF('Monthly forecast and cash'!F5="","",'Monthly forecast and cash'!F5=1))),IF('Editable assumptions'!B12="","",'Editable assumptions'!B12),IF('Monthly forecast and cash'!E7="","",'Monthly forecast and cash'!E7))="",0,IF(IF(IF(ISERROR('Monthly forecast and cash'!F5=1),'Monthly forecast and cash'!F5=1,IF('Monthly forecast and cash'!F5="","",'Monthly forecast and cash'!F5=1))="",FALSE,IF(ISERROR('Monthly forecast and cash'!F5=1),'Monthly forecast and cash'!F5=1,IF('Monthly forecast and cash'!F5="","",'Monthly forecast and cash'!F5=1))),IF('Editable assumptions'!B12="","",'Editable assumptions'!B12),IF('Monthly forecast and cash'!E7="","",'Monthly forecast and cash'!E7)))+'Monthly forecast and cash'!F6 -> 20 | G7: =IF(IF(IF(IF(ISERROR('Monthly forecast and cash'!G5=1),'Monthly forecast and cash'!G5=1,IF('Monthly forecast and cash'!G5="","",'Monthly forecast and cash'!G5=1))="",FALSE,IF(ISERROR('Monthly forecast and cash'!G5=1),'Monthly forecast and cash'!G5=1,IF('Monthly forecast and cash'!G5="","",'Monthly forecast and cash'!G5=1))),IF('Editable assumptions'!B12="","",'Editable assumptions'!B12),IF('Monthly forecast and cash'!F7="","",'Monthly forecast and cash'!F7))="",0,IF(IF(IF(ISERROR('Monthly forecast and cash'!G5=1),'Monthly forecast and cash'!G5=1,IF('Monthly forecast and cash'!G5="","",'Monthly forecast and cash'!G5=1))="",FALSE,IF(ISERROR('Monthly forecast and cash'!G5=1),'Monthly forecast and cash'!G5=1,IF('Monthly forecast and cash'!G5="","",'Monthly forecast and cash'!G5=1))),IF('Editable assumptions'!B12="","",'Editable assumptions'!B12),IF('Monthly forecast and cash'!F7="","",'Monthly forecast and cash'!F7)))+'Monthly forecast and cash'!G6 -> 25 | H7: =IF(IF(IF(IF(ISERROR('Monthly forecast and cash'!H5=1),'Monthly forecast and cash'!H5=1,IF('Monthly forecast and cash'!H5="","",'Monthly forecast and cash'!H5=1))="",FALSE,IF(ISERROR('Monthly forecast and cash'!H5=1),'Monthly forecast and cash'!H5=1,IF('Monthly forecast and cash'!H5="","",'Monthly forecast and cash'!H5=1))),IF('Editable assumptions'!B12="","",'Editable assumptions'!B12),IF('Monthly forecast and cash'!G7="","",'Monthly forecast and cash'!G7))="",0,IF(IF(IF(ISERROR('Monthly forecast and cash'!H5=1),'Monthly forecast and cash'!H5=1,IF('Monthly forecast and cash'!H5="","",'Monthly forecast and cash'!H5=1))="",FALSE,IF(ISERROR('Monthly forecast and cash'!H5=1),'Monthly forecast and cash'!H5=1,IF('Monthly forecast and cash'!H5="","",'Monthly forecast and cash'!H5=1))),IF('Editable assumptions'!B12="","",'Editable assumptions'!B12),IF('Monthly forecast and cash'!G7="","",'Monthly forecast and cash'!G7)))+'Monthly forecast and cash'!H6 -> 30 | I7: =IF(IF(IF(IF(ISERROR('Monthly forecast and cash'!I5=1),'Monthly forecast and cash'!I5=1,IF('Monthly forecast and cash'!I5="","",'Monthly forecast and cash'!I5=1))="",FALSE,IF(ISERROR('Monthly forecast and cash'!I5=1),'Monthly forecast and cash'!I5=1,IF('Monthly forecast and cash'!I5="","",'Monthly forecast and cash'!I5=1))),IF('Editable assumptions'!B12="","",'Editable assumptions'!B12),IF('Monthly forecast and cash'!H7="","",'Monthly forecast and cash'!H7))="",0,IF(IF(IF(ISERROR('Monthly forecast and cash'!I5=1),'Monthly forecast and cash'!I5=1,IF('Monthly forecast and cash'!I5="","",'Monthly forecast and cash'!I5=1))="",FALSE,IF(ISERROR('Monthly forecast and cash'!I5=1),'Monthly forecast and cash'!I5=1,IF('Monthly forecast and cash'!I5="","",'Monthly forecast and cash'!I5=1))),IF('Editable assumptions'!B12="","",'Editable assumptions'!B12),IF('Monthly forecast and cash'!H7="","",'Monthly forecast and cash'!H7)))+'Monthly forecast and cash'!I6 -> 35 | J7: =IF(IF(IF(IF(ISERROR('Monthly forecast and cash'!J5=1),'Monthly forecast and cash'!J5=1,IF('Monthly forecast and cash'!J5="","",'Monthly forecast and cash'!J5=1))="",FALSE,IF(ISERROR('Monthly forecast and cash'!J5=1),'Monthly forecast and cash'!J5=1,IF('Monthly forecast and cash'!J5="","",'Monthly forecast and cash'!J5=1))),IF('Editable assumptions'!B12="","",'Editable assumptions'!B12),IF('Monthly forecast and cash'!I7="","",'Monthly forecast and cash'!I7))="",0,IF(IF(IF(ISERROR('Monthly forecast and cash'!J5=1),'Monthly forecast and cash'!J5=1,IF('Monthly forecast and cash'!J5="","",'Monthly forecast and cash'!J5=1))="",FALSE,IF(ISERROR('Monthly forecast and cash'!J5=1),'Monthly forecast and cash'!J5=1,IF('Monthly forecast and cash'!J5="","",'Monthly forecast and cash'!J5=1))),IF('Editable assumptions'!B12="","",'Editable assumptions'!B12),IF('Monthly forecast and cash'!I7="","",'Monthly forecast and cash'!I7)))+'Monthly forecast and cash'!J6 -> 40 | K7: =IF(IF(IF(IF(ISERROR('Monthly forecast and cash'!K5=1),'Monthly forecast and cash'!K5=1,IF('Monthly forecast and cash'!K5="","",'Monthly forecast and cash'!K5=1))="",FALSE,IF(ISERROR('Monthly forecast and cash'!K5=1),'Monthly forecast and cash'!K5=1,IF('Monthly forecast and cash'!K5="","",'Monthly forecast and cash'!K5=1))),IF('Editable assumptions'!B12="","",'Editable assumptions'!B12),IF('Monthly forecast and cash'!J7="","",'Monthly forecast and cash'!J7))="",0,IF(IF(IF(ISERROR('Monthly forecast and cash'!K5=1),'Monthly forecast and cash'!K5=1,IF('Monthly forecast and cash'!K5="","",'Monthly forecast and cash'!K5=1))="",FALSE,IF(ISERROR('Monthly forecast and cash'!K5=1),'Monthly forecast and cash'!K5=1,IF('Monthly forecast and cash'!K5="","",'Monthly forecast and cash'!K5=1))),IF('Editable assumptions'!B12="","",'Editable assumptions'!B12),IF('Monthly forecast and cash'!J7="","",'Monthly forecast and cash'!J7)))+'Monthly forecast and cash'!K6 -> 45 | L7: =IF(IF(IF(IF(ISERROR('Monthly forecast and cash'!L5=1),'Monthly forecast and cash'!L5=1,IF('Monthly forecast and cash'!L5="","",'Monthly forecast and cash'!L5=1))="",FALSE,IF(ISERROR('Monthly forecast and cash'!L5=1),'Monthly forecast and cash'!L5=1,IF('Monthly forecast and cash'!L5="","",'Monthly forecast and cash'!L5=1))),IF('Editable assumptions'!B12="","",'Editable assumptions'!B12),IF('Monthly forecast and cash'!K7="","",'Monthly forecast and cash'!K7))="",0,IF(IF(IF(ISERROR('Monthly forecast and cash'!L5=1),'Monthly forecast and cash'!L5=1,IF('Monthly forecast and cash'!L5="","",'Monthly forecast and cash'!L5=1))="",FALSE,IF(ISERROR('Monthly forecast and cash'!L5=1),'Monthly forecast and cash'!L5=1,IF('Monthly forecast and cash'!L5="","",'Monthly forecast and cash'!L5=1))),IF('Editable assumptions'!B12="","",'Editable assumptions'!B12),IF('Monthly forecast and cash'!K7="","",'Monthly forecast and cash'!K7)))+'Monthly forecast and cash'!L6 -> 50 | M7: =IF(IF(IF(IF(ISERROR('Monthly forecast and cash'!M5=1),'Monthly forecast and cash'!M5=1,IF('Monthly forecast and cash'!M5="","",'Monthly forecast and cash'!M5=1))="",FALSE,IF(ISERROR('Monthly forecast and cash'!M5=1),'Monthly forecast and cash'!M5=1,IF('Monthly forecast and cash'!M5="","",'Monthly forecast and cash'!M5=1))),IF('Editable assumptions'!B12="","",'Editable assumptions'!B12),IF('Monthly forecast and cash'!L7="","",'Monthly forecast and cash'!L7))="",0,IF(IF(IF(ISERROR('Monthly forecast and cash'!M5=1),'Monthly forecast and cash'!M5=1,IF('Monthly forecast and cash'!M5="","",'Monthly forecast and cash'!M5=1))="",FALSE,IF(ISERROR('Monthly forecast and cash'!M5=1),'Monthly forecast and cash'!M5=1,IF('Monthly forecast and cash'!M5="","",'Monthly forecast and cash'!M5=1))),IF('Editable assumptions'!B12="","",'Editable assumptions'!B12),IF('Monthly forecast and cash'!L7="","",'Monthly forecast and cash'!L7)))+'Monthly forecast and cash'!M6 -> 55 | N7: =IF(IF(IF(IF(ISERROR('Monthly forecast and cash'!N5=1),'Monthly forecast and cash'!N5=1,IF('Monthly forecast and cash'!N5="","",'Monthly forecast and cash'!N5=1))="",FALSE,IF(ISERROR('Monthly forecast and cash'!N5=1),'Monthly forecast and cash'!N5=1,IF('Monthly forecast and cash'!N5="","",'Monthly forecast and cash'!N5=1))),IF('Editable assumptions'!B12="","",'Editable assumptions'!B12),IF('Monthly forecast and cash'!M7="","",'Monthly forecast and cash'!M7))="",0,IF(IF(IF(ISERROR('Monthly forecast and cash'!N5=1),'Monthly forecast and cash'!N5=1,IF('Monthly forecast and cash'!N5="","",'Monthly forecast and cash'!N5=1))="",FALSE,IF(ISERROR('Monthly forecast and cash'!N5=1),'Monthly forecast and cash'!N5=1,IF('Monthly forecast and cash'!N5="","",'Monthly forecast and cash'!N5=1))),IF('Editable assumptions'!B12="","",'Editable assumptions'!B12),IF('Monthly forecast and cash'!M7="","",'Monthly forecast and cash'!M7)))+'Monthly forecast and cash'!N6 -> 60 | O7: =IF(IF(IF(IF(ISERROR('Monthly forecast and cash'!O5=1),'Monthly forecast and cash'!O5=1,IF('Monthly forecast and cash'!O5="","",'Monthly forecast and cash'!O5=1))="",FALSE,IF(ISERROR('Monthly forecast and cash'!O5=1),'Monthly forecast and cash'!O5=1,IF('Monthly forecast and cash'!O5="","",'Monthly forecast and cash'!O5=1))),IF('Editable assumptions'!B12="","",'Editable assumptions'!B12),IF('Monthly forecast and cash'!N7="","",'Monthly forecast and cash'!N7))="",0,IF(IF(IF(ISERROR('Monthly forecast and cash'!O5=1),'Monthly forecast and cash'!O5=1,IF('Monthly forecast and cash'!O5="","",'Monthly forecast and cash'!O5=1))="",FALSE,IF(ISERROR('Monthly forecast and cash'!O5=1),'Monthly forecast and cash'!O5=1,IF('Monthly forecast and cash'!O5="","",'Monthly forecast and cash'!O5=1))),IF('Editable assumptions'!B12="","",'Editable assumptions'!B12),IF('Monthly forecast and cash'!N7="","",'Monthly forecast and cash'!N7)))+'Monthly forecast and cash'!O6 -> 65 | P7: =IF(IF(IF(IF(ISERROR('Monthly forecast and cash'!P5=1),'Monthly forecast and cash'!P5=1,IF('Monthly forecast and cash'!P5="","",'Monthly forecast and cash'!P5=1))="",FALSE,IF(ISERROR('Monthly forecast and cash'!P5=1),'Monthly forecast and cash'!P5=1,IF('Monthly forecast and cash'!P5="","",'Monthly forecast and cash'!P5=1))),IF('Editable assumptions'!B12="","",'Editable assumptions'!B12),IF('Monthly forecast and cash'!O7="","",'Monthly forecast and cash'!O7))="",0,IF(IF(IF(ISERROR('Monthly forecast and cash'!P5=1),'Monthly forecast and cash'!P5=1,IF('Monthly forecast and cash'!P5="","",'Monthly forecast and cash'!P5=1))="",FALSE,IF(ISERROR('Monthly forecast and cash'!P5=1),'Monthly forecast and cash'!P5=1,IF('Monthly forecast and cash'!P5="","",'Monthly forecast and cash'!P5=1))),IF('Editable assumptions'!B12="","",'Editable assumptions'!B12),IF('Monthly forecast and cash'!O7="","",'Monthly forecast and cash'!O7)))+'Monthly forecast and cash'!P6 -> 70 | Q7: =IF(IF(IF(IF(ISERROR('Monthly forecast and cash'!Q5=1),'Monthly forecast and cash'!Q5=1,IF('Monthly forecast and cash'!Q5="","",'Monthly forecast and cash'!Q5=1))="",FALSE,IF(ISERROR('Monthly forecast and cash'!Q5=1),'Monthly forecast and cash'!Q5=1,IF('Monthly forecast and cash'!Q5="","",'Monthly forecast and cash'!Q5=1))),IF('Editable assumptions'!B12="","",'Editable assumptions'!B12),IF('Monthly forecast and cash'!P7="","",'Monthly forecast and cash'!P7))="",0,IF(IF(IF(ISERROR('Monthly forecast and cash'!Q5=1),'Monthly forecast and cash'!Q5=1,IF('Monthly forecast and cash'!Q5="","",'Monthly forecast and cash'!Q5=1))="",FALSE,IF(ISERROR('Monthly forecast and cash'!Q5=1),'Monthly forecast and cash'!Q5=1,IF('Monthly forecast and cash'!Q5="","",'Monthly forecast and cash'!Q5=1))),IF('Editable assumptions'!B12="","",'Editable assumptions'!B12),IF('Monthly forecast and cash'!P7="","",'Monthly forecast and cash'!P7)))+'Monthly forecast and cash'!Q6 -> 75 | R7: =IF(IF(IF(IF(ISERROR('Monthly forecast and cash'!R5=1),'Monthly forecast and cash'!R5=1,IF('Monthly forecast and cash'!R5="","",'Monthly forecast and cash'!R5=1))="",FALSE,IF(ISERROR('Monthly forecast and cash'!R5=1),'Monthly forecast and cash'!R5=1,IF('Monthly forecast and cash'!R5="","",'Monthly forecast and cash'!R5=1))),IF('Editable assumptions'!B12="","",'Editable assumptions'!B12),IF('Monthly forecast and cash'!Q7="","",'Monthly forecast and cash'!Q7))="",0,IF(IF(IF(ISERROR('Monthly forecast and cash'!R5=1),'Monthly forecast and cash'!R5=1,IF('Monthly forecast and cash'!R5="","",'Monthly forecast and cash'!R5=1))="",FALSE,IF(ISERROR('Monthly forecast and cash'!R5=1),'Monthly forecast and cash'!R5=1,IF('Monthly forecast and cash'!R5="","",'Monthly forecast and cash'!R5=1))),IF('Editable assumptions'!B12="","",'Editable assumptions'!B12),IF('Monthly forecast and cash'!Q7="","",'Monthly forecast and cash'!Q7)))+'Monthly forecast and cash'!R6 -> 80 | S7: =IF(IF(IF(IF(ISERROR('Monthly forecast and cash'!S5=1),'Monthly forecast and cash'!S5=1,IF('Monthly forecast and cash'!S5="","",'Monthly forecast and cash'!S5=1))="",FALSE,IF(ISERROR('Monthly forecast and cash'!S5=1),'Monthly forecast and cash'!S5=1,IF('Monthly forecast and cash'!S5="","",'Monthly forecast and cash'!S5=1))),IF('Editable assumptions'!B12="","",'Editable assumptions'!B12),IF('Monthly forecast and cash'!R7="","",'Monthly forecast and cash'!R7))="",0,IF(IF(IF(ISERROR('Monthly forecast and cash'!S5=1),'Monthly forecast and cash'!S5=1,IF('Monthly forecast and cash'!S5="","",'Monthly forecast and cash'!S5=1))="",FALSE,IF(ISERROR('Monthly forecast and cash'!S5=1),'Monthly forecast and cash'!S5=1,IF('Monthly forecast and cash'!S5="","",'Monthly forecast and cash'!S5=1))),IF('Editable assumptions'!B12="","",'Editable assumptions'!B12),IF('Monthly forecast and cash'!R7="","",'Monthly forecast and cash'!R7)))+'Monthly forecast and cash'!S6 -> 85 | T7: =IF(IF(IF(IF(ISERROR('Monthly forecast and cash'!T5=1),'Monthly forecast and cash'!T5=1,IF('Monthly forecast and cash'!T5="","",'Monthly forecast and cash'!T5=1))="",FALSE,IF(ISERROR('Monthly forecast and cash'!T5=1),'Monthly forecast and cash'!T5=1,IF('Monthly forecast and cash'!T5="","",'Monthly forecast and cash'!T5=1))),IF('Editable assumptions'!B12="","",'Editable assumptions'!B12),IF('Monthly forecast and cash'!S7="","",'Monthly forecast and cash'!S7))="",0,IF(IF(IF(ISERROR('Monthly forecast and cash'!T5=1),'Monthly forecast and cash'!T5=1,IF('Monthly forecast and cash'!T5="","",'Monthly forecast and cash'!T5=1))="",FALSE,IF(ISERROR('Monthly forecast and cash'!T5=1),'Monthly forecast and cash'!T5=1,IF('Monthly forecast and cash'!T5="","",'Monthly forecast and cash'!T5=1))),IF('Editable assumptions'!B12="","",'Editable assumptions'!B12),IF('Monthly forecast and cash'!S7="","",'Monthly forecast and cash'!S7)))+'Monthly forecast and cash'!T6 -> 90 | U7: =IF(IF(IF(IF(ISERROR('Monthly forecast and cash'!U5=1),'Monthly forecast and cash'!U5=1,IF('Monthly forecast and cash'!U5="","",'Monthly forecast and cash'!U5=1))="",FALSE,IF(ISERROR('Monthly forecast and cash'!U5=1),'Monthly forecast and cash'!U5=1,IF('Monthly forecast and cash'!U5="","",'Monthly forecast and cash'!U5=1))),IF('Editable assumptions'!B12="","",'Editable assumptions'!B12),IF('Monthly forecast and cash'!T7="","",'Monthly forecast and cash'!T7))="",0,IF(IF(IF(ISERROR('Monthly forecast and cash'!U5=1),'Monthly forecast and cash'!U5=1,IF('Monthly forecast and cash'!U5="","",'Monthly forecast and cash'!U5=1))="",FALSE,IF(ISERROR('Monthly forecast and cash'!U5=1),'Monthly forecast and cash'!U5=1,IF('Monthly forecast and cash'!U5="","",'Monthly forecast and cash'!U5=1))),IF('Editable assumptions'!B12="","",'Editable assumptions'!B12),IF('Monthly forecast and cash'!T7="","",'Monthly forecast and cash'!T7)))+'Monthly forecast and cash'!U6 -> 95 | V7: =IF(IF(IF(IF(ISERROR('Monthly forecast and cash'!V5=1),'Monthly forecast and cash'!V5=1,IF('Monthly forecast and cash'!V5="","",'Monthly forecast and cash'!V5=1))="",FALSE,IF(ISERROR('Monthly forecast and cash'!V5=1),'Monthly forecast and cash'!V5=1,IF('Monthly forecast and cash'!V5="","",'Monthly forecast and cash'!V5=1))),IF('Editable assumptions'!B12="","",'Editable assumptions'!B12),IF('Monthly forecast and cash'!U7="","",'Monthly forecast and cash'!U7))="",0,IF(IF(IF(ISERROR('Monthly forecast and cash'!V5=1),'Monthly forecast and cash'!V5=1,IF('Monthly forecast and cash'!V5="","",'Monthly forecast and cash'!V5=1))="",FALSE,IF(ISERROR('Monthly forecast and cash'!V5=1),'Monthly forecast and cash'!V5=1,IF('Monthly forecast and cash'!V5="","",'Monthly forecast and cash'!V5=1))),IF('Editable assumptions'!B12="","",'Editable assumptions'!B12),IF('Monthly forecast and cash'!U7="","",'Monthly forecast and cash'!U7)))+'Monthly forecast and cash'!V6 -> 100 | W7: =IF(IF(IF(IF(ISERROR('Monthly forecast and cash'!W5=1),'Monthly forecast and cash'!W5=1,IF('Monthly forecast and cash'!W5="","",'Monthly forecast and cash'!W5=1))="",FALSE,IF(ISERROR('Monthly forecast and cash'!W5=1),'Monthly forecast and cash'!W5=1,IF('Monthly forecast and cash'!W5="","",'Monthly forecast and cash'!W5=1))),IF('Editable assumptions'!B12="","",'Editable assumptions'!B12),IF('Monthly forecast and cash'!V7="","",'Monthly forecast and cash'!V7))="",0,IF(IF(IF(ISERROR('Monthly forecast and cash'!W5=1),'Monthly forecast and cash'!W5=1,IF('Monthly forecast and cash'!W5="","",'Monthly forecast and cash'!W5=1))="",FALSE,IF(ISERROR('Monthly forecast and cash'!W5=1),'Monthly forecast and cash'!W5=1,IF('Monthly forecast and cash'!W5="","",'Monthly forecast and cash'!W5=1))),IF('Editable assumptions'!B12="","",'Editable assumptions'!B12),IF('Monthly forecast and cash'!V7="","",'Monthly forecast and cash'!V7)))+'Monthly forecast and cash'!W6 -> 105 | X7: =IF(IF(IF(IF(ISERROR('Monthly forecast and cash'!X5=1),'Monthly forecast and cash'!X5=1,IF('Monthly forecast and cash'!X5="","",'Monthly forecast and cash'!X5=1))="",FALSE,IF(ISERROR('Monthly forecast and cash'!X5=1),'Monthly forecast and cash'!X5=1,IF('Monthly forecast and cash'!X5="","",'Monthly forecast and cash'!X5=1))),IF('Editable assumptions'!B12="","",'Editable assumptions'!B12),IF('Monthly forecast and cash'!W7="","",'Monthly forecast and cash'!W7))="",0,IF(IF(IF(ISERROR('Monthly forecast and cash'!X5=1),'Monthly forecast and cash'!X5=1,IF('Monthly forecast and cash'!X5="","",'Monthly forecast and cash'!X5=1))="",FALSE,IF(ISERROR('Monthly forecast and cash'!X5=1),'Monthly forecast and cash'!X5=1,IF('Monthly forecast and cash'!X5="","",'Monthly forecast and cash'!X5=1))),IF('Editable assumptions'!B12="","",'Editable assumptions'!B12),IF('Monthly forecast and cash'!W7="","",'Monthly forecast and cash'!W7)))+'Monthly forecast and cash'!X6 -> 110 | Y7: =IF(IF(IF(IF(ISERROR('Monthly forecast and cash'!Y5=1),'Monthly forecast and cash'!Y5=1,IF('Monthly forecast and cash'!Y5="","",'Monthly forecast and cash'!Y5=1))="",FALSE,IF(ISERROR('Monthly forecast and cash'!Y5=1),'Monthly forecast and cash'!Y5=1,IF('Monthly forecast and cash'!Y5="","",'Monthly forecast and cash'!Y5=1))),IF('Editable assumptions'!B12="","",'Editable assumptions'!B12),IF('Monthly forecast and cash'!X7="","",'Monthly forecast and cash'!X7))="",0,IF(IF(IF(ISERROR('Monthly forecast and cash'!Y5=1),'Monthly forecast and cash'!Y5=1,IF('Monthly forecast and cash'!Y5="","",'Monthly forecast and cash'!Y5=1))="",FALSE,IF(ISERROR('Monthly forecast and cash'!Y5=1),'Monthly forecast and cash'!Y5=1,IF('Monthly forecast and cash'!Y5="","",'Monthly forecast and cash'!Y5=1))),IF('Editable assumptions'!B12="","",'Editable assumptions'!B12),IF('Monthly forecast and cash'!X7="","",'Monthly forecast and cash'!X7)))+'Monthly forecast and cash'!Y6 -> 115 | Z7: =IF(IF(IF(IF(ISERROR('Monthly forecast and cash'!Z5=1),'Monthly forecast and cash'!Z5=1,IF('Monthly forecast and cash'!Z5="","",'Monthly forecast and cash'!Z5=1))="",FALSE,IF(ISERROR('Monthly forecast and cash'!Z5=1),'Monthly forecast and cash'!Z5=1,IF('Monthly forecast and cash'!Z5="","",'Monthly forecast and cash'!Z5=1))),IF('Editable assumptions'!B12="","",'Editable assumptions'!B12),IF('Monthly forecast and cash'!Y7="","",'Monthly forecast and cash'!Y7))="",0,IF(IF(IF(ISERROR('Monthly forecast and cash'!Z5=1),'Monthly forecast and cash'!Z5=1,IF('Monthly forecast and cash'!Z5="","",'Monthly forecast and cash'!Z5=1))="",FALSE,IF(ISERROR('Monthly forecast and cash'!Z5=1),'Monthly forecast and cash'!Z5=1,IF('Monthly forecast and cash'!Z5="","",'Monthly forecast and cash'!Z5=1))),IF('Editable assumptions'!B12="","",'Editable assumptions'!B12),IF('Monthly forecast and cash'!Y7="","",'Monthly forecast and cash'!Y7)))+'Monthly forecast and cash'!Z6 -> 120
A8: Active free repos | B8: 0 | C8: =IF('Editable assumptions'!B14="","",'Editable assumptions'!B14) -> 50 | D8: =IF('Editable assumptions'!B14="","",'Editable assumptions'!B14) -> 50 | E8: =IF('Editable assumptions'!B14="","",'Editable assumptions'!B14) -> 50 | F8: =IF('Editable assumptions'!B14="","",'Editable assumptions'!B14) -> 50 | G8: =IF('Editable assumptions'!B14="","",'Editable assumptions'!B14) -> 50 | H8: =IF('Editable assumptions'!B14="","",'Editable assumptions'!B14) -> 50 | I8: =IF('Editable assumptions'!B14="","",'Editable assumptions'!B14) -> 50 | J8: =IF('Editable assumptions'!B14="","",'Editable assumptions'!B14) -> 50 | K8: =IF('Editable assumptions'!B14="","",'Editable assumptions'!B14) -> 50 | L8: =IF('Editable assumptions'!B14="","",'Editable assumptions'!B14) -> 50 | M8: =IF('Editable assumptions'!B14="","",'Editable assumptions'!B14) -> 50 | N8: =IF('Editable assumptions'!B14="","",'Editable assumptions'!B14) -> 50 | O8: =IF('Editable assumptions'!B14="","",'Editable assumptions'!B14) -> 50 | P8: =IF('Editable assumptions'!B14="","",'Editable assumptions'!B14) -> 50 | Q8: =IF('Editable assumptions'!B14="","",'Editable assumptions'!B14) -> 50 | R8: =IF('Editable assumptions'!B14="","",'Editable assumptions'!B14) -> 50 | S8: =IF('Editable assumptions'!B14="","",'Editable assumptions'!B14) -> 50 | T8: =IF('Editable assumptions'!B14="","",'Editable assumptions'!B14) -> 50 | U8: =IF('Editable assumptions'!B14="","",'Editable assumptions'!B14) -> 50 | V8: =IF('Editable assumptions'!B14="","",'Editable assumptions'!B14) -> 50 | W8: =IF('Editable assumptions'!B14="","",'Editable assumptions'!B14) -> 50 | X8: =IF('Editable assumptions'!B14="","",'Editable assumptions'!B14) -> 50 | Y8: =IF('Editable assumptions'!B14="","",'Editable assumptions'!B14) -> 50 | Z8: =IF('Editable assumptions'!B14="","",'Editable assumptions'!B14) -> 50
A9: Investigations | B9: =SUM('Monthly forecast and cash'!B10,'Monthly forecast and cash'!B11) -> 0 | C9: =SUM('Monthly forecast and cash'!C10,'Monthly forecast and cash'!C11) -> 800 | D9: =SUM('Monthly forecast and cash'!D10,'Monthly forecast and cash'!D11) -> 1100 | E9: =SUM('Monthly forecast and cash'!E10,'Monthly forecast and cash'!E11) -> 1400 | F9: =SUM('Monthly forecast and cash'!F10,'Monthly forecast and cash'!F11) -> 1700 | G9: =SUM('Monthly forecast and cash'!G10,'Monthly forecast and cash'!G11) -> 2000 | H9: =SUM('Monthly forecast and cash'!H10,'Monthly forecast and cash'!H11) -> 2300 | I9: =SUM('Monthly forecast and cash'!I10,'Monthly forecast and cash'!I11) -> 2600 | ... Z9: =SUM('Monthly forecast and cash'!Z10,'Monthly forecast and cash'!Z11) -> 7700
A10: Free | B10: =0 -> 0 | C10: =IF(IF(EXACT("Free","Team"),IF('Monthly forecast and cash'!C7="","",'Monthly forecast and cash'!C7),IF('Monthly forecast and cash'!C8="","",'Monthly forecast and cash'!C8))="",0,IF(EXACT("Free","Team"),IF('Monthly forecast and cash'!C7="","",'Monthly forecast and cash'!C7),IF('Monthly forecast and cash'!C8="","",'Monthly forecast and cash'!C8)))*'Unit economics by plan'!D5 -> 500 | D10: =IF(IF(EXACT("Free","Team"),IF('Monthly forecast and cash'!D7="","",'Monthly forecast and cash'!D7),IF('Monthly forecast and cash'!D8="","",'Monthly forecast and cash'!D8))="",0,IF(EXACT("Free","Team"),IF('Monthly forecast and cash'!D7="","",'Monthly forecast and cash'!D7),IF('Monthly forecast and cash'!D8="","",'Monthly forecast and cash'!D8)))*'Unit economics by plan'!D5 -> 500 | E10: =IF(IF(EXACT("Free","Team"),IF('Monthly forecast and cash'!E7="","",'Monthly forecast and cash'!E7),IF('Monthly forecast and cash'!E8="","",'Monthly forecast and cash'!E8))="",0,IF(EXACT("Free","Team"),IF('Monthly forecast and cash'!E7="","",'Monthly forecast and cash'!E7),IF('Monthly forecast and cash'!E8="","",'Monthly forecast and cash'!E8)))*'Unit economics by plan'!D5 -> 500 | F10: =IF(IF(EXACT("Free","Team"),IF('Monthly forecast and cash'!F7="","",'Monthly forecast and cash'!F7),IF('Monthly forecast and cash'!F8="","",'Monthly forecast and cash'!F8))="",0,IF(EXACT("Free","Team"),IF('Monthly forecast and cash'!F7="","",'Monthly forecast and cash'!F7),IF('Monthly forecast and cash'!F8="","",'Monthly forecast and cash'!F8)))*'Unit economics by plan'!D5 -> 500 | G10: =IF(IF(EXACT("Free","Team"),IF('Monthly forecast and cash'!G7="","",'Monthly forecast and cash'!G7),IF('Monthly forecast and cash'!G8="","",'Monthly forecast and cash'!G8))="",0,IF(EXACT("Free","Team"),IF('Monthly forecast and cash'!G7="","",'Monthly forecast and cash'!G7),IF('Monthly forecast and cash'!G8="","",'Monthly forecast and cash'!G8)))*'Unit economics by plan'!D5 -> 500 | H10: =IF(IF(EXACT("Free","Team"),IF('Monthly forecast and cash'!H7="","",'Monthly forecast and cash'!H7),IF('Monthly forecast and cash'!H8="","",'Monthly forecast and cash'!H8))="",0,IF(EXACT("Free","Team"),IF('Monthly forecast and cash'!H7="","",'Monthly forecast and cash'!H7),IF('Monthly forecast and cash'!H8="","",'Monthly forecast and cash'!H8)))*'Unit economics by plan'!D5 -> 500 | I10: =IF(IF(EXACT("Free","Team"),IF('Monthly forecast and cash'!I7="","",'Monthly forecast and cash'!I7),IF('Monthly forecast and cash'!I8="","",'Monthly forecast and cash'!I8))="",0,IF(EXACT("Free","Team"),IF('Monthly forecast and cash'!I7="","",'Monthly forecast and cash'!I7),IF('Monthly forecast and cash'!I8="","",'Monthly forecast and cash'!I8)))*'Unit economics by plan'!D5 -> 500 | J10: =IF(IF(EXACT("Free","Team"),IF('Monthly forecast and cash'!J7="","",'Monthly forecast and cash'!J7),IF('Monthly forecast and cash'!J8="","",'Monthly forecast and cash'!J8))="",0,IF(EXACT("Free","Team"),IF('Monthly forecast and cash'!J7="","",'Monthly forecast and cash'!J7),IF('Monthly forecast and cash'!J8="","",'Monthly forecast and cash'!J8)))*'Unit economics by plan'!D5 -> 500 | K10: =IF(IF(EXACT("Free","Team"),IF('Monthly forecast and cash'!K7="","",'Monthly forecast and cash'!K7),IF('Monthly forecast and cash'!K8="","",'Monthly forecast and cash'!K8))="",0,IF(EXACT("Free","Team"),IF('Monthly forecast and cash'!K7="","",'Monthly forecast and cash'!K7),IF('Monthly forecast and cash'!K8="","",'Monthly forecast and cash'!K8)))*'Unit economics by plan'!D5 -> 500 | L10: =IF(IF(EXACT("Free","Team"),IF('Monthly forecast and cash'!L7="","",'Monthly forecast and cash'!L7),IF('Monthly forecast and cash'!L8="","",'Monthly forecast and cash'!L8))="",0,IF(EXACT("Free","Team"),IF('Monthly forecast and cash'!L7="","",'Monthly forecast and cash'!L7),IF('Monthly forecast and cash'!L8="","",'Monthly forecast and cash'!L8)))*'Unit economics by plan'!D5 -> 500 | M10: =IF(IF(EXACT("Free","Team"),IF('Monthly forecast and cash'!M7="","",'Monthly forecast and cash'!M7),IF('Monthly forecast and cash'!M8="","",'Monthly forecast and cash'!M8))="",0,IF(EXACT("Free","Team"),IF('Monthly forecast and cash'!M7="","",'Monthly forecast and cash'!M7),IF('Monthly forecast and cash'!M8="","",'Monthly forecast and cash'!M8)))*'Unit economics by plan'!D5 -> 500 | N10: =IF(IF(EXACT("Free","Team"),IF('Monthly forecast and cash'!N7="","",'Monthly forecast and cash'!N7),IF('Monthly forecast and cash'!N8="","",'Monthly forecast and cash'!N8))="",0,IF(EXACT("Free","Team"),IF('Monthly forecast and cash'!N7="","",'Monthly forecast and cash'!N7),IF('Monthly forecast and cash'!N8="","",'Monthly forecast and cash'!N8)))*'Unit economics by plan'!D5 -> 500 | O10: =IF(IF(EXACT("Free","Team"),IF('Monthly forecast and cash'!O7="","",'Monthly forecast and cash'!O7),IF('Monthly forecast and cash'!O8="","",'Monthly forecast and cash'!O8))="",0,IF(EXACT("Free","Team"),IF('Monthly forecast and cash'!O7="","",'Monthly forecast and cash'!O7),IF('Monthly forecast and cash'!O8="","",'Monthly forecast and cash'!O8)))*'Unit economics by plan'!D5 -> 500 | P10: =IF(IF(EXACT("Free","Team"),IF('Monthly forecast and cash'!P7="","",'Monthly forecast and cash'!P7),IF('Monthly forecast and cash'!P8="","",'Monthly forecast and cash'!P8))="",0,IF(EXACT("Free","Team"),IF('Monthly forecast and cash'!P7="","",'Monthly forecast and cash'!P7),IF('Monthly forecast and cash'!P8="","",'Monthly forecast and cash'!P8)))*'Unit economics by plan'!D5 -> 500 | Q10: =IF(IF(EXACT("Free","Team"),IF('Monthly forecast and cash'!Q7="","",'Monthly forecast and cash'!Q7),IF('Monthly forecast and cash'!Q8="","",'Monthly forecast and cash'!Q8))="",0,IF(EXACT("Free","Team"),IF('Monthly forecast and cash'!Q7="","",'Monthly forecast and cash'!Q7),IF('Monthly forecast and cash'!Q8="","",'Monthly forecast and cash'!Q8)))*'Unit economics by plan'!D5 -> 500 | R10: =IF(IF(EXACT("Free","Team"),IF('Monthly forecast and cash'!R7="","",'Monthly forecast and cash'!R7),IF('Monthly forecast and cash'!R8="","",'Monthly forecast and cash'!R8))="",0,IF(EXACT("Free","Team"),IF('Monthly forecast and cash'!R7="","",'Monthly forecast and cash'!R7),IF('Monthly forecast and cash'!R8="","",'Monthly forecast and cash'!R8)))*'Unit economics by plan'!D5 -> 500 | S10: =IF(IF(EXACT("Free","Team"),IF('Monthly forecast and cash'!S7="","",'Monthly forecast and cash'!S7),IF('Monthly forecast and cash'!S8="","",'Monthly forecast and cash'!S8))="",0,IF(EXACT("Free","Team"),IF('Monthly forecast and cash'!S7="","",'Monthly forecast and cash'!S7),IF('Monthly forecast and cash'!S8="","",'Monthly forecast and cash'!S8)))*'Unit economics by plan'!D5 -> 500 | T10: =IF(IF(EXACT("Free","Team"),IF('Monthly forecast and cash'!T7="","",'Monthly forecast and cash'!T7),IF('Monthly forecast and cash'!T8="","",'Monthly forecast and cash'!T8))="",0,IF(EXACT("Free","Team"),IF('Monthly forecast and cash'!T7="","",'Monthly forecast and cash'!T7),IF('Monthly forecast and cash'!T8="","",'Monthly forecast and cash'!T8)))*'Unit economics by plan'!D5 -> 500 | U10: =IF(IF(EXACT("Free","Team"),IF('Monthly forecast and cash'!U7="","",'Monthly forecast and cash'!U7),IF('Monthly forecast and cash'!U8="","",'Monthly forecast and cash'!U8))="",0,IF(EXACT("Free","Team"),IF('Monthly forecast and cash'!U7="","",'Monthly forecast and cash'!U7),IF('Monthly forecast and cash'!U8="","",'Monthly forecast and cash'!U8)))*'Unit economics by plan'!D5 -> 500 | V10: =IF(IF(EXACT("Free","Team"),IF('Monthly forecast and cash'!V7="","",'Monthly forecast and cash'!V7),IF('Monthly forecast and cash'!V8="","",'Monthly forecast and cash'!V8))="",0,IF(EXACT("Free","Team"),IF('Monthly forecast and cash'!V7="","",'Monthly forecast and cash'!V7),IF('Monthly forecast and cash'!V8="","",'Monthly forecast and cash'!V8)))*'Unit economics by plan'!D5 -> 500 | W10: =IF(IF(EXACT("Free","Team"),IF('Monthly forecast and cash'!W7="","",'Monthly forecast and cash'!W7),IF('Monthly forecast and cash'!W8="","",'Monthly forecast and cash'!W8))="",0,IF(EXACT("Free","Team"),IF('Monthly forecast and cash'!W7="","",'Monthly forecast and cash'!W7),IF('Monthly forecast and cash'!W8="","",'Monthly forecast and cash'!W8)))*'Unit economics by plan'!D5 -> 500 | X10: =IF(IF(EXACT("Free","Team"),IF('Monthly forecast and cash'!X7="","",'Monthly forecast and cash'!X7),IF('Monthly forecast and cash'!X8="","",'Monthly forecast and cash'!X8))="",0,IF(EXACT("Free","Team"),IF('Monthly forecast and cash'!X7="","",'Monthly forecast and cash'!X7),IF('Monthly forecast and cash'!X8="","",'Monthly forecast and cash'!X8)))*'Unit economics by plan'!D5 -> 500 | Y10: =IF(IF(EXACT("Free","Team"),IF('Monthly forecast and cash'!Y7="","",'Monthly forecast and cash'!Y7),IF('Monthly forecast and cash'!Y8="","",'Monthly forecast and cash'!Y8))="",0,IF(EXACT("Free","Team"),IF('Monthly forecast and cash'!Y7="","",'Monthly forecast and cash'!Y7),IF('Monthly forecast and cash'!Y8="","",'Monthly forecast and cash'!Y8)))*'Unit economics by plan'!D5 -> 500 | Z10: =IF(IF(EXACT("Free","Team"),IF('Monthly forecast and cash'!Z7="","",'Monthly forecast and cash'!Z7),IF('Monthly forecast and cash'!Z8="","",'Monthly forecast and cash'!Z8))="",0,IF(EXACT("Free","Team"),IF('Monthly forecast and cash'!Z7="","",'Monthly forecast and cash'!Z7),IF('Monthly forecast and cash'!Z8="","",'Monthly forecast and cash'!Z8)))*'Unit economics by plan'!D5 -> 500
A11: Team | B11: =0 -> 0 | C11: =IF(IF(EXACT("Team","Team"),IF('Monthly forecast and cash'!C7="","",'Monthly forecast and cash'!C7),IF('Monthly forecast and cash'!C8="","",'Monthly forecast and cash'!C8))="",0,IF(EXACT("Team","Team"),IF('Monthly forecast and cash'!C7="","",'Monthly forecast and cash'!C7),IF('Monthly forecast and cash'!C8="","",'Monthly forecast and cash'!C8)))*'Unit economics by plan'!D6 -> 300 | D11: =IF(IF(EXACT("Team","Team"),IF('Monthly forecast and cash'!D7="","",'Monthly forecast and cash'!D7),IF('Monthly forecast and cash'!D8="","",'Monthly forecast and cash'!D8))="",0,IF(EXACT("Team","Team"),IF('Monthly forecast and cash'!D7="","",'Monthly forecast and cash'!D7),IF('Monthly forecast and cash'!D8="","",'Monthly forecast and cash'!D8)))*'Unit economics by plan'!D6 -> 600 | E11: =IF(IF(EXACT("Team","Team"),IF('Monthly forecast and cash'!E7="","",'Monthly forecast and cash'!E7),IF('Monthly forecast and cash'!E8="","",'Monthly forecast and cash'!E8))="",0,IF(EXACT("Team","Team"),IF('Monthly forecast and cash'!E7="","",'Monthly forecast and cash'!E7),IF('Monthly forecast and cash'!E8="","",'Monthly forecast and cash'!E8)))*'Unit economics by plan'!D6 -> 900 | F11: =IF(IF(EXACT("Team","Team"),IF('Monthly forecast and cash'!F7="","",'Monthly forecast and cash'!F7),IF('Monthly forecast and cash'!F8="","",'Monthly forecast and cash'!F8))="",0,IF(EXACT("Team","Team"),IF('Monthly forecast and cash'!F7="","",'Monthly forecast and cash'!F7),IF('Monthly forecast and cash'!F8="","",'Monthly forecast and cash'!F8)))*'Unit economics by plan'!D6 -> 1200 | G11: =IF(IF(EXACT("Team","Team"),IF('Monthly forecast and cash'!G7="","",'Monthly forecast and cash'!G7),IF('Monthly forecast and cash'!G8="","",'Monthly forecast and cash'!G8))="",0,IF(EXACT("Team","Team"),IF('Monthly forecast and cash'!G7="","",'Monthly forecast and cash'!G7),IF('Monthly forecast and cash'!G8="","",'Monthly forecast and cash'!G8)))*'Unit economics by plan'!D6 -> 1500 | H11: =IF(IF(EXACT("Team","Team"),IF('Monthly forecast and cash'!H7="","",'Monthly forecast and cash'!H7),IF('Monthly forecast and cash'!H8="","",'Monthly forecast and cash'!H8))="",0,IF(EXACT("Team","Team"),IF('Monthly forecast and cash'!H7="","",'Monthly forecast and cash'!H7),IF('Monthly forecast and cash'!H8="","",'Monthly forecast and cash'!H8)))*'Unit economics by plan'!D6 -> 1800 | I11: =IF(IF(EXACT("Team","Team"),IF('Monthly forecast and cash'!I7="","",'Monthly forecast and cash'!I7),IF('Monthly forecast and cash'!I8="","",'Monthly forecast and cash'!I8))="",0,IF(EXACT("Team","Team"),IF('Monthly forecast and cash'!I7="","",'Monthly forecast and cash'!I7),IF('Monthly forecast and cash'!I8="","",'Monthly forecast and cash'!I8)))*'Unit economics by plan'!D6 -> 2100 | J11: =IF(IF(EXACT("Team","Team"),IF('Monthly forecast and cash'!J7="","",'Monthly forecast and cash'!J7),IF('Monthly forecast and cash'!J8="","",'Monthly forecast and cash'!J8))="",0,IF(EXACT("Team","Team"),IF('Monthly forecast and cash'!J7="","",'Monthly forecast and cash'!J7),IF('Monthly forecast and cash'!J8="","",'Monthly forecast and cash'!J8)))*'Unit economics by plan'!D6 -> 2400 | K11: =IF(IF(EXACT("Team","Team"),IF('Monthly forecast and cash'!K7="","",'Monthly forecast and cash'!K7),IF('Monthly forecast and cash'!K8="","",'Monthly forecast and cash'!K8))="",0,IF(EXACT("Team","Team"),IF('Monthly forecast and cash'!K7="","",'Monthly forecast and cash'!K7),IF('Monthly forecast and cash'!K8="","",'Monthly forecast and cash'!K8)))*'Unit economics by plan'!D6 -> 2700 | L11: =IF(IF(EXACT("Team","Team"),IF('Monthly forecast and cash'!L7="","",'Monthly forecast and cash'!L7),IF('Monthly forecast and cash'!L8="","",'Monthly forecast and cash'!L8))="",0,IF(EXACT("Team","Team"),IF('Monthly forecast and cash'!L7="","",'Monthly forecast and cash'!L7),IF('Monthly forecast and cash'!L8="","",'Monthly forecast and cash'!L8)))*'Unit economics by plan'!D6 -> 3000 | M11: =IF(IF(EXACT("Team","Team"),IF('Monthly forecast and cash'!M7="","",'Monthly forecast and cash'!M7),IF('Monthly forecast and cash'!M8="","",'Monthly forecast and cash'!M8))="",0,IF(EXACT("Team","Team"),IF('Monthly forecast and cash'!M7="","",'Monthly forecast and cash'!M7),IF('Monthly forecast and cash'!M8="","",'Monthly forecast and cash'!M8)))*'Unit economics by plan'!D6 -> 3300 | N11: =IF(IF(EXACT("Team","Team"),IF('Monthly forecast and cash'!N7="","",'Monthly forecast and cash'!N7),IF('Monthly forecast and cash'!N8="","",'Monthly forecast and cash'!N8))="",0,IF(EXACT("Team","Team"),IF('Monthly forecast and cash'!N7="","",'Monthly forecast and cash'!N7),IF('Monthly forecast and cash'!N8="","",'Monthly forecast and cash'!N8)))*'Unit economics by plan'!D6 -> 3600 | O11: =IF(IF(EXACT("Team","Team"),IF('Monthly forecast and cash'!O7="","",'Monthly forecast and cash'!O7),IF('Monthly forecast and cash'!O8="","",'Monthly forecast and cash'!O8))="",0,IF(EXACT("Team","Team"),IF('Monthly forecast and cash'!O7="","",'Monthly forecast and cash'!O7),IF('Monthly forecast and cash'!O8="","",'Monthly forecast and cash'!O8)))*'Unit economics by plan'!D6 -> 3900 | P11: =IF(IF(EXACT("Team","Team"),IF('Monthly forecast and cash'!P7="","",'Monthly forecast and cash'!P7),IF('Monthly forecast and cash'!P8="","",'Monthly forecast and cash'!P8))="",0,IF(EXACT("Team","Team"),IF('Monthly forecast and cash'!P7="","",'Monthly forecast and cash'!P7),IF('Monthly forecast and cash'!P8="","",'Monthly forecast and cash'!P8)))*'Unit economics by plan'!D6 -> 4200 | Q11: =IF(IF(EXACT("Team","Team"),IF('Monthly forecast and cash'!Q7="","",'Monthly forecast and cash'!Q7),IF('Monthly forecast and cash'!Q8="","",'Monthly forecast and cash'!Q8))="",0,IF(EXACT("Team","Team"),IF('Monthly forecast and cash'!Q7="","",'Monthly forecast and cash'!Q7),IF('Monthly forecast and cash'!Q8="","",'Monthly forecast and cash'!Q8)))*'Unit economics by plan'!D6 -> 4500 | R11: =IF(IF(EXACT("Team","Team"),IF('Monthly forecast and cash'!R7="","",'Monthly forecast and cash'!R7),IF('Monthly forecast and cash'!R8="","",'Monthly forecast and cash'!R8))="",0,IF(EXACT("Team","Team"),IF('Monthly forecast and cash'!R7="","",'Monthly forecast and cash'!R7),IF('Monthly forecast and cash'!R8="","",'Monthly forecast and cash'!R8)))*'Unit economics by plan'!D6 -> 4800 | S11: =IF(IF(EXACT("Team","Team"),IF('Monthly forecast and cash'!S7="","",'Monthly forecast and cash'!S7),IF('Monthly forecast and cash'!S8="","",'Monthly forecast and cash'!S8))="",0,IF(EXACT("Team","Team"),IF('Monthly forecast and cash'!S7="","",'Monthly forecast and cash'!S7),IF('Monthly forecast and cash'!S8="","",'Monthly forecast and cash'!S8)))*'Unit economics by plan'!D6 -> 5100 | T11: =IF(IF(EXACT("Team","Team"),IF('Monthly forecast and cash'!T7="","",'Monthly forecast and cash'!T7),IF('Monthly forecast and cash'!T8="","",'Monthly forecast and cash'!T8))="",0,IF(EXACT("Team","Team"),IF('Monthly forecast and cash'!T7="","",'Monthly forecast and cash'!T7),IF('Monthly forecast and cash'!T8="","",'Monthly forecast and cash'!T8)))*'Unit economics by plan'!D6 -> 5400 | U11: =IF(IF(EXACT("Team","Team"),IF('Monthly forecast and cash'!U7="","",'Monthly forecast and cash'!U7),IF('Monthly forecast and cash'!U8="","",'Monthly forecast and cash'!U8))="",0,IF(EXACT("Team","Team"),IF('Monthly forecast and cash'!U7="","",'Monthly forecast and cash'!U7),IF('Monthly forecast and cash'!U8="","",'Monthly forecast and cash'!U8)))*'Unit economics by plan'!D6 -> 5700 | V11: =IF(IF(EXACT("Team","Team"),IF('Monthly forecast and cash'!V7="","",'Monthly forecast and cash'!V7),IF('Monthly forecast and cash'!V8="","",'Monthly forecast and cash'!V8))="",0,IF(EXACT("Team","Team"),IF('Monthly forecast and cash'!V7="","",'Monthly forecast and cash'!V7),IF('Monthly forecast and cash'!V8="","",'Monthly forecast and cash'!V8)))*'Unit economics by plan'!D6 -> 6000 | W11: =IF(IF(EXACT("Team","Team"),IF('Monthly forecast and cash'!W7="","",'Monthly forecast and cash'!W7),IF('Monthly forecast and cash'!W8="","",'Monthly forecast and cash'!W8))="",0,IF(EXACT("Team","Team"),IF('Monthly forecast and cash'!W7="","",'Monthly forecast and cash'!W7),IF('Monthly forecast and cash'!W8="","",'Monthly forecast and cash'!W8)))*'Unit economics by plan'!D6 -> 6300 | X11: =IF(IF(EXACT("Team","Team"),IF('Monthly forecast and cash'!X7="","",'Monthly forecast and cash'!X7),IF('Monthly forecast and cash'!X8="","",'Monthly forecast and cash'!X8))="",0,IF(EXACT("Team","Team"),IF('Monthly forecast and cash'!X7="","",'Monthly forecast and cash'!X7),IF('Monthly forecast and cash'!X8="","",'Monthly forecast and cash'!X8)))*'Unit economics by plan'!D6 -> 6600 | Y11: =IF(IF(EXACT("Team","Team"),IF('Monthly forecast and cash'!Y7="","",'Monthly forecast and cash'!Y7),IF('Monthly forecast and cash'!Y8="","",'Monthly forecast and cash'!Y8))="",0,IF(EXACT("Team","Team"),IF('Monthly forecast and cash'!Y7="","",'Monthly forecast and cash'!Y7),IF('Monthly forecast and cash'!Y8="","",'Monthly forecast and cash'!Y8)))*'Unit economics by plan'!D6 -> 6900 | Z11: =IF(IF(EXACT("Team","Team"),IF('Monthly forecast and cash'!Z7="","",'Monthly forecast and cash'!Z7),IF('Monthly forecast and cash'!Z8="","",'Monthly forecast and cash'!Z8))="",0,IF(EXACT("Team","Team"),IF('Monthly forecast and cash'!Z7="","",'Monthly forecast and cash'!Z7),IF('Monthly forecast and cash'!Z8="","",'Monthly forecast and cash'!Z8)))*'Unit economics by plan'!D6 -> 7200
A12: Revenue | B12: =SUM('Monthly forecast and cash'!B13,'Monthly forecast and cash'!B14) -> 0 | C12: =SUM('Monthly forecast and cash'!C13,'Monthly forecast and cash'!C14) -> 495 | D12: =SUM('Monthly forecast and cash'!D13,'Monthly forecast and cash'!D14) -> 990 | E12: =SUM('Monthly forecast and cash'!E13,'Monthly forecast and cash'!E14) -> 1485 | F12: =SUM('Monthly forecast and cash'!F13,'Monthly forecast and cash'!F14) -> 1980 | G12: =SUM('Monthly forecast and cash'!G13,'Monthly forecast and cash'!G14) -> 2475 | H12: =SUM('Monthly forecast and cash'!H13,'Monthly forecast and cash'!H14) -> 2970 | I12: =SUM('Monthly forecast and cash'!I13,'Monthly forecast and cash'!I14) -> 3465 | ... Z12: =SUM('Monthly forecast and cash'!Z13,'Monthly forecast and cash'!Z14) -> 11880
A13: Free | B13: =0 -> 0 | C13: =IF(IF(EXACT("Free","Team"),IF('Monthly forecast and cash'!C7="","",'Monthly forecast and cash'!C7),IF('Monthly forecast and cash'!C8="","",'Monthly forecast and cash'!C8))="",0,IF(EXACT("Free","Team"),IF('Monthly forecast and cash'!C7="","",'Monthly forecast and cash'!C7),IF('Monthly forecast and cash'!C8="","",'Monthly forecast and cash'!C8)))*'Unit economics by plan'!F5 -> 0 | D13: =IF(IF(EXACT("Free","Team"),IF('Monthly forecast and cash'!D7="","",'Monthly forecast and cash'!D7),IF('Monthly forecast and cash'!D8="","",'Monthly forecast and cash'!D8))="",0,IF(EXACT("Free","Team"),IF('Monthly forecast and cash'!D7="","",'Monthly forecast and cash'!D7),IF('Monthly forecast and cash'!D8="","",'Monthly forecast and cash'!D8)))*'Unit economics by plan'!F5 -> 0 | E13: =IF(IF(EXACT("Free","Team"),IF('Monthly forecast and cash'!E7="","",'Monthly forecast and cash'!E7),IF('Monthly forecast and cash'!E8="","",'Monthly forecast and cash'!E8))="",0,IF(EXACT("Free","Team"),IF('Monthly forecast and cash'!E7="","",'Monthly forecast and cash'!E7),IF('Monthly forecast and cash'!E8="","",'Monthly forecast and cash'!E8)))*'Unit economics by plan'!F5 -> 0 | F13: =IF(IF(EXACT("Free","Team"),IF('Monthly forecast and cash'!F7="","",'Monthly forecast and cash'!F7),IF('Monthly forecast and cash'!F8="","",'Monthly forecast and cash'!F8))="",0,IF(EXACT("Free","Team"),IF('Monthly forecast and cash'!F7="","",'Monthly forecast and cash'!F7),IF('Monthly forecast and cash'!F8="","",'Monthly forecast and cash'!F8)))*'Unit economics by plan'!F5 -> 0 | G13: =IF(IF(EXACT("Free","Team"),IF('Monthly forecast and cash'!G7="","",'Monthly forecast and cash'!G7),IF('Monthly forecast and cash'!G8="","",'Monthly forecast and cash'!G8))="",0,IF(EXACT("Free","Team"),IF('Monthly forecast and cash'!G7="","",'Monthly forecast and cash'!G7),IF('Monthly forecast and cash'!G8="","",'Monthly forecast and cash'!G8)))*'Unit economics by plan'!F5 -> 0 | H13: =IF(IF(EXACT("Free","Team"),IF('Monthly forecast and cash'!H7="","",'Monthly forecast and cash'!H7),IF('Monthly forecast and cash'!H8="","",'Monthly forecast and cash'!H8))="",0,IF(EXACT("Free","Team"),IF('Monthly forecast and cash'!H7="","",'Monthly forecast and cash'!H7),IF('Monthly forecast and cash'!H8="","",'Monthly forecast and cash'!H8)))*'Unit economics by plan'!F5 -> 0 | I13: =IF(IF(EXACT("Free","Team"),IF('Monthly forecast and cash'!I7="","",'Monthly forecast and cash'!I7),IF('Monthly forecast and cash'!I8="","",'Monthly forecast and cash'!I8))="",0,IF(EXACT("Free","Team"),IF('Monthly forecast and cash'!I7="","",'Monthly forecast and cash'!I7),IF('Monthly forecast and cash'!I8="","",'Monthly forecast and cash'!I8)))*'Unit economics by plan'!F5 -> 0 | J13: =IF(IF(EXACT("Free","Team"),IF('Monthly forecast and cash'!J7="","",'Monthly forecast and cash'!J7),IF('Monthly forecast and cash'!J8="","",'Monthly forecast and cash'!J8))="",0,IF(EXACT("Free","Team"),IF('Monthly forecast and cash'!J7="","",'Monthly forecast and cash'!J7),IF('Monthly forecast and cash'!J8="","",'Monthly forecast and cash'!J8)))*'Unit economics by plan'!F5 -> 0 | K13: =IF(IF(EXACT("Free","Team"),IF('Monthly forecast and cash'!K7="","",'Monthly forecast and cash'!K7),IF('Monthly forecast and cash'!K8="","",'Monthly forecast and cash'!K8))="",0,IF(EXACT("Free","Team"),IF('Monthly forecast and cash'!K7="","",'Monthly forecast and cash'!K7),IF('Monthly forecast and cash'!K8="","",'Monthly forecast and cash'!K8)))*'Unit economics by plan'!F5 -> 0 | L13: =IF(IF(EXACT("Free","Team"),IF('Monthly forecast and cash'!L7="","",'Monthly forecast and cash'!L7),IF('Monthly forecast and cash'!L8="","",'Monthly forecast and cash'!L8))="",0,IF(EXACT("Free","Team"),IF('Monthly forecast and cash'!L7="","",'Monthly forecast and cash'!L7),IF('Monthly forecast and cash'!L8="","",'Monthly forecast and cash'!L8)))*'Unit economics by plan'!F5 -> 0 | M13: =IF(IF(EXACT("Free","Team"),IF('Monthly forecast and cash'!M7="","",'Monthly forecast and cash'!M7),IF('Monthly forecast and cash'!M8="","",'Monthly forecast and cash'!M8))="",0,IF(EXACT("Free","Team"),IF('Monthly forecast and cash'!M7="","",'Monthly forecast and cash'!M7),IF('Monthly forecast and cash'!M8="","",'Monthly forecast and cash'!M8)))*'Unit economics by plan'!F5 -> 0 | N13: =IF(IF(EXACT("Free","Team"),IF('Monthly forecast and cash'!N7="","",'Monthly forecast and cash'!N7),IF('Monthly forecast and cash'!N8="","",'Monthly forecast and cash'!N8))="",0,IF(EXACT("Free","Team"),IF('Monthly forecast and cash'!N7="","",'Monthly forecast and cash'!N7),IF('Monthly forecast and cash'!N8="","",'Monthly forecast and cash'!N8)))*'Unit economics by plan'!F5 -> 0 | O13: =IF(IF(EXACT("Free","Team"),IF('Monthly forecast and cash'!O7="","",'Monthly forecast and cash'!O7),IF('Monthly forecast and cash'!O8="","",'Monthly forecast and cash'!O8))="",0,IF(EXACT("Free","Team"),IF('Monthly forecast and cash'!O7="","",'Monthly forecast and cash'!O7),IF('Monthly forecast and cash'!O8="","",'Monthly forecast and cash'!O8)))*'Unit economics by plan'!F5 -> 0 | P13: =IF(IF(EXACT("Free","Team"),IF('Monthly forecast and cash'!P7="","",'Monthly forecast and cash'!P7),IF('Monthly forecast and cash'!P8="","",'Monthly forecast and cash'!P8))="",0,IF(EXACT("Free","Team"),IF('Monthly forecast and cash'!P7="","",'Monthly forecast and cash'!P7),IF('Monthly forecast and cash'!P8="","",'Monthly forecast and cash'!P8)))*'Unit economics by plan'!F5 -> 0 | Q13: =IF(IF(EXACT("Free","Team"),IF('Monthly forecast and cash'!Q7="","",'Monthly forecast and cash'!Q7),IF('Monthly forecast and cash'!Q8="","",'Monthly forecast and cash'!Q8))="",0,IF(EXACT("Free","Team"),IF('Monthly forecast and cash'!Q7="","",'Monthly forecast and cash'!Q7),IF('Monthly forecast and cash'!Q8="","",'Monthly forecast and cash'!Q8)))*'Unit economics by plan'!F5 -> 0 | R13: =IF(IF(EXACT("Free","Team"),IF('Monthly forecast and cash'!R7="","",'Monthly forecast and cash'!R7),IF('Monthly forecast and cash'!R8="","",'Monthly forecast and cash'!R8))="",0,IF(EXACT("Free","Team"),IF('Monthly forecast and cash'!R7="","",'Monthly forecast and cash'!R7),IF('Monthly forecast and cash'!R8="","",'Monthly forecast and cash'!R8)))*'Unit economics by plan'!F5 -> 0 | S13: =IF(IF(EXACT("Free","Team"),IF('Monthly forecast and cash'!S7="","",'Monthly forecast and cash'!S7),IF('Monthly forecast and cash'!S8="","",'Monthly forecast and cash'!S8))="",0,IF(EXACT("Free","Team"),IF('Monthly forecast and cash'!S7="","",'Monthly forecast and cash'!S7),IF('Monthly forecast and cash'!S8="","",'Monthly forecast and cash'!S8)))*'Unit economics by plan'!F5 -> 0 | T13: =IF(IF(EXACT("Free","Team"),IF('Monthly forecast and cash'!T7="","",'Monthly forecast and cash'!T7),IF('Monthly forecast and cash'!T8="","",'Monthly forecast and cash'!T8))="",0,IF(EXACT("Free","Team"),IF('Monthly forecast and cash'!T7="","",'Monthly forecast and cash'!T7),IF('Monthly forecast and cash'!T8="","",'Monthly forecast and cash'!T8)))*'Unit economics by plan'!F5 -> 0 | U13: =IF(IF(EXACT("Free","Team"),IF('Monthly forecast and cash'!U7="","",'Monthly forecast and cash'!U7),IF('Monthly forecast and cash'!U8="","",'Monthly forecast and cash'!U8))="",0,IF(EXACT("Free","Team"),IF('Monthly forecast and cash'!U7="","",'Monthly forecast and cash'!U7),IF('Monthly forecast and cash'!U8="","",'Monthly forecast and cash'!U8)))*'Unit economics by plan'!F5 -> 0 | V13: =IF(IF(EXACT("Free","Team"),IF('Monthly forecast and cash'!V7="","",'Monthly forecast and cash'!V7),IF('Monthly forecast and cash'!V8="","",'Monthly forecast and cash'!V8))="",0,IF(EXACT("Free","Team"),IF('Monthly forecast and cash'!V7="","",'Monthly forecast and cash'!V7),IF('Monthly forecast and cash'!V8="","",'Monthly forecast and cash'!V8)))*'Unit economics by plan'!F5 -> 0 | W13: =IF(IF(EXACT("Free","Team"),IF('Monthly forecast and cash'!W7="","",'Monthly forecast and cash'!W7),IF('Monthly forecast and cash'!W8="","",'Monthly forecast and cash'!W8))="",0,IF(EXACT("Free","Team"),IF('Monthly forecast and cash'!W7="","",'Monthly forecast and cash'!W7),IF('Monthly forecast and cash'!W8="","",'Monthly forecast and cash'!W8)))*'Unit economics by plan'!F5 -> 0 | X13: =IF(IF(EXACT("Free","Team"),IF('Monthly forecast and cash'!X7="","",'Monthly forecast and cash'!X7),IF('Monthly forecast and cash'!X8="","",'Monthly forecast and cash'!X8))="",0,IF(EXACT("Free","Team"),IF('Monthly forecast and cash'!X7="","",'Monthly forecast and cash'!X7),IF('Monthly forecast and cash'!X8="","",'Monthly forecast and cash'!X8)))*'Unit economics by plan'!F5 -> 0 | Y13: =IF(IF(EXACT("Free","Team"),IF('Monthly forecast and cash'!Y7="","",'Monthly forecast and cash'!Y7),IF('Monthly forecast and cash'!Y8="","",'Monthly forecast and cash'!Y8))="",0,IF(EXACT("Free","Team"),IF('Monthly forecast and cash'!Y7="","",'Monthly forecast and cash'!Y7),IF('Monthly forecast and cash'!Y8="","",'Monthly forecast and cash'!Y8)))*'Unit economics by plan'!F5 -> 0 | Z13: =IF(IF(EXACT("Free","Team"),IF('Monthly forecast and cash'!Z7="","",'Monthly forecast and cash'!Z7),IF('Monthly forecast and cash'!Z8="","",'Monthly forecast and cash'!Z8))="",0,IF(EXACT("Free","Team"),IF('Monthly forecast and cash'!Z7="","",'Monthly forecast and cash'!Z7),IF('Monthly forecast and cash'!Z8="","",'Monthly forecast and cash'!Z8)))*'Unit economics by plan'!F5 -> 0
A14: Team | B14: =0 -> 0 | C14: =IF(IF(EXACT("Team","Team"),IF('Monthly forecast and cash'!C7="","",'Monthly forecast and cash'!C7),IF('Monthly forecast and cash'!C8="","",'Monthly forecast and cash'!C8))="",0,IF(EXACT("Team","Team"),IF('Monthly forecast and cash'!C7="","",'Monthly forecast and cash'!C7),IF('Monthly forecast and cash'!C8="","",'Monthly forecast and cash'!C8)))*'Unit economics by plan'!F6 -> 495 | D14: =IF(IF(EXACT("Team","Team"),IF('Monthly forecast and cash'!D7="","",'Monthly forecast and cash'!D7),IF('Monthly forecast and cash'!D8="","",'Monthly forecast and cash'!D8))="",0,IF(EXACT("Team","Team"),IF('Monthly forecast and cash'!D7="","",'Monthly forecast and cash'!D7),IF('Monthly forecast and cash'!D8="","",'Monthly forecast and cash'!D8)))*'Unit economics by plan'!F6 -> 990 | E14: =IF(IF(EXACT("Team","Team"),IF('Monthly forecast and cash'!E7="","",'Monthly forecast and cash'!E7),IF('Monthly forecast and cash'!E8="","",'Monthly forecast and cash'!E8))="",0,IF(EXACT("Team","Team"),IF('Monthly forecast and cash'!E7="","",'Monthly forecast and cash'!E7),IF('Monthly forecast and cash'!E8="","",'Monthly forecast and cash'!E8)))*'Unit economics by plan'!F6 -> 1485 | F14: =IF(IF(EXACT("Team","Team"),IF('Monthly forecast and cash'!F7="","",'Monthly forecast and cash'!F7),IF('Monthly forecast and cash'!F8="","",'Monthly forecast and cash'!F8))="",0,IF(EXACT("Team","Team"),IF('Monthly forecast and cash'!F7="","",'Monthly forecast and cash'!F7),IF('Monthly forecast and cash'!F8="","",'Monthly forecast and cash'!F8)))*'Unit economics by plan'!F6 -> 1980 | G14: =IF(IF(EXACT("Team","Team"),IF('Monthly forecast and cash'!G7="","",'Monthly forecast and cash'!G7),IF('Monthly forecast and cash'!G8="","",'Monthly forecast and cash'!G8))="",0,IF(EXACT("Team","Team"),IF('Monthly forecast and cash'!G7="","",'Monthly forecast and cash'!G7),IF('Monthly forecast and cash'!G8="","",'Monthly forecast and cash'!G8)))*'Unit economics by plan'!F6 -> 2475 | H14: =IF(IF(EXACT("Team","Team"),IF('Monthly forecast and cash'!H7="","",'Monthly forecast and cash'!H7),IF('Monthly forecast and cash'!H8="","",'Monthly forecast and cash'!H8))="",0,IF(EXACT("Team","Team"),IF('Monthly forecast and cash'!H7="","",'Monthly forecast and cash'!H7),IF('Monthly forecast and cash'!H8="","",'Monthly forecast and cash'!H8)))*'Unit economics by plan'!F6 -> 2970 | I14: =IF(IF(EXACT("Team","Team"),IF('Monthly forecast and cash'!I7="","",'Monthly forecast and cash'!I7),IF('Monthly forecast and cash'!I8="","",'Monthly forecast and cash'!I8))="",0,IF(EXACT("Team","Team"),IF('Monthly forecast and cash'!I7="","",'Monthly forecast and cash'!I7),IF('Monthly forecast and cash'!I8="","",'Monthly forecast and cash'!I8)))*'Unit economics by plan'!F6 -> 3465 | J14: =IF(IF(EXACT("Team","Team"),IF('Monthly forecast and cash'!J7="","",'Monthly forecast and cash'!J7),IF('Monthly forecast and cash'!J8="","",'Monthly forecast and cash'!J8))="",0,IF(EXACT("Team","Team"),IF('Monthly forecast and cash'!J7="","",'Monthly forecast and cash'!J7),IF('Monthly forecast and cash'!J8="","",'Monthly forecast and cash'!J8)))*'Unit economics by plan'!F6 -> 3960 | K14: =IF(IF(EXACT("Team","Team"),IF('Monthly forecast and cash'!K7="","",'Monthly forecast and cash'!K7),IF('Monthly forecast and cash'!K8="","",'Monthly forecast and cash'!K8))="",0,IF(EXACT("Team","Team"),IF('Monthly forecast and cash'!K7="","",'Monthly forecast and cash'!K7),IF('Monthly forecast and cash'!K8="","",'Monthly forecast and cash'!K8)))*'Unit economics by plan'!F6 -> 4455 | L14: =IF(IF(EXACT("Team","Team"),IF('Monthly forecast and cash'!L7="","",'Monthly forecast and cash'!L7),IF('Monthly forecast and cash'!L8="","",'Monthly forecast and cash'!L8))="",0,IF(EXACT("Team","Team"),IF('Monthly forecast and cash'!L7="","",'Monthly forecast and cash'!L7),IF('Monthly forecast and cash'!L8="","",'Monthly forecast and cash'!L8)))*'Unit economics by plan'!F6 -> 4950 | M14: =IF(IF(EXACT("Team","Team"),IF('Monthly forecast and cash'!M7="","",'Monthly forecast and cash'!M7),IF('Monthly forecast and cash'!M8="","",'Monthly forecast and cash'!M8))="",0,IF(EXACT("Team","Team"),IF('Monthly forecast and cash'!M7="","",'Monthly forecast and cash'!M7),IF('Monthly forecast and cash'!M8="","",'Monthly forecast and cash'!M8)))*'Unit economics by plan'!F6 -> 5445 | N14: =IF(IF(EXACT("Team","Team"),IF('Monthly forecast and cash'!N7="","",'Monthly forecast and cash'!N7),IF('Monthly forecast and cash'!N8="","",'Monthly forecast and cash'!N8))="",0,IF(EXACT("Team","Team"),IF('Monthly forecast and cash'!N7="","",'Monthly forecast and cash'!N7),IF('Monthly forecast and cash'!N8="","",'Monthly forecast and cash'!N8)))*'Unit economics by plan'!F6 -> 5940 | O14: =IF(IF(EXACT("Team","Team"),IF('Monthly forecast and cash'!O7="","",'Monthly forecast and cash'!O7),IF('Monthly forecast and cash'!O8="","",'Monthly forecast and cash'!O8))="",0,IF(EXACT("Team","Team"),IF('Monthly forecast and cash'!O7="","",'Monthly forecast and cash'!O7),IF('Monthly forecast and cash'!O8="","",'Monthly forecast and cash'!O8)))*'Unit economics by plan'!F6 -> 6435 | P14: =IF(IF(EXACT("Team","Team"),IF('Monthly forecast and cash'!P7="","",'Monthly forecast and cash'!P7),IF('Monthly forecast and cash'!P8="","",'Monthly forecast and cash'!P8))="",0,IF(EXACT("Team","Team"),IF('Monthly forecast and cash'!P7="","",'Monthly forecast and cash'!P7),IF('Monthly forecast and cash'!P8="","",'Monthly forecast and cash'!P8)))*'Unit economics by plan'!F6 -> 6930 | Q14: =IF(IF(EXACT("Team","Team"),IF('Monthly forecast and cash'!Q7="","",'Monthly forecast and cash'!Q7),IF('Monthly forecast and cash'!Q8="","",'Monthly forecast and cash'!Q8))="",0,IF(EXACT("Team","Team"),IF('Monthly forecast and cash'!Q7="","",'Monthly forecast and cash'!Q7),IF('Monthly forecast and cash'!Q8="","",'Monthly forecast and cash'!Q8)))*'Unit economics by plan'!F6 -> 7425 | R14: =IF(IF(EXACT("Team","Team"),IF('Monthly forecast and cash'!R7="","",'Monthly forecast and cash'!R7),IF('Monthly forecast and cash'!R8="","",'Monthly forecast and cash'!R8))="",0,IF(EXACT("Team","Team"),IF('Monthly forecast and cash'!R7="","",'Monthly forecast and cash'!R7),IF('Monthly forecast and cash'!R8="","",'Monthly forecast and cash'!R8)))*'Unit economics by plan'!F6 -> 7920 | S14: =IF(IF(EXACT("Team","Team"),IF('Monthly forecast and cash'!S7="","",'Monthly forecast and cash'!S7),IF('Monthly forecast and cash'!S8="","",'Monthly forecast and cash'!S8))="",0,IF(EXACT("Team","Team"),IF('Monthly forecast and cash'!S7="","",'Monthly forecast and cash'!S7),IF('Monthly forecast and cash'!S8="","",'Monthly forecast and cash'!S8)))*'Unit economics by plan'!F6 -> 8415 | T14: =IF(IF(EXACT("Team","Team"),IF('Monthly forecast and cash'!T7="","",'Monthly forecast and cash'!T7),IF('Monthly forecast and cash'!T8="","",'Monthly forecast and cash'!T8))="",0,IF(EXACT("Team","Team"),IF('Monthly forecast and cash'!T7="","",'Monthly forecast and cash'!T7),IF('Monthly forecast and cash'!T8="","",'Monthly forecast and cash'!T8)))*'Unit economics by plan'!F6 -> 8910 | U14: =IF(IF(EXACT("Team","Team"),IF('Monthly forecast and cash'!U7="","",'Monthly forecast and cash'!U7),IF('Monthly forecast and cash'!U8="","",'Monthly forecast and cash'!U8))="",0,IF(EXACT("Team","Team"),IF('Monthly forecast and cash'!U7="","",'Monthly forecast and cash'!U7),IF('Monthly forecast and cash'!U8="","",'Monthly forecast and cash'!U8)))*'Unit economics by plan'!F6 -> 9405 | V14: =IF(IF(EXACT("Team","Team"),IF('Monthly forecast and cash'!V7="","",'Monthly forecast and cash'!V7),IF('Monthly forecast and cash'!V8="","",'Monthly forecast and cash'!V8))="",0,IF(EXACT("Team","Team"),IF('Monthly forecast and cash'!V7="","",'Monthly forecast and cash'!V7),IF('Monthly forecast and cash'!V8="","",'Monthly forecast and cash'!V8)))*'Unit economics by plan'!F6 -> 9900 | W14: =IF(IF(EXACT("Team","Team"),IF('Monthly forecast and cash'!W7="","",'Monthly forecast and cash'!W7),IF('Monthly forecast and cash'!W8="","",'Monthly forecast and cash'!W8))="",0,IF(EXACT("Team","Team"),IF('Monthly forecast and cash'!W7="","",'Monthly forecast and cash'!W7),IF('Monthly forecast and cash'!W8="","",'Monthly forecast and cash'!W8)))*'Unit economics by plan'!F6 -> 10395 | X14: =IF(IF(EXACT("Team","Team"),IF('Monthly forecast and cash'!X7="","",'Monthly forecast and cash'!X7),IF('Monthly forecast and cash'!X8="","",'Monthly forecast and cash'!X8))="",0,IF(EXACT("Team","Team"),IF('Monthly forecast and cash'!X7="","",'Monthly forecast and cash'!X7),IF('Monthly forecast and cash'!X8="","",'Monthly forecast and cash'!X8)))*'Unit economics by plan'!F6 -> 10890 | Y14: =IF(IF(EXACT("Team","Team"),IF('Monthly forecast and cash'!Y7="","",'Monthly forecast and cash'!Y7),IF('Monthly forecast and cash'!Y8="","",'Monthly forecast and cash'!Y8))="",0,IF(EXACT("Team","Team"),IF('Monthly forecast and cash'!Y7="","",'Monthly forecast and cash'!Y7),IF('Monthly forecast and cash'!Y8="","",'Monthly forecast and cash'!Y8)))*'Unit economics by plan'!F6 -> 11385 | Z14: =IF(IF(EXACT("Team","Team"),IF('Monthly forecast and cash'!Z7="","",'Monthly forecast and cash'!Z7),IF('Monthly forecast and cash'!Z8="","",'Monthly forecast and cash'!Z8))="",0,IF(EXACT("Team","Team"),IF('Monthly forecast and cash'!Z7="","",'Monthly forecast and cash'!Z7),IF('Monthly forecast and cash'!Z8="","",'Monthly forecast and cash'!Z8)))*'Unit economics by plan'!F6 -> 11880
A15: Model spend | B15: =SUM('Monthly forecast and cash'!B16,'Monthly forecast and cash'!B17) -> 0 | C15: =SUM('Monthly forecast and cash'!C16,'Monthly forecast and cash'!C17) -> 200 | D15: =SUM('Monthly forecast and cash'!D16,'Monthly forecast and cash'!D17) -> 275 | E15: =SUM('Monthly forecast and cash'!E16,'Monthly forecast and cash'!E17) -> 350 | F15: =SUM('Monthly forecast and cash'!F16,'Monthly forecast and cash'!F17) -> 425 | G15: =SUM('Monthly forecast and cash'!G16,'Monthly forecast and cash'!G17) -> 500 | H15: =SUM('Monthly forecast and cash'!H16,'Monthly forecast and cash'!H17) -> 575 | I15: =SUM('Monthly forecast and cash'!I16,'Monthly forecast and cash'!I17) -> 650 | ... Z15: =SUM('Monthly forecast and cash'!Z16,'Monthly forecast and cash'!Z17) -> 1925
A16: Free | B16: =0 -> 0 | C16: ='Monthly forecast and cash'!C10*'Editable assumptions'!B5 -> 125 | D16: ='Monthly forecast and cash'!D10*'Editable assumptions'!B5 -> 125 | E16: ='Monthly forecast and cash'!E10*'Editable assumptions'!B5 -> 125 | F16: ='Monthly forecast and cash'!F10*'Editable assumptions'!B5 -> 125 | G16: ='Monthly forecast and cash'!G10*'Editable assumptions'!B5 -> 125 | H16: ='Monthly forecast and cash'!H10*'Editable assumptions'!B5 -> 125 | I16: ='Monthly forecast and cash'!I10*'Editable assumptions'!B5 -> 125 | J16: ='Monthly forecast and cash'!J10*'Editable assumptions'!B5 -> 125 | K16: ='Monthly forecast and cash'!K10*'Editable assumptions'!B5 -> 125 | L16: ='Monthly forecast and cash'!L10*'Editable assumptions'!B5 -> 125 | M16: ='Monthly forecast and cash'!M10*'Editable assumptions'!B5 -> 125 | N16: ='Monthly forecast and cash'!N10*'Editable assumptions'!B5 -> 125 | O16: ='Monthly forecast and cash'!O10*'Editable assumptions'!B5 -> 125 | P16: ='Monthly forecast and cash'!P10*'Editable assumptions'!B5 -> 125 | Q16: ='Monthly forecast and cash'!Q10*'Editable assumptions'!B5 -> 125 | R16: ='Monthly forecast and cash'!R10*'Editable assumptions'!B5 -> 125 | S16: ='Monthly forecast and cash'!S10*'Editable assumptions'!B5 -> 125 | T16: ='Monthly forecast and cash'!T10*'Editable assumptions'!B5 -> 125 | U16: ='Monthly forecast and cash'!U10*'Editable assumptions'!B5 -> 125 | V16: ='Monthly forecast and cash'!V10*'Editable assumptions'!B5 -> 125 | W16: ='Monthly forecast and cash'!W10*'Editable assumptions'!B5 -> 125 | X16: ='Monthly forecast and cash'!X10*'Editable assumptions'!B5 -> 125 | Y16: ='Monthly forecast and cash'!Y10*'Editable assumptions'!B5 -> 125 | Z16: ='Monthly forecast and cash'!Z10*'Editable assumptions'!B5 -> 125
A17: Team | B17: =0 -> 0 | C17: ='Monthly forecast and cash'!C11*'Editable assumptions'!B5 -> 75 | D17: ='Monthly forecast and cash'!D11*'Editable assumptions'!B5 -> 150 | E17: ='Monthly forecast and cash'!E11*'Editable assumptions'!B5 -> 225 | F17: ='Monthly forecast and cash'!F11*'Editable assumptions'!B5 -> 300 | G17: ='Monthly forecast and cash'!G11*'Editable assumptions'!B5 -> 375 | H17: ='Monthly forecast and cash'!H11*'Editable assumptions'!B5 -> 450 | I17: ='Monthly forecast and cash'!I11*'Editable assumptions'!B5 -> 525 | J17: ='Monthly forecast and cash'!J11*'Editable assumptions'!B5 -> 600 | K17: ='Monthly forecast and cash'!K11*'Editable assumptions'!B5 -> 675 | L17: ='Monthly forecast and cash'!L11*'Editable assumptions'!B5 -> 750 | M17: ='Monthly forecast and cash'!M11*'Editable assumptions'!B5 -> 825 | N17: ='Monthly forecast and cash'!N11*'Editable assumptions'!B5 -> 900 | O17: ='Monthly forecast and cash'!O11*'Editable assumptions'!B5 -> 975 | P17: ='Monthly forecast and cash'!P11*'Editable assumptions'!B5 -> 1050 | Q17: ='Monthly forecast and cash'!Q11*'Editable assumptions'!B5 -> 1125 | R17: ='Monthly forecast and cash'!R11*'Editable assumptions'!B5 -> 1200 | S17: ='Monthly forecast and cash'!S11*'Editable assumptions'!B5 -> 1275 | T17: ='Monthly forecast and cash'!T11*'Editable assumptions'!B5 -> 1350 | U17: ='Monthly forecast and cash'!U11*'Editable assumptions'!B5 -> 1425 | V17: ='Monthly forecast and cash'!V11*'Editable assumptions'!B5 -> 1500 | W17: ='Monthly forecast and cash'!W11*'Editable assumptions'!B5 -> 1575 | X17: ='Monthly forecast and cash'!X11*'Editable assumptions'!B5 -> 1650 | Y17: ='Monthly forecast and cash'!Y11*'Editable assumptions'!B5 -> 1725 | Z17: ='Monthly forecast and cash'!Z11*'Editable assumptions'!B5 -> 1800
A18: Compute spend | B18: =SUM('Monthly forecast and cash'!B19,'Monthly forecast and cash'!B20) -> 0 | C18: =SUM('Monthly forecast and cash'!C19,'Monthly forecast and cash'!C20) -> 40 | D18: =SUM('Monthly forecast and cash'!D19,'Monthly forecast and cash'!D20) -> 55 | E18: =SUM('Monthly forecast and cash'!E19,'Monthly forecast and cash'!E20) -> 70 | F18: =SUM('Monthly forecast and cash'!F19,'Monthly forecast and cash'!F20) -> 85 | G18: =SUM('Monthly forecast and cash'!G19,'Monthly forecast and cash'!G20) -> 100 | H18: =SUM('Monthly forecast and cash'!H19,'Monthly forecast and cash'!H20) -> 115 | I18: =SUM('Monthly forecast and cash'!I19,'Monthly forecast and cash'!I20) -> 130 | ... Z18: =SUM('Monthly forecast and cash'!Z19,'Monthly forecast and cash'!Z20) -> 385
A19: Free | B19: =0 -> 0 | C19: ='Monthly forecast and cash'!C10*'Editable assumptions'!B6 -> 25 | D19: ='Monthly forecast and cash'!D10*'Editable assumptions'!B6 -> 25 | E19: ='Monthly forecast and cash'!E10*'Editable assumptions'!B6 -> 25 | F19: ='Monthly forecast and cash'!F10*'Editable assumptions'!B6 -> 25 | G19: ='Monthly forecast and cash'!G10*'Editable assumptions'!B6 -> 25 | H19: ='Monthly forecast and cash'!H10*'Editable assumptions'!B6 -> 25 | I19: ='Monthly forecast and cash'!I10*'Editable assumptions'!B6 -> 25 | J19: ='Monthly forecast and cash'!J10*'Editable assumptions'!B6 -> 25 | K19: ='Monthly forecast and cash'!K10*'Editable assumptions'!B6 -> 25 | L19: ='Monthly forecast and cash'!L10*'Editable assumptions'!B6 -> 25 | M19: ='Monthly forecast and cash'!M10*'Editable assumptions'!B6 -> 25 | N19: ='Monthly forecast and cash'!N10*'Editable assumptions'!B6 -> 25 | O19: ='Monthly forecast and cash'!O10*'Editable assumptions'!B6 -> 25 | P19: ='Monthly forecast and cash'!P10*'Editable assumptions'!B6 -> 25 | Q19: ='Monthly forecast and cash'!Q10*'Editable assumptions'!B6 -> 25 | R19: ='Monthly forecast and cash'!R10*'Editable assumptions'!B6 -> 25 | S19: ='Monthly forecast and cash'!S10*'Editable assumptions'!B6 -> 25 | T19: ='Monthly forecast and cash'!T10*'Editable assumptions'!B6 -> 25 | U19: ='Monthly forecast and cash'!U10*'Editable assumptions'!B6 -> 25 | V19: ='Monthly forecast and cash'!V10*'Editable assumptions'!B6 -> 25 | W19: ='Monthly forecast and cash'!W10*'Editable assumptions'!B6 -> 25 | X19: ='Monthly forecast and cash'!X10*'Editable assumptions'!B6 -> 25 | Y19: ='Monthly forecast and cash'!Y10*'Editable assumptions'!B6 -> 25 | Z19: ='Monthly forecast and cash'!Z10*'Editable assumptions'!B6 -> 25
A20: Team | B20: =0 -> 0 | C20: ='Monthly forecast and cash'!C11*'Editable assumptions'!B6 -> 15 | D20: ='Monthly forecast and cash'!D11*'Editable assumptions'!B6 -> 30 | E20: ='Monthly forecast and cash'!E11*'Editable assumptions'!B6 -> 45 | F20: ='Monthly forecast and cash'!F11*'Editable assumptions'!B6 -> 60 | G20: ='Monthly forecast and cash'!G11*'Editable assumptions'!B6 -> 75 | H20: ='Monthly forecast and cash'!H11*'Editable assumptions'!B6 -> 90 | I20: ='Monthly forecast and cash'!I11*'Editable assumptions'!B6 -> 105 | J20: ='Monthly forecast and cash'!J11*'Editable assumptions'!B6 -> 120 | K20: ='Monthly forecast and cash'!K11*'Editable assumptions'!B6 -> 135 | L20: ='Monthly forecast and cash'!L11*'Editable assumptions'!B6 -> 150 | M20: ='Monthly forecast and cash'!M11*'Editable assumptions'!B6 -> 165 | N20: ='Monthly forecast and cash'!N11*'Editable assumptions'!B6 -> 180 | O20: ='Monthly forecast and cash'!O11*'Editable assumptions'!B6 -> 195 | P20: ='Monthly forecast and cash'!P11*'Editable assumptions'!B6 -> 210 | Q20: ='Monthly forecast and cash'!Q11*'Editable assumptions'!B6 -> 225 | R20: ='Monthly forecast and cash'!R11*'Editable assumptions'!B6 -> 240 | S20: ='Monthly forecast and cash'!S11*'Editable assumptions'!B6 -> 255 | T20: ='Monthly forecast and cash'!T11*'Editable assumptions'!B6 -> 270 | U20: ='Monthly forecast and cash'!U11*'Editable assumptions'!B6 -> 285 | V20: ='Monthly forecast and cash'!V11*'Editable assumptions'!B6 -> 300 | W20: ='Monthly forecast and cash'!W11*'Editable assumptions'!B6 -> 315 | X20: ='Monthly forecast and cash'!X11*'Editable assumptions'!B6 -> 330 | Y20: ='Monthly forecast and cash'!Y11*'Editable assumptions'!B6 -> 345 | Z20: ='Monthly forecast and cash'!Z11*'Editable assumptions'!B6 -> 360
A21: Hosting expense | B21: 0 | C21: =IF('Editable assumptions'!B8="","",'Editable assumptions'!B8) -> 300 | D21: =IF('Editable assumptions'!B8="","",'Editable assumptions'!B8) -> 300 | E21: =IF('Editable assumptions'!B8="","",'Editable assumptions'!B8) -> 300 | F21: =IF('Editable assumptions'!B8="","",'Editable assumptions'!B8) -> 300 | G21: =IF('Editable assumptions'!B8="","",'Editable assumptions'!B8) -> 300 | H21: =IF('Editable assumptions'!B8="","",'Editable assumptions'!B8) -> 300 | I21: =IF('Editable assumptions'!B8="","",'Editable assumptions'!B8) -> 300 | J21: =IF('Editable assumptions'!B8="","",'Editable assumptions'!B8) -> 300 | K21: =IF('Editable assumptions'!B8="","",'Editable assumptions'!B8) -> 300 | L21: =IF('Editable assumptions'!B8="","",'Editable assumptions'!B8) -> 300 | M21: =IF('Editable assumptions'!B8="","",'Editable assumptions'!B8) -> 300 | N21: =IF('Editable assumptions'!B8="","",'Editable assumptions'!B8) -> 300 | O21: =IF('Editable assumptions'!B8="","",'Editable assumptions'!B8) -> 300 | P21: =IF('Editable assumptions'!B8="","",'Editable assumptions'!B8) -> 300 | Q21: =IF('Editable assumptions'!B8="","",'Editable assumptions'!B8) -> 300 | R21: =IF('Editable assumptions'!B8="","",'Editable assumptions'!B8) -> 300 | S21: =IF('Editable assumptions'!B8="","",'Editable assumptions'!B8) -> 300 | T21: =IF('Editable assumptions'!B8="","",'Editable assumptions'!B8) -> 300 | U21: =IF('Editable assumptions'!B8="","",'Editable assumptions'!B8) -> 300 | V21: =IF('Editable assumptions'!B8="","",'Editable assumptions'!B8) -> 300 | W21: =IF('Editable assumptions'!B8="","",'Editable assumptions'!B8) -> 300 | X21: =IF('Editable assumptions'!B8="","",'Editable assumptions'!B8) -> 300 | Y21: =IF('Editable assumptions'!B8="","",'Editable assumptions'!B8) -> 300 | Z21: =IF('Editable assumptions'!B8="","",'Editable assumptions'!B8) -> 300
A22: Cost of revenue | B22: 0 | C22: ='Monthly forecast and cash'!C15+'Monthly forecast and cash'!C18+'Monthly forecast and cash'!C21 -> 540 | D22: ='Monthly forecast and cash'!D15+'Monthly forecast and cash'!D18+'Monthly forecast and cash'!D21 -> 630 | E22: ='Monthly forecast and cash'!E15+'Monthly forecast and cash'!E18+'Monthly forecast and cash'!E21 -> 720 | F22: ='Monthly forecast and cash'!F15+'Monthly forecast and cash'!F18+'Monthly forecast and cash'!F21 -> 810 | G22: ='Monthly forecast and cash'!G15+'Monthly forecast and cash'!G18+'Monthly forecast and cash'!G21 -> 900 | H22: ='Monthly forecast and cash'!H15+'Monthly forecast and cash'!H18+'Monthly forecast and cash'!H21 -> 990 | I22: ='Monthly forecast and cash'!I15+'Monthly forecast and cash'!I18+'Monthly forecast and cash'!I21 -> 1080 | J22: ='Monthly forecast and cash'!J15+'Monthly forecast and cash'!J18+'Monthly forecast and cash'!J21 -> 1170 | ... Z22: ='Monthly forecast and cash'!Z15+'Monthly forecast and cash'!Z18+'Monthly forecast and cash'!Z21 -> 2610
A23: Gross profit | B23: 0 | C23: ='Monthly forecast and cash'!C12-'Monthly forecast and cash'!C22 -> -45 | D23: ='Monthly forecast and cash'!D12-'Monthly forecast and cash'!D22 -> 360 | E23: ='Monthly forecast and cash'!E12-'Monthly forecast and cash'!E22 -> 765 | F23: ='Monthly forecast and cash'!F12-'Monthly forecast and cash'!F22 -> 1170 | G23: ='Monthly forecast and cash'!G12-'Monthly forecast and cash'!G22 -> 1575 | H23: ='Monthly forecast and cash'!H12-'Monthly forecast and cash'!H22 -> 1980 | I23: ='Monthly forecast and cash'!I12-'Monthly forecast and cash'!I22 -> 2385 | J23: ='Monthly forecast and cash'!J12-'Monthly forecast and cash'!J22 -> 2790 | ... Z23: ='Monthly forecast and cash'!Z12-'Monthly forecast and cash'!Z22 -> 9270
A24: Gross margin | B24: =IFERROR('Monthly forecast and cash'!B23/'Monthly forecast and cash'!B12,"") | C24: =IFERROR('Monthly forecast and cash'!C23/'Monthly forecast and cash'!C12,"") -> -0.090909091 | D24: =IFERROR('Monthly forecast and cash'!D23/'Monthly forecast and cash'!D12,"") -> 0.36363636 | E24: =IFERROR('Monthly forecast and cash'!E23/'Monthly forecast and cash'!E12,"") -> 0.51515152 | F24: =IFERROR('Monthly forecast and cash'!F23/'Monthly forecast and cash'!F12,"") -> 0.59090909 | G24: =IFERROR('Monthly forecast and cash'!G23/'Monthly forecast and cash'!G12,"") -> 0.63636364 | H24: =IFERROR('Monthly forecast and cash'!H23/'Monthly forecast and cash'!H12,"") -> 0.66666667 | I24: =IFERROR('Monthly forecast and cash'!I23/'Monthly forecast and cash'!I12,"") -> 0.68831169 | ... Z24: =IFERROR('Monthly forecast and cash'!Z23/'Monthly forecast and cash'!Z12,"") -> 0.78030303
A25: Founder pay | B25: =SUM('Monthly forecast and cash'!B26) -> 0 | C25: =SUM('Monthly forecast and cash'!C26) -> 0 | D25: =SUM('Monthly forecast and cash'!D26) -> 0 | E25: =SUM('Monthly forecast and cash'!E26) -> 0 | F25: =SUM('Monthly forecast and cash'!F26) -> 0 | G25: =SUM('Monthly forecast and cash'!G26) -> 0 | H25: =SUM('Monthly forecast and cash'!H26) -> 0 | I25: =SUM('Monthly forecast and cash'!I26) -> 8000 | ... Z25: =SUM('Monthly forecast and cash'!Z26) -> 8000
A26: Founder — sole operator | B26: =0 -> 0 | C26: =IF(IF(IF(ISERROR('Monthly forecast and cash'!C5<='Editable assumptions'!B10),'Monthly forecast and cash'!C5<='Editable assumptions'!B10,IF(OR('Monthly forecast and cash'!C5="",'Editable assumptions'!B10=""),"",'Monthly forecast and cash'!C5<='Editable assumptions'!B10))="",FALSE,IF(ISERROR('Monthly forecast and cash'!C5<='Editable assumptions'!B10),'Monthly forecast and cash'!C5<='Editable assumptions'!B10,IF(OR('Monthly forecast and cash'!C5="",'Editable assumptions'!B10=""),"",'Monthly forecast and cash'!C5<='Editable assumptions'!B10))),0,IF('Editable assumptions'!B9="","",'Editable assumptions'!B9)) -> 0 | D26: =IF(IF(IF(ISERROR('Monthly forecast and cash'!D5<='Editable assumptions'!B10),'Monthly forecast and cash'!D5<='Editable assumptions'!B10,IF(OR('Monthly forecast and cash'!D5="",'Editable assumptions'!B10=""),"",'Monthly forecast and cash'!D5<='Editable assumptions'!B10))="",FALSE,IF(ISERROR('Monthly forecast and cash'!D5<='Editable assumptions'!B10),'Monthly forecast and cash'!D5<='Editable assumptions'!B10,IF(OR('Monthly forecast and cash'!D5="",'Editable assumptions'!B10=""),"",'Monthly forecast and cash'!D5<='Editable assumptions'!B10))),0,IF('Editable assumptions'!B9="","",'Editable assumptions'!B9)) -> 0 | E26: =IF(IF(IF(ISERROR('Monthly forecast and cash'!E5<='Editable assumptions'!B10),'Monthly forecast and cash'!E5<='Editable assumptions'!B10,IF(OR('Monthly forecast and cash'!E5="",'Editable assumptions'!B10=""),"",'Monthly forecast and cash'!E5<='Editable assumptions'!B10))="",FALSE,IF(ISERROR('Monthly forecast and cash'!E5<='Editable assumptions'!B10),'Monthly forecast and cash'!E5<='Editable assumptions'!B10,IF(OR('Monthly forecast and cash'!E5="",'Editable assumptions'!B10=""),"",'Monthly forecast and cash'!E5<='Editable assumptions'!B10))),0,IF('Editable assumptions'!B9="","",'Editable assumptions'!B9)) -> 0 | F26: =IF(IF(IF(ISERROR('Monthly forecast and cash'!F5<='Editable assumptions'!B10),'Monthly forecast and cash'!F5<='Editable assumptions'!B10,IF(OR('Monthly forecast and cash'!F5="",'Editable assumptions'!B10=""),"",'Monthly forecast and cash'!F5<='Editable assumptions'!B10))="",FALSE,IF(ISERROR('Monthly forecast and cash'!F5<='Editable assumptions'!B10),'Monthly forecast and cash'!F5<='Editable assumptions'!B10,IF(OR('Monthly forecast and cash'!F5="",'Editable assumptions'!B10=""),"",'Monthly forecast and cash'!F5<='Editable assumptions'!B10))),0,IF('Editable assumptions'!B9="","",'Editable assumptions'!B9)) -> 0 | G26: =IF(IF(IF(ISERROR('Monthly forecast and cash'!G5<='Editable assumptions'!B10),'Monthly forecast and cash'!G5<='Editable assumptions'!B10,IF(OR('Monthly forecast and cash'!G5="",'Editable assumptions'!B10=""),"",'Monthly forecast and cash'!G5<='Editable assumptions'!B10))="",FALSE,IF(ISERROR('Monthly forecast and cash'!G5<='Editable assumptions'!B10),'Monthly forecast and cash'!G5<='Editable assumptions'!B10,IF(OR('Monthly forecast and cash'!G5="",'Editable assumptions'!B10=""),"",'Monthly forecast and cash'!G5<='Editable assumptions'!B10))),0,IF('Editable assumptions'!B9="","",'Editable assumptions'!B9)) -> 0 | H26: =IF(IF(IF(ISERROR('Monthly forecast and cash'!H5<='Editable assumptions'!B10),'Monthly forecast and cash'!H5<='Editable assumptions'!B10,IF(OR('Monthly forecast and cash'!H5="",'Editable assumptions'!B10=""),"",'Monthly forecast and cash'!H5<='Editable assumptions'!B10))="",FALSE,IF(ISERROR('Monthly forecast and cash'!H5<='Editable assumptions'!B10),'Monthly forecast and cash'!H5<='Editable assumptions'!B10,IF(OR('Monthly forecast and cash'!H5="",'Editable assumptions'!B10=""),"",'Monthly forecast and cash'!H5<='Editable assumptions'!B10))),0,IF('Editable assumptions'!B9="","",'Editable assumptions'!B9)) -> 0 | I26: =IF(IF(IF(ISERROR('Monthly forecast and cash'!I5<='Editable assumptions'!B10),'Monthly forecast and cash'!I5<='Editable assumptions'!B10,IF(OR('Monthly forecast and cash'!I5="",'Editable assumptions'!B10=""),"",'Monthly forecast and cash'!I5<='Editable assumptions'!B10))="",FALSE,IF(ISERROR('Monthly forecast and cash'!I5<='Editable assumptions'!B10),'Monthly forecast and cash'!I5<='Editable assumptions'!B10,IF(OR('Monthly forecast and cash'!I5="",'Editable assumptions'!B10=""),"",'Monthly forecast and cash'!I5<='Editable assumptions'!B10))),0,IF('Editable assumptions'!B9="","",'Editable assumptions'!B9)) -> 8000 | J26: =IF(IF(IF(ISERROR('Monthly forecast and cash'!J5<='Editable assumptions'!B10),'Monthly forecast and cash'!J5<='Editable assumptions'!B10,IF(OR('Monthly forecast and cash'!J5="",'Editable assumptions'!B10=""),"",'Monthly forecast and cash'!J5<='Editable assumptions'!B10))="",FALSE,IF(ISERROR('Monthly forecast and cash'!J5<='Editable assumptions'!B10),'Monthly forecast and cash'!J5<='Editable assumptions'!B10,IF(OR('Monthly forecast and cash'!J5="",'Editable assumptions'!B10=""),"",'Monthly forecast and cash'!J5<='Editable assumptions'!B10))),0,IF('Editable assumptions'!B9="","",'Editable assumptions'!B9)) -> 8000 | K26: =IF(IF(IF(ISERROR('Monthly forecast and cash'!K5<='Editable assumptions'!B10),'Monthly forecast and cash'!K5<='Editable assumptions'!B10,IF(OR('Monthly forecast and cash'!K5="",'Editable assumptions'!B10=""),"",'Monthly forecast and cash'!K5<='Editable assumptions'!B10))="",FALSE,IF(ISERROR('Monthly forecast and cash'!K5<='Editable assumptions'!B10),'Monthly forecast and cash'!K5<='Editable assumptions'!B10,IF(OR('Monthly forecast and cash'!K5="",'Editable assumptions'!B10=""),"",'Monthly forecast and cash'!K5<='Editable assumptions'!B10))),0,IF('Editable assumptions'!B9="","",'Editable assumptions'!B9)) -> 8000 | L26: =IF(IF(IF(ISERROR('Monthly forecast and cash'!L5<='Editable assumptions'!B10),'Monthly forecast and cash'!L5<='Editable assumptions'!B10,IF(OR('Monthly forecast and cash'!L5="",'Editable assumptions'!B10=""),"",'Monthly forecast and cash'!L5<='Editable assumptions'!B10))="",FALSE,IF(ISERROR('Monthly forecast and cash'!L5<='Editable assumptions'!B10),'Monthly forecast and cash'!L5<='Editable assumptions'!B10,IF(OR('Monthly forecast and cash'!L5="",'Editable assumptions'!B10=""),"",'Monthly forecast and cash'!L5<='Editable assumptions'!B10))),0,IF('Editable assumptions'!B9="","",'Editable assumptions'!B9)) -> 8000 | M26: =IF(IF(IF(ISERROR('Monthly forecast and cash'!M5<='Editable assumptions'!B10),'Monthly forecast and cash'!M5<='Editable assumptions'!B10,IF(OR('Monthly forecast and cash'!M5="",'Editable assumptions'!B10=""),"",'Monthly forecast and cash'!M5<='Editable assumptions'!B10))="",FALSE,IF(ISERROR('Monthly forecast and cash'!M5<='Editable assumptions'!B10),'Monthly forecast and cash'!M5<='Editable assumptions'!B10,IF(OR('Monthly forecast and cash'!M5="",'Editable assumptions'!B10=""),"",'Monthly forecast and cash'!M5<='Editable assumptions'!B10))),0,IF('Editable assumptions'!B9="","",'Editable assumptions'!B9)) -> 8000 | N26: =IF(IF(IF(ISERROR('Monthly forecast and cash'!N5<='Editable assumptions'!B10),'Monthly forecast and cash'!N5<='Editable assumptions'!B10,IF(OR('Monthly forecast and cash'!N5="",'Editable assumptions'!B10=""),"",'Monthly forecast and cash'!N5<='Editable assumptions'!B10))="",FALSE,IF(ISERROR('Monthly forecast and cash'!N5<='Editable assumptions'!B10),'Monthly forecast and cash'!N5<='Editable assumptions'!B10,IF(OR('Monthly forecast and cash'!N5="",'Editable assumptions'!B10=""),"",'Monthly forecast and cash'!N5<='Editable assumptions'!B10))),0,IF('Editable assumptions'!B9="","",'Editable assumptions'!B9)) -> 8000 | O26: =IF(IF(IF(ISERROR('Monthly forecast and cash'!O5<='Editable assumptions'!B10),'Monthly forecast and cash'!O5<='Editable assumptions'!B10,IF(OR('Monthly forecast and cash'!O5="",'Editable assumptions'!B10=""),"",'Monthly forecast and cash'!O5<='Editable assumptions'!B10))="",FALSE,IF(ISERROR('Monthly forecast and cash'!O5<='Editable assumptions'!B10),'Monthly forecast and cash'!O5<='Editable assumptions'!B10,IF(OR('Monthly forecast and cash'!O5="",'Editable assumptions'!B10=""),"",'Monthly forecast and cash'!O5<='Editable assumptions'!B10))),0,IF('Editable assumptions'!B9="","",'Editable assumptions'!B9)) -> 8000 | P26: =IF(IF(IF(ISERROR('Monthly forecast and cash'!P5<='Editable assumptions'!B10),'Monthly forecast and cash'!P5<='Editable assumptions'!B10,IF(OR('Monthly forecast and cash'!P5="",'Editable assumptions'!B10=""),"",'Monthly forecast and cash'!P5<='Editable assumptions'!B10))="",FALSE,IF(ISERROR('Monthly forecast and cash'!P5<='Editable assumptions'!B10),'Monthly forecast and cash'!P5<='Editable assumptions'!B10,IF(OR('Monthly forecast and cash'!P5="",'Editable assumptions'!B10=""),"",'Monthly forecast and cash'!P5<='Editable assumptions'!B10))),0,IF('Editable assumptions'!B9="","",'Editable assumptions'!B9)) -> 8000 | Q26: =IF(IF(IF(ISERROR('Monthly forecast and cash'!Q5<='Editable assumptions'!B10),'Monthly forecast and cash'!Q5<='Editable assumptions'!B10,IF(OR('Monthly forecast and cash'!Q5="",'Editable assumptions'!B10=""),"",'Monthly forecast and cash'!Q5<='Editable assumptions'!B10))="",FALSE,IF(ISERROR('Monthly forecast and cash'!Q5<='Editable assumptions'!B10),'Monthly forecast and cash'!Q5<='Editable assumptions'!B10,IF(OR('Monthly forecast and cash'!Q5="",'Editable assumptions'!B10=""),"",'Monthly forecast and cash'!Q5<='Editable assumptions'!B10))),0,IF('Editable assumptions'!B9="","",'Editable assumptions'!B9)) -> 8000 | R26: =IF(IF(IF(ISERROR('Monthly forecast and cash'!R5<='Editable assumptions'!B10),'Monthly forecast and cash'!R5<='Editable assumptions'!B10,IF(OR('Monthly forecast and cash'!R5="",'Editable assumptions'!B10=""),"",'Monthly forecast and cash'!R5<='Editable assumptions'!B10))="",FALSE,IF(ISERROR('Monthly forecast and cash'!R5<='Editable assumptions'!B10),'Monthly forecast and cash'!R5<='Editable assumptions'!B10,IF(OR('Monthly forecast and cash'!R5="",'Editable assumptions'!B10=""),"",'Monthly forecast and cash'!R5<='Editable assumptions'!B10))),0,IF('Editable assumptions'!B9="","",'Editable assumptions'!B9)) -> 8000 | S26: =IF(IF(IF(ISERROR('Monthly forecast and cash'!S5<='Editable assumptions'!B10),'Monthly forecast and cash'!S5<='Editable assumptions'!B10,IF(OR('Monthly forecast and cash'!S5="",'Editable assumptions'!B10=""),"",'Monthly forecast and cash'!S5<='Editable assumptions'!B10))="",FALSE,IF(ISERROR('Monthly forecast and cash'!S5<='Editable assumptions'!B10),'Monthly forecast and cash'!S5<='Editable assumptions'!B10,IF(OR('Monthly forecast and cash'!S5="",'Editable assumptions'!B10=""),"",'Monthly forecast and cash'!S5<='Editable assumptions'!B10))),0,IF('Editable assumptions'!B9="","",'Editable assumptions'!B9)) -> 8000 | T26: =IF(IF(IF(ISERROR('Monthly forecast and cash'!T5<='Editable assumptions'!B10),'Monthly forecast and cash'!T5<='Editable assumptions'!B10,IF(OR('Monthly forecast and cash'!T5="",'Editable assumptions'!B10=""),"",'Monthly forecast and cash'!T5<='Editable assumptions'!B10))="",FALSE,IF(ISERROR('Monthly forecast and cash'!T5<='Editable assumptions'!B10),'Monthly forecast and cash'!T5<='Editable assumptions'!B10,IF(OR('Monthly forecast and cash'!T5="",'Editable assumptions'!B10=""),"",'Monthly forecast and cash'!T5<='Editable assumptions'!B10))),0,IF('Editable assumptions'!B9="","",'Editable assumptions'!B9)) -> 8000 | U26: =IF(IF(IF(ISERROR('Monthly forecast and cash'!U5<='Editable assumptions'!B10),'Monthly forecast and cash'!U5<='Editable assumptions'!B10,IF(OR('Monthly forecast and cash'!U5="",'Editable assumptions'!B10=""),"",'Monthly forecast and cash'!U5<='Editable assumptions'!B10))="",FALSE,IF(ISERROR('Monthly forecast and cash'!U5<='Editable assumptions'!B10),'Monthly forecast and cash'!U5<='Editable assumptions'!B10,IF(OR('Monthly forecast and cash'!U5="",'Editable assumptions'!B10=""),"",'Monthly forecast and cash'!U5<='Editable assumptions'!B10))),0,IF('Editable assumptions'!B9="","",'Editable assumptions'!B9)) -> 8000 | V26: =IF(IF(IF(ISERROR('Monthly forecast and cash'!V5<='Editable assumptions'!B10),'Monthly forecast and cash'!V5<='Editable assumptions'!B10,IF(OR('Monthly forecast and cash'!V5="",'Editable assumptions'!B10=""),"",'Monthly forecast and cash'!V5<='Editable assumptions'!B10))="",FALSE,IF(ISERROR('Monthly forecast and cash'!V5<='Editable assumptions'!B10),'Monthly forecast and cash'!V5<='Editable assumptions'!B10,IF(OR('Monthly forecast and cash'!V5="",'Editable assumptions'!B10=""),"",'Monthly forecast and cash'!V5<='Editable assumptions'!B10))),0,IF('Editable assumptions'!B9="","",'Editable assumptions'!B9)) -> 8000 | W26: =IF(IF(IF(ISERROR('Monthly forecast and cash'!W5<='Editable assumptions'!B10),'Monthly forecast and cash'!W5<='Editable assumptions'!B10,IF(OR('Monthly forecast and cash'!W5="",'Editable assumptions'!B10=""),"",'Monthly forecast and cash'!W5<='Editable assumptions'!B10))="",FALSE,IF(ISERROR('Monthly forecast and cash'!W5<='Editable assumptions'!B10),'Monthly forecast and cash'!W5<='Editable assumptions'!B10,IF(OR('Monthly forecast and cash'!W5="",'Editable assumptions'!B10=""),"",'Monthly forecast and cash'!W5<='Editable assumptions'!B10))),0,IF('Editable assumptions'!B9="","",'Editable assumptions'!B9)) -> 8000 | X26: =IF(IF(IF(ISERROR('Monthly forecast and cash'!X5<='Editable assumptions'!B10),'Monthly forecast and cash'!X5<='Editable assumptions'!B10,IF(OR('Monthly forecast and cash'!X5="",'Editable assumptions'!B10=""),"",'Monthly forecast and cash'!X5<='Editable assumptions'!B10))="",FALSE,IF(ISERROR('Monthly forecast and cash'!X5<='Editable assumptions'!B10),'Monthly forecast and cash'!X5<='Editable assumptions'!B10,IF(OR('Monthly forecast and cash'!X5="",'Editable assumptions'!B10=""),"",'Monthly forecast and cash'!X5<='Editable assumptions'!B10))),0,IF('Editable assumptions'!B9="","",'Editable assumptions'!B9)) -> 8000 | Y26: =IF(IF(IF(ISERROR('Monthly forecast and cash'!Y5<='Editable assumptions'!B10),'Monthly forecast and cash'!Y5<='Editable assumptions'!B10,IF(OR('Monthly forecast and cash'!Y5="",'Editable assumptions'!B10=""),"",'Monthly forecast and cash'!Y5<='Editable assumptions'!B10))="",FALSE,IF(ISERROR('Monthly forecast and cash'!Y5<='Editable assumptions'!B10),'Monthly forecast and cash'!Y5<='Editable assumptions'!B10,IF(OR('Monthly forecast and cash'!Y5="",'Editable assumptions'!B10=""),"",'Monthly forecast and cash'!Y5<='Editable assumptions'!B10))),0,IF('Editable assumptions'!B9="","",'Editable assumptions'!B9)) -> 8000 | Z26: =IF(IF(IF(ISERROR('Monthly forecast and cash'!Z5<='Editable assumptions'!B10),'Monthly forecast and cash'!Z5<='Editable assumptions'!B10,IF(OR('Monthly forecast and cash'!Z5="",'Editable assumptions'!B10=""),"",'Monthly forecast and cash'!Z5<='Editable assumptions'!B10))="",FALSE,IF(ISERROR('Monthly forecast and cash'!Z5<='Editable assumptions'!B10),'Monthly forecast and cash'!Z5<='Editable assumptions'!B10,IF(OR('Monthly forecast and cash'!Z5="",'Editable assumptions'!B10=""),"",'Monthly forecast and cash'!Z5<='Editable assumptions'!B10))),0,IF('Editable assumptions'!B9="","",'Editable assumptions'!B9)) -> 8000
A27: Operating profit | B27: 0 | C27: ='Monthly forecast and cash'!C23-'Monthly forecast and cash'!C25 -> -45 | D27: ='Monthly forecast and cash'!D23-'Monthly forecast and cash'!D25 -> 360 | E27: ='Monthly forecast and cash'!E23-'Monthly forecast and cash'!E25 -> 765 | F27: ='Monthly forecast and cash'!F23-'Monthly forecast and cash'!F25 -> 1170 | G27: ='Monthly forecast and cash'!G23-'Monthly forecast and cash'!G25 -> 1575 | H27: ='Monthly forecast and cash'!H23-'Monthly forecast and cash'!H25 -> 1980 | I27: ='Monthly forecast and cash'!I23-'Monthly forecast and cash'!I25 -> -5615 | J27: ='Monthly forecast and cash'!J23-'Monthly forecast and cash'!J25 -> -5210 | ... Z27: ='Monthly forecast and cash'!Z23-'Monthly forecast and cash'!Z25 -> 1270
A28: Net cash flow | B28: 0 | C28: =IF('Monthly forecast and cash'!C27="","",'Monthly forecast and cash'!C27) -> -45 | D28: =IF('Monthly forecast and cash'!D27="","",'Monthly forecast and cash'!D27) -> 360 | E28: =IF('Monthly forecast and cash'!E27="","",'Monthly forecast and cash'!E27) -> 765 | F28: =IF('Monthly forecast and cash'!F27="","",'Monthly forecast and cash'!F27) -> 1170 | G28: =IF('Monthly forecast and cash'!G27="","",'Monthly forecast and cash'!G27) -> 1575 | H28: =IF('Monthly forecast and cash'!H27="","",'Monthly forecast and cash'!H27) -> 1980 | I28: =IF('Monthly forecast and cash'!I27="","",'Monthly forecast and cash'!I27) -> -5615 | J28: =IF('Monthly forecast and cash'!J27="","",'Monthly forecast and cash'!J27) -> -5210 | ... Z28: =IF('Monthly forecast and cash'!Z27="","",'Monthly forecast and cash'!Z27) -> 1270
A29: Cash balance | B29: =IF('Editable assumptions'!B11="","",'Editable assumptions'!B11) -> 25000 | C29: ='Monthly forecast and cash'!B29+'Monthly forecast and cash'!C28 -> 24955 | D29: ='Monthly forecast and cash'!C29+'Monthly forecast and cash'!D28 -> 25315 | E29: ='Monthly forecast and cash'!D29+'Monthly forecast and cash'!E28 -> 26080 | F29: ='Monthly forecast and cash'!E29+'Monthly forecast and cash'!F28 -> 27250 | G29: ='Monthly forecast and cash'!F29+'Monthly forecast and cash'!G28 -> 28825 | H29: ='Monthly forecast and cash'!G29+'Monthly forecast and cash'!H28 -> 30805 | I29: ='Monthly forecast and cash'!H29+'Monthly forecast and cash'!I28 -> 25190 | J29: ='Monthly forecast and cash'!I29+'Monthly forecast and cash'!J28 -> 19980 | ... Z29: ='Monthly forecast and cash'!Y29+'Monthly forecast and cash'!Z28 -> -8300
A30: Monthly cash burn | B30: 0 | C30: =MAX(-'Monthly forecast and cash'!C28,0) -> 45 | D30: =MAX(-'Monthly forecast and cash'!D28,0) -> 0 | E30: =MAX(-'Monthly forecast and cash'!E28,0) -> 0 | F30: =MAX(-'Monthly forecast and cash'!F28,0) -> 0 | G30: =MAX(-'Monthly forecast and cash'!G28,0) -> 0 | H30: =MAX(-'Monthly forecast and cash'!H28,0) -> 0 | I30: =MAX(-'Monthly forecast and cash'!I28,0) -> 5615 | J30: =MAX(-'Monthly forecast and cash'!J28,0) -> 5210 | ... Z30: =MAX(-'Monthly forecast and cash'!Z28,0) -> 0
A31: Paying teams to break even | B31: 0 | C31: =IF(IF(IF(ISERROR('Unit economics by plan'!I6>0),'Unit economics by plan'!I6>0,IF('Unit economics by plan'!I6="","",'Unit economics by plan'!I6>0))="",FALSE,IF(ISERROR('Unit economics by plan'!I6>0),'Unit economics by plan'!I6>0,IF('Unit economics by plan'!I6="","",'Unit economics by plan'!I6>0))),CEILING(('Monthly forecast and cash'!C21+'Monthly forecast and cash'!C25+'Monthly forecast and cash'!C8*'Unit economics by plan'!H5)/'Unit economics by plan'!I6,1),"") -> 6 | D31: =IF(IF(IF(ISERROR('Unit economics by plan'!I6>0),'Unit economics by plan'!I6>0,IF('Unit economics by plan'!I6="","",'Unit economics by plan'!I6>0))="",FALSE,IF(ISERROR('Unit economics by plan'!I6>0),'Unit economics by plan'!I6>0,IF('Unit economics by plan'!I6="","",'Unit economics by plan'!I6>0))),CEILING(('Monthly forecast and cash'!D21+'Monthly forecast and cash'!D25+'Monthly forecast and cash'!D8*'Unit economics by plan'!H5)/'Unit economics by plan'!I6,1),"") -> 6 | E31: =IF(IF(IF(ISERROR('Unit economics by plan'!I6>0),'Unit economics by plan'!I6>0,IF('Unit economics by plan'!I6="","",'Unit economics by plan'!I6>0))="",FALSE,IF(ISERROR('Unit economics by plan'!I6>0),'Unit economics by plan'!I6>0,IF('Unit economics by plan'!I6="","",'Unit economics by plan'!I6>0))),CEILING(('Monthly forecast and cash'!E21+'Monthly forecast and cash'!E25+'Monthly forecast and cash'!E8*'Unit economics by plan'!H5)/'Unit economics by plan'!I6,1),"") -> 6 | F31: =IF(IF(IF(ISERROR('Unit economics by plan'!I6>0),'Unit economics by plan'!I6>0,IF('Unit economics by plan'!I6="","",'Unit economics by plan'!I6>0))="",FALSE,IF(ISERROR('Unit economics by plan'!I6>0),'Unit economics by plan'!I6>0,IF('Unit economics by plan'!I6="","",'Unit economics by plan'!I6>0))),CEILING(('Monthly forecast and cash'!F21+'Monthly forecast and cash'!F25+'Monthly forecast and cash'!F8*'Unit economics by plan'!H5)/'Unit economics by plan'!I6,1),"") -> 6 | G31: =IF(IF(IF(ISERROR('Unit economics by plan'!I6>0),'Unit economics by plan'!I6>0,IF('Unit economics by plan'!I6="","",'Unit economics by plan'!I6>0))="",FALSE,IF(ISERROR('Unit economics by plan'!I6>0),'Unit economics by plan'!I6>0,IF('Unit economics by plan'!I6="","",'Unit economics by plan'!I6>0))),CEILING(('Monthly forecast and cash'!G21+'Monthly forecast and cash'!G25+'Monthly forecast and cash'!G8*'Unit economics by plan'!H5)/'Unit economics by plan'!I6,1),"") -> 6 | H31: =IF(IF(IF(ISERROR('Unit economics by plan'!I6>0),'Unit economics by plan'!I6>0,IF('Unit economics by plan'!I6="","",'Unit economics by plan'!I6>0))="",FALSE,IF(ISERROR('Unit economics by plan'!I6>0),'Unit economics by plan'!I6>0,IF('Unit economics by plan'!I6="","",'Unit economics by plan'!I6>0))),CEILING(('Monthly forecast and cash'!H21+'Monthly forecast and cash'!H25+'Monthly forecast and cash'!H8*'Unit economics by plan'!H5)/'Unit economics by plan'!I6,1),"") -> 6 | I31: =IF(IF(IF(ISERROR('Unit economics by plan'!I6>0),'Unit economics by plan'!I6>0,IF('Unit economics by plan'!I6="","",'Unit economics by plan'!I6>0))="",FALSE,IF(ISERROR('Unit economics by plan'!I6>0),'Unit economics by plan'!I6>0,IF('Unit economics by plan'!I6="","",'Unit economics by plan'!I6>0))),CEILING(('Monthly forecast and cash'!I21+'Monthly forecast and cash'!I25+'Monthly forecast and cash'!I8*'Unit economics by plan'!H5)/'Unit economics by plan'!I6,1),"") -> 105 | J31: =IF(IF(IF(ISERROR('Unit economics by plan'!I6>0),'Unit economics by plan'!I6>0,IF('Unit economics by plan'!I6="","",'Unit economics by plan'!I6>0))="",FALSE,IF(ISERROR('Unit economics by plan'!I6>0),'Unit economics by plan'!I6>0,IF('Unit economics by plan'!I6="","",'Unit economics by plan'!I6>0))),CEILING(('Monthly forecast and cash'!J21+'Monthly forecast and cash'!J25+'Monthly forecast and cash'!J8*'Unit economics by plan'!H5)/'Unit economics by plan'!I6,1),"") -> 105 | K31: =IF(IF(IF(ISERROR('Unit economics by plan'!I6>0),'Unit economics by plan'!I6>0,IF('Unit economics by plan'!I6="","",'Unit economics by plan'!I6>0))="",FALSE,IF(ISERROR('Unit economics by plan'!I6>0),'Unit economics by plan'!I6>0,IF('Unit economics by plan'!I6="","",'Unit economics by plan'!I6>0))),CEILING(('Monthly forecast and cash'!K21+'Monthly forecast and cash'!K25+'Monthly forecast and cash'!K8*'Unit economics by plan'!H5)/'Unit economics by plan'!I6,1),"") -> 105 | L31: =IF(IF(IF(ISERROR('Unit economics by plan'!I6>0),'Unit economics by plan'!I6>0,IF('Unit economics by plan'!I6="","",'Unit economics by plan'!I6>0))="",FALSE,IF(ISERROR('Unit economics by plan'!I6>0),'Unit economics by plan'!I6>0,IF('Unit economics by plan'!I6="","",'Unit economics by plan'!I6>0))),CEILING(('Monthly forecast and cash'!L21+'Monthly forecast and cash'!L25+'Monthly forecast and cash'!L8*'Unit economics by plan'!H5)/'Unit economics by plan'!I6,1),"") -> 105 | M31: =IF(IF(IF(ISERROR('Unit economics by plan'!I6>0),'Unit economics by plan'!I6>0,IF('Unit economics by plan'!I6="","",'Unit economics by plan'!I6>0))="",FALSE,IF(ISERROR('Unit economics by plan'!I6>0),'Unit economics by plan'!I6>0,IF('Unit economics by plan'!I6="","",'Unit economics by plan'!I6>0))),CEILING(('Monthly forecast and cash'!M21+'Monthly forecast and cash'!M25+'Monthly forecast and cash'!M8*'Unit economics by plan'!H5)/'Unit economics by plan'!I6,1),"") -> 105 | N31: =IF(IF(IF(ISERROR('Unit economics by plan'!I6>0),'Unit economics by plan'!I6>0,IF('Unit economics by plan'!I6="","",'Unit economics by plan'!I6>0))="",FALSE,IF(ISERROR('Unit economics by plan'!I6>0),'Unit economics by plan'!I6>0,IF('Unit economics by plan'!I6="","",'Unit economics by plan'!I6>0))),CEILING(('Monthly forecast and cash'!N21+'Monthly forecast and cash'!N25+'Monthly forecast and cash'!N8*'Unit economics by plan'!H5)/'Unit economics by plan'!I6,1),"") -> 105 | O31: =IF(IF(IF(ISERROR('Unit economics by plan'!I6>0),'Unit economics by plan'!I6>0,IF('Unit economics by plan'!I6="","",'Unit economics by plan'!I6>0))="",FALSE,IF(ISERROR('Unit economics by plan'!I6>0),'Unit economics by plan'!I6>0,IF('Unit economics by plan'!I6="","",'Unit economics by plan'!I6>0))),CEILING(('Monthly forecast and cash'!O21+'Monthly forecast and cash'!O25+'Monthly forecast and cash'!O8*'Unit economics by plan'!H5)/'Unit economics by plan'!I6,1),"") -> 105 | P31: =IF(IF(IF(ISERROR('Unit economics by plan'!I6>0),'Unit economics by plan'!I6>0,IF('Unit economics by plan'!I6="","",'Unit economics by plan'!I6>0))="",FALSE,IF(ISERROR('Unit economics by plan'!I6>0),'Unit economics by plan'!I6>0,IF('Unit economics by plan'!I6="","",'Unit economics by plan'!I6>0))),CEILING(('Monthly forecast and cash'!P21+'Monthly forecast and cash'!P25+'Monthly forecast and cash'!P8*'Unit economics by plan'!H5)/'Unit economics by plan'!I6,1),"") -> 105 | Q31: =IF(IF(IF(ISERROR('Unit economics by plan'!I6>0),'Unit economics by plan'!I6>0,IF('Unit economics by plan'!I6="","",'Unit economics by plan'!I6>0))="",FALSE,IF(ISERROR('Unit economics by plan'!I6>0),'Unit economics by plan'!I6>0,IF('Unit economics by plan'!I6="","",'Unit economics by plan'!I6>0))),CEILING(('Monthly forecast and cash'!Q21+'Monthly forecast and cash'!Q25+'Monthly forecast and cash'!Q8*'Unit economics by plan'!H5)/'Unit economics by plan'!I6,1),"") -> 105 | R31: =IF(IF(IF(ISERROR('Unit economics by plan'!I6>0),'Unit economics by plan'!I6>0,IF('Unit economics by plan'!I6="","",'Unit economics by plan'!I6>0))="",FALSE,IF(ISERROR('Unit economics by plan'!I6>0),'Unit economics by plan'!I6>0,IF('Unit economics by plan'!I6="","",'Unit economics by plan'!I6>0))),CEILING(('Monthly forecast and cash'!R21+'Monthly forecast and cash'!R25+'Monthly forecast and cash'!R8*'Unit economics by plan'!H5)/'Unit economics by plan'!I6,1),"") -> 105 | S31: =IF(IF(IF(ISERROR('Unit economics by plan'!I6>0),'Unit economics by plan'!I6>0,IF('Unit economics by plan'!I6="","",'Unit economics by plan'!I6>0))="",FALSE,IF(ISERROR('Unit economics by plan'!I6>0),'Unit economics by plan'!I6>0,IF('Unit economics by plan'!I6="","",'Unit economics by plan'!I6>0))),CEILING(('Monthly forecast and cash'!S21+'Monthly forecast and cash'!S25+'Monthly forecast and cash'!S8*'Unit economics by plan'!H5)/'Unit economics by plan'!I6,1),"") -> 105 | T31: =IF(IF(IF(ISERROR('Unit economics by plan'!I6>0),'Unit economics by plan'!I6>0,IF('Unit economics by plan'!I6="","",'Unit economics by plan'!I6>0))="",FALSE,IF(ISERROR('Unit economics by plan'!I6>0),'Unit economics by plan'!I6>0,IF('Unit economics by plan'!I6="","",'Unit economics by plan'!I6>0))),CEILING(('Monthly forecast and cash'!T21+'Monthly forecast and cash'!T25+'Monthly forecast and cash'!T8*'Unit economics by plan'!H5)/'Unit economics by plan'!I6,1),"") -> 105 | U31: =IF(IF(IF(ISERROR('Unit economics by plan'!I6>0),'Unit economics by plan'!I6>0,IF('Unit economics by plan'!I6="","",'Unit economics by plan'!I6>0))="",FALSE,IF(ISERROR('Unit economics by plan'!I6>0),'Unit economics by plan'!I6>0,IF('Unit economics by plan'!I6="","",'Unit economics by plan'!I6>0))),CEILING(('Monthly forecast and cash'!U21+'Monthly forecast and cash'!U25+'Monthly forecast and cash'!U8*'Unit economics by plan'!H5)/'Unit economics by plan'!I6,1),"") -> 105 | V31: =IF(IF(IF(ISERROR('Unit economics by plan'!I6>0),'Unit economics by plan'!I6>0,IF('Unit economics by plan'!I6="","",'Unit economics by plan'!I6>0))="",FALSE,IF(ISERROR('Unit economics by plan'!I6>0),'Unit economics by plan'!I6>0,IF('Unit economics by plan'!I6="","",'Unit economics by plan'!I6>0))),CEILING(('Monthly forecast and cash'!V21+'Monthly forecast and cash'!V25+'Monthly forecast and cash'!V8*'Unit economics by plan'!H5)/'Unit economics by plan'!I6,1),"") -> 105 | W31: =IF(IF(IF(ISERROR('Unit economics by plan'!I6>0),'Unit economics by plan'!I6>0,IF('Unit economics by plan'!I6="","",'Unit economics by plan'!I6>0))="",FALSE,IF(ISERROR('Unit economics by plan'!I6>0),'Unit economics by plan'!I6>0,IF('Unit economics by plan'!I6="","",'Unit economics by plan'!I6>0))),CEILING(('Monthly forecast and cash'!W21+'Monthly forecast and cash'!W25+'Monthly forecast and cash'!W8*'Unit economics by plan'!H5)/'Unit economics by plan'!I6,1),"") -> 105 | X31: =IF(IF(IF(ISERROR('Unit economics by plan'!I6>0),'Unit economics by plan'!I6>0,IF('Unit economics by plan'!I6="","",'Unit economics by plan'!I6>0))="",FALSE,IF(ISERROR('Unit economics by plan'!I6>0),'Unit economics by plan'!I6>0,IF('Unit economics by plan'!I6="","",'Unit economics by plan'!I6>0))),CEILING(('Monthly forecast and cash'!X21+'Monthly forecast and cash'!X25+'Monthly forecast and cash'!X8*'Unit economics by plan'!H5)/'Unit economics by plan'!I6,1),"") -> 105 | Y31: =IF(IF(IF(ISERROR('Unit economics by plan'!I6>0),'Unit economics by plan'!I6>0,IF('Unit economics by plan'!I6="","",'Unit economics by plan'!I6>0))="",FALSE,IF(ISERROR('Unit economics by plan'!I6>0),'Unit economics by plan'!I6>0,IF('Unit economics by plan'!I6="","",'Unit economics by plan'!I6>0))),CEILING(('Monthly forecast and cash'!Y21+'Monthly forecast and cash'!Y25+'Monthly forecast and cash'!Y8*'Unit economics by plan'!H5)/'Unit economics by plan'!I6,1),"") -> 105 | Z31: =IF(IF(IF(ISERROR('Unit economics by plan'!I6>0),'Unit economics by plan'!I6>0,IF('Unit economics by plan'!I6="","",'Unit economics by plan'!I6>0))="",FALSE,IF(ISERROR('Unit economics by plan'!I6>0),'Unit economics by plan'!I6>0,IF('Unit economics by plan'!I6="","",'Unit economics by plan'!I6>0))),CEILING(('Monthly forecast and cash'!Z21+'Monthly forecast and cash'!Z25+'Monthly forecast and cash'!Z8*'Unit economics by plan'!H5)/'Unit economics by plan'!I6,1),"") -> 105
A32: Compute hours | B32: 0 | C32: ='Monthly forecast and cash'!C9*'Editable assumptions'!B7/60 -> 133.33333 | D32: ='Monthly forecast and cash'!D9*'Editable assumptions'!B7/60 -> 183.33333 | E32: ='Monthly forecast and cash'!E9*'Editable assumptions'!B7/60 -> 233.33333 | F32: ='Monthly forecast and cash'!F9*'Editable assumptions'!B7/60 -> 283.33333 | G32: ='Monthly forecast and cash'!G9*'Editable assumptions'!B7/60 -> 333.33333 | H32: ='Monthly forecast and cash'!H9*'Editable assumptions'!B7/60 -> 383.33333 | I32: ='Monthly forecast and cash'!I9*'Editable assumptions'!B7/60 -> 433.33333 | J32: ='Monthly forecast and cash'!J9*'Editable assumptions'!B7/60 -> 483.33333 | K32: ='Monthly forecast and cash'!K9*'Editable assumptions'!B7/60 -> 533.33333 | L32: ='Monthly forecast and cash'!L9*'Editable assumptions'!B7/60 -> 583.33333 | M32: ='Monthly forecast and cash'!M9*'Editable assumptions'!B7/60 -> 633.33333 | N32: ='Monthly forecast and cash'!N9*'Editable assumptions'!B7/60 -> 683.33333 | O32: ='Monthly forecast and cash'!O9*'Editable assumptions'!B7/60 -> 733.33333 | P32: ='Monthly forecast and cash'!P9*'Editable assumptions'!B7/60 -> 783.33333 | Q32: ='Monthly forecast and cash'!Q9*'Editable assumptions'!B7/60 -> 833.33333 | R32: ='Monthly forecast and cash'!R9*'Editable assumptions'!B7/60 -> 883.33333 | S32: ='Monthly forecast and cash'!S9*'Editable assumptions'!B7/60 -> 933.33333 | T32: ='Monthly forecast and cash'!T9*'Editable assumptions'!B7/60 -> 983.33333 | U32: ='Monthly forecast and cash'!U9*'Editable assumptions'!B7/60 -> 1033.3333 | V32: ='Monthly forecast and cash'!V9*'Editable assumptions'!B7/60 -> 1083.3333 | W32: ='Monthly forecast and cash'!W9*'Editable assumptions'!B7/60 -> 1133.3333 | X32: ='Monthly forecast and cash'!X9*'Editable assumptions'!B7/60 -> 1183.3333 | Y32: ='Monthly forecast and cash'!Y9*'Editable assumptions'!B7/60 -> 1233.3333 | Z32: ='Monthly forecast and cash'!Z9*'Editable assumptions'!B7/60 -> 1283.3333
A33: Fully funded month | B33: 0 | C33: =IF(IF(IF(ISERROR('Model inputs'!B313>0),'Model inputs'!B313>0,IF('Model inputs'!B313="","",'Model inputs'!B313>0))="",FALSE,IF(ISERROR('Model inputs'!B313>0),'Model inputs'!B313>0,IF('Model inputs'!B313="","",'Model inputs'!B313>0))),1,0) -> 1 | D33: =IF(IF(IF(ISERROR('Model inputs'!B347>0),'Model inputs'!B347>0,IF('Model inputs'!B347="","",'Model inputs'!B347>0))="",FALSE,IF(ISERROR('Model inputs'!B347>0),'Model inputs'!B347>0,IF('Model inputs'!B347="","",'Model inputs'!B347>0))),1,0) -> 1 | E33: =IF(IF(IF(ISERROR('Model inputs'!B381>0),'Model inputs'!B381>0,IF('Model inputs'!B381="","",'Model inputs'!B381>0))="",FALSE,IF(ISERROR('Model inputs'!B381>0),'Model inputs'!B381>0,IF('Model inputs'!B381="","",'Model inputs'!B381>0))),1,0) -> 1 | F33: =IF(IF(IF(ISERROR('Model inputs'!B415>0),'Model inputs'!B415>0,IF('Model inputs'!B415="","",'Model inputs'!B415>0))="",FALSE,IF(ISERROR('Model inputs'!B415>0),'Model inputs'!B415>0,IF('Model inputs'!B415="","",'Model inputs'!B415>0))),1,0) -> 1 | G33: =IF(IF(IF(ISERROR('Model inputs'!B449>0),'Model inputs'!B449>0,IF('Model inputs'!B449="","",'Model inputs'!B449>0))="",FALSE,IF(ISERROR('Model inputs'!B449>0),'Model inputs'!B449>0,IF('Model inputs'!B449="","",'Model inputs'!B449>0))),1,0) -> 1 | H33: =IF(IF(IF(ISERROR('Model inputs'!B483>0),'Model inputs'!B483>0,IF('Model inputs'!B483="","",'Model inputs'!B483>0))="",FALSE,IF(ISERROR('Model inputs'!B483>0),'Model inputs'!B483>0,IF('Model inputs'!B483="","",'Model inputs'!B483>0))),1,0) -> 1 | I33: =IF(IF(IF(ISERROR('Model inputs'!B517>0),'Model inputs'!B517>0,IF('Model inputs'!B517="","",'Model inputs'!B517>0))="",FALSE,IF(ISERROR('Model inputs'!B517>0),'Model inputs'!B517>0,IF('Model inputs'!B517="","",'Model inputs'!B517>0))),1,0) -> 1 | J33: =IF(IF(IF(ISERROR('Model inputs'!B551>0),'Model inputs'!B551>0,IF('Model inputs'!B551="","",'Model inputs'!B551>0))="",FALSE,IF(ISERROR('Model inputs'!B551>0),'Model inputs'!B551>0,IF('Model inputs'!B551="","",'Model inputs'!B551>0))),1,0) -> 1 | K33: =IF(IF(IF(ISERROR('Model inputs'!B585>0),'Model inputs'!B585>0,IF('Model inputs'!B585="","",'Model inputs'!B585>0))="",FALSE,IF(ISERROR('Model inputs'!B585>0),'Model inputs'!B585>0,IF('Model inputs'!B585="","",'Model inputs'!B585>0))),1,0) -> 1 | L33: =IF(IF(IF(ISERROR('Model inputs'!B619>0),'Model inputs'!B619>0,IF('Model inputs'!B619="","",'Model inputs'!B619>0))="",FALSE,IF(ISERROR('Model inputs'!B619>0),'Model inputs'!B619>0,IF('Model inputs'!B619="","",'Model inputs'!B619>0))),1,0) -> 1 | M33: =IF(IF(IF(ISERROR('Model inputs'!B653>0),'Model inputs'!B653>0,IF('Model inputs'!B653="","",'Model inputs'!B653>0))="",FALSE,IF(ISERROR('Model inputs'!B653>0),'Model inputs'!B653>0,IF('Model inputs'!B653="","",'Model inputs'!B653>0))),1,0) -> 1 | N33: =IF(IF(IF(ISERROR('Model inputs'!B687>0),'Model inputs'!B687>0,IF('Model inputs'!B687="","",'Model inputs'!B687>0))="",FALSE,IF(ISERROR('Model inputs'!B687>0),'Model inputs'!B687>0,IF('Model inputs'!B687="","",'Model inputs'!B687>0))),1,0) -> 1 | O33: =IF(IF(IF(ISERROR('Model inputs'!B721>0),'Model inputs'!B721>0,IF('Model inputs'!B721="","",'Model inputs'!B721>0))="",FALSE,IF(ISERROR('Model inputs'!B721>0),'Model inputs'!B721>0,IF('Model inputs'!B721="","",'Model inputs'!B721>0))),1,0) -> 1 | P33: =IF(IF(IF(ISERROR('Model inputs'!B755>0),'Model inputs'!B755>0,IF('Model inputs'!B755="","",'Model inputs'!B755>0))="",FALSE,IF(ISERROR('Model inputs'!B755>0),'Model inputs'!B755>0,IF('Model inputs'!B755="","",'Model inputs'!B755>0))),1,0) -> 0 | Q33: =IF(IF(IF(ISERROR('Model inputs'!B789>0),'Model inputs'!B789>0,IF('Model inputs'!B789="","",'Model inputs'!B789>0))="",FALSE,IF(ISERROR('Model inputs'!B789>0),'Model inputs'!B789>0,IF('Model inputs'!B789="","",'Model inputs'!B789>0))),1,0) -> 0 | R33: =IF(IF(IF(ISERROR('Model inputs'!B823>0),'Model inputs'!B823>0,IF('Model inputs'!B823="","",'Model inputs'!B823>0))="",FALSE,IF(ISERROR('Model inputs'!B823>0),'Model inputs'!B823>0,IF('Model inputs'!B823="","",'Model inputs'!B823>0))),1,0) -> 0 | S33: =IF(IF(IF(ISERROR('Model inputs'!B857>0),'Model inputs'!B857>0,IF('Model inputs'!B857="","",'Model inputs'!B857>0))="",FALSE,IF(ISERROR('Model inputs'!B857>0),'Model inputs'!B857>0,IF('Model inputs'!B857="","",'Model inputs'!B857>0))),1,0) -> 0 | T33: =IF(IF(IF(ISERROR('Model inputs'!B891>0),'Model inputs'!B891>0,IF('Model inputs'!B891="","",'Model inputs'!B891>0))="",FALSE,IF(ISERROR('Model inputs'!B891>0),'Model inputs'!B891>0,IF('Model inputs'!B891="","",'Model inputs'!B891>0))),1,0) -> 0 | U33: =IF(IF(IF(ISERROR('Model inputs'!B925>0),'Model inputs'!B925>0,IF('Model inputs'!B925="","",'Model inputs'!B925>0))="",FALSE,IF(ISERROR('Model inputs'!B925>0),'Model inputs'!B925>0,IF('Model inputs'!B925="","",'Model inputs'!B925>0))),1,0) -> 0 | V33: =IF(IF(IF(ISERROR('Model inputs'!B959>0),'Model inputs'!B959>0,IF('Model inputs'!B959="","",'Model inputs'!B959>0))="",FALSE,IF(ISERROR('Model inputs'!B959>0),'Model inputs'!B959>0,IF('Model inputs'!B959="","",'Model inputs'!B959>0))),1,0) -> 0 | W33: =IF(IF(IF(ISERROR('Model inputs'!B993>0),'Model inputs'!B993>0,IF('Model inputs'!B993="","",'Model inputs'!B993>0))="",FALSE,IF(ISERROR('Model inputs'!B993>0),'Model inputs'!B993>0,IF('Model inputs'!B993="","",'Model inputs'!B993>0))),1,0) -> 0 | X33: =IF(IF(IF(ISERROR('Model inputs'!B1027>0),'Model inputs'!B1027>0,IF('Model inputs'!B1027="","",'Model inputs'!B1027>0))="",FALSE,IF(ISERROR('Model inputs'!B1027>0),'Model inputs'!B1027>0,IF('Model inputs'!B1027="","",'Model inputs'!B1027>0))),1,0) -> 0 | Y33: =IF(IF(IF(ISERROR('Model inputs'!B1061>0),'Model inputs'!B1061>0,IF('Model inputs'!B1061="","",'Model inputs'!B1061>0))="",FALSE,IF(ISERROR('Model inputs'!B1061>0),'Model inputs'!B1061>0,IF('Model inputs'!B1061="","",'Model inputs'!B1061>0))),1,0) -> 0 | Z33: =IF(IF(IF(ISERROR('Model inputs'!B1095>0),'Model inputs'!B1095>0,IF('Model inputs'!B1095="","",'Model inputs'!B1095>0))="",FALSE,IF(ISERROR('Model inputs'!B1095>0),'Model inputs'!B1095>0,IF('Model inputs'!B1095="","",'Model inputs'!B1095>0))),1,0) -> 0

Sheet Runway summary
A1: Runway summary
A2: AgentBisect — Financial Model · Main Scenario
A4: Variable / dimension | B4: Value
A5: Initial runway months | B5: =SUM('Model inputs'!B1102,'Model inputs'!B1103,'Model inputs'!B1104) -> 13
A6: First cash shortfall month | B6: =IF(IF(IF(ISERROR('Runway summary'!B5<'Editable assumptions'!B15),'Runway summary'!B5<'Editable assumptions'!B15,IF(OR('Runway summary'!B5="",'Editable assumptions'!B15=""),"",'Runway summary'!B5<'Editable assumptions'!B15))="",FALSE,IF(ISERROR('Runway summary'!B5<'Editable assumptions'!B15),'Runway summary'!B5<'Editable assumptions'!B15,IF(OR('Runway summary'!B5="",'Editable assumptions'!B15=""),"",'Runway summary'!B5<'Editable assumptions'!B15))),EDATE('Editable assumptions'!B16,'Runway summary'!B5*1),"") -> 46692
A7: Cash after forecast | B7: =IF('Model inputs'!B1138=0,"",SUM('Model inputs'!B1105,'Model inputs'!B1106,'Model inputs'!B1107,'Model inputs'!B1108,'Model inputs'!B1109,'Model inputs'!B1110,'Model inputs'!B1111,'Model inputs'!B1112,'Model inputs'!B1113,'Model inputs'!B1114,'Model inputs'!B1115,'Model inputs'!B1116,'Model inputs'!B1117,'Model inputs'!B1118,'Model inputs'!B1119,'Model inputs'!B1120,'Model inputs'!B1121,'Model inputs'!B1122,'Model inputs'!B1123,'Model inputs'!B1124,'Model inputs'!B1125,'Model inputs'!B1126,'Model inputs'!B1127,'Model inputs'!B1128,'Model inputs'!B1129,'Model inputs'!B1130,'Model inputs'!B1131,'Model inputs'!B1132,'Model inputs'!B1133,'Model inputs'!B1134,'Model inputs'!B1135,'Model inputs'!B1136,'Model inputs'!B1137)) -> -8300
A8: Lowest forecast cash | B8: =IF(AND('Model inputs'!B1139="",'Model inputs'!B1140="",'Model inputs'!B1141="",'Model inputs'!B1142="",'Model inputs'!B1143="",'Model inputs'!B1144="",'Model inputs'!B1145="",'Model inputs'!B1146="",'Model inputs'!B1147="",'Model inputs'!B1148="",'Model inputs'!B1149="",'Model inputs'!B1150="",'Model inputs'!B1151="",'Model inputs'!B1152="",'Model inputs'!B1153="",'Model inputs'!B1154="",'Model inputs'!B1155="",'Model inputs'!B1156="",'Model inputs'!B1157="",'Model inputs'!B1158="",'Model inputs'!B1159="",'Model inputs'!B1160="",'Model inputs'!B1161="",'Model inputs'!B1162="",'Model inputs'!B1163="",'Model inputs'!B1164="",'Model inputs'!B1165="",'Model inputs'!B1166="",'Model inputs'!B1167="",'Model inputs'!B1168="",'Model inputs'!B1169="",'Model inputs'!B1170="",'Model inputs'!B1171=""),"",MIN('Model inputs'!B1139,'Model inputs'!B1140,'Model inputs'!B1141,'Model inputs'!B1142,'Model inputs'!B1143,'Model inputs'!B1144,'Model inputs'!B1145,'Model inputs'!B1146,'Model inputs'!B1147,'Model inputs'!B1148,'Model inputs'!B1149,'Model inputs'!B1150,'Model inputs'!B1151,'Model inputs'!B1152,'Model inputs'!B1153,'Model inputs'!B1154,'Model inputs'!B1155,'Model inputs'!B1156,'Model inputs'!B1157,'Model inputs'!B1158,'Model inputs'!B1159,'Model inputs'!B1160,'Model inputs'!B1161,'Model inputs'!B1162,'Model inputs'!B1163,'Model inputs'!B1164,'Model inputs'!B1165,'Model inputs'!B1166,'Model inputs'!B1167,'Model inputs'!B1168,'Model inputs'!B1169,'Model inputs'!B1170,'Model inputs'!B1171)) -> -10950
A9: Minimum additional funding | B9: =MAX(-'Runway summary'!B8,0) -> 10950

Sheet Usage and overage sensitivity
A1: Usage and overage sensitivity
A2: AgentBisect — Financial Model · Main Scenario
A4: Variable / dimension | B4: Sensitivity investigations | C4: Sensitivity overage investigations | D4: Sensitivity monthly revenue | E4: Sensitivity variable cost | F4: Sensitivity contribution | G4: Sensitivity contribution margin | H4: Overage unit contribution | I4: Overage unit margin | J4: Sensitivity teams to break even | K4: Sensitivity compute hours per team
A5: Allowance fully used — 100 | B5: =100 -> 100 | C5: =MAX('Usage and overage sensitivity'!B5-'Unit economics by plan'!C6,0) -> 0 | D5: ='Unit economics by plan'!B6+'Usage and overage sensitivity'!C5*'Unit economics by plan'!E6 -> 99 | E5: ='Usage and overage sensitivity'!B5*('Editable assumptions'!B5+'Editable assumptions'!B6) -> 30 | F5: ='Usage and overage sensitivity'!D5-'Usage and overage sensitivity'!E5 -> 69 | G5: =IFERROR('Usage and overage sensitivity'!F5/'Usage and overage sensitivity'!D5,"") -> 0.6969697 | H5: ='Unit economics by plan'!E6-'Editable assumptions'!B5-'Editable assumptions'!B6 -> 0.7 | I5: =IFERROR('Usage and overage sensitivity'!H5/'Unit economics by plan'!E6,"") -> 0.7 | J5: =IF(IF(IF(ISERROR('Usage and overage sensitivity'!F5>0),'Usage and overage sensitivity'!F5>0,IF('Usage and overage sensitivity'!F5="","",'Usage and overage sensitivity'!F5>0))="",FALSE,IF(ISERROR('Usage and overage sensitivity'!F5>0),'Usage and overage sensitivity'!F5>0,IF('Usage and overage sensitivity'!F5="","",'Usage and overage sensitivity'!F5>0))),CEILING(('Editable assumptions'!B9+'Editable assumptions'!B8+'Editable assumptions'!B14*'Unit economics by plan'!H5)/'Usage and overage sensitivity'!F5,1),"") -> 123 | K5: ='Usage and overage sensitivity'!B5*'Editable assumptions'!B7/60 -> 16.666667
A6: Heavy — 300 | B6: =300 -> 300 | C6: =MAX('Usage and overage sensitivity'!B6-'Unit economics by plan'!C6,0) -> 200 | D6: ='Unit economics by plan'!B6+'Usage and overage sensitivity'!C6*'Unit economics by plan'!E6 -> 299 | E6: ='Usage and overage sensitivity'!B6*('Editable assumptions'!B5+'Editable assumptions'!B6) -> 90 | F6: ='Usage and overage sensitivity'!D6-'Usage and overage sensitivity'!E6 -> 209 | G6: =IFERROR('Usage and overage sensitivity'!F6/'Usage and overage sensitivity'!D6,"") -> 0.69899666 | H6: ='Unit economics by plan'!E6-'Editable assumptions'!B5-'Editable assumptions'!B6 -> 0.7 | I6: =IFERROR('Usage and overage sensitivity'!H6/'Unit economics by plan'!E6,"") -> 0.7 | J6: =IF(IF(IF(ISERROR('Usage and overage sensitivity'!F6>0),'Usage and overage sensitivity'!F6>0,IF('Usage and overage sensitivity'!F6="","",'Usage and overage sensitivity'!F6>0))="",FALSE,IF(ISERROR('Usage and overage sensitivity'!F6>0),'Usage and overage sensitivity'!F6>0,IF('Usage and overage sensitivity'!F6="","",'Usage and overage sensitivity'!F6>0))),CEILING(('Editable assumptions'!B9+'Editable assumptions'!B8+'Editable assumptions'!B14*'Unit economics by plan'!H5)/'Usage and overage sensitivity'!F6,1),"") -> 41 | K6: ='Usage and overage sensitivity'!B6*'Editable assumptions'!B7/60 -> 50
A7: Typical — 60 | B7: =60 -> 60 | C7: =MAX('Usage and overage sensitivity'!B7-'Unit economics by plan'!C6,0) -> 0 | D7: ='Unit economics by plan'!B6+'Usage and overage sensitivity'!C7*'Unit economics by plan'!E6 -> 99 | E7: ='Usage and overage sensitivity'!B7*('Editable assumptions'!B5+'Editable assumptions'!B6) -> 18 | F7: ='Usage and overage sensitivity'!D7-'Usage and overage sensitivity'!E7 -> 81 | G7: =IFERROR('Usage and overage sensitivity'!F7/'Usage and overage sensitivity'!D7,"") -> 0.81818182 | H7: ='Unit economics by plan'!E6-'Editable assumptions'!B5-'Editable assumptions'!B6 -> 0.7 | I7: =IFERROR('Usage and overage sensitivity'!H7/'Unit economics by plan'!E6,"") -> 0.7 | J7: =IF(IF(IF(ISERROR('Usage and overage sensitivity'!F7>0),'Usage and overage sensitivity'!F7>0,IF('Usage and overage sensitivity'!F7="","",'Usage and overage sensitivity'!F7>0))="",FALSE,IF(ISERROR('Usage and overage sensitivity'!F7>0),'Usage and overage sensitivity'!F7>0,IF('Usage and overage sensitivity'!F7="","",'Usage and overage sensitivity'!F7>0))),CEILING(('Editable assumptions'!B9+'Editable assumptions'!B8+'Editable assumptions'!B14*'Unit economics by plan'!H5)/'Usage and overage sensitivity'!F7,1),"") -> 105 | K7: ='Usage and overage sensitivity'!B7*'Editable assumptions'!B7/60 -> 10

Sheet Month 12 growth scenario compar
A1: Month 12 growth scenario comparison
A2: AgentBisect — Financial Model · Main Scenario
A4: Variable / dimension | B4: 2027-09 | C4: 2027-09 > AgentBisect — 20 teams at month 12 | D4: 2027-09 > AgentBisect — 100 teams at month 12 | E4: 2027-09 > AgentBisect — 300 teams at month 12
A5: Paying teams | B5: =IF(IF(IF(IF(ISERROR('Monthly forecast and cash'!N5=1),'Monthly forecast and cash'!N5=1,IF('Monthly forecast and cash'!N5="","",'Monthly forecast and cash'!N5=1))="",FALSE,IF(ISERROR('Monthly forecast and cash'!N5=1),'Monthly forecast and cash'!N5=1,IF('Monthly forecast and cash'!N5="","",'Monthly forecast and cash'!N5=1))),IF('Editable assumptions'!B12="","",'Editable assumptions'!B12),IF('Monthly forecast and cash'!M7="","",'Monthly forecast and cash'!M7))="",0,IF(IF(IF(ISERROR('Monthly forecast and cash'!N5=1),'Monthly forecast and cash'!N5=1,IF('Monthly forecast and cash'!N5="","",'Monthly forecast and cash'!N5=1))="",FALSE,IF(ISERROR('Monthly forecast and cash'!N5=1),'Monthly forecast and cash'!N5=1,IF('Monthly forecast and cash'!N5="","",'Monthly forecast and cash'!N5=1))),IF('Editable assumptions'!B12="","",'Editable assumptions'!B12),IF('Monthly forecast and cash'!M7="","",'Monthly forecast and cash'!M7)))+'Monthly forecast and cash'!N6 -> 60 | C5: =ROUND('Model inputs'!C65+('Model inputs'!C54-'Model inputs'!C65)*'Model inputs'!X30/12,0) -> 20 | D5: =ROUND('Model inputs'!C64+('Model inputs'!C53-'Model inputs'!C64)*'Model inputs'!X29/12,0) -> 100 | E5: =ROUND('Model inputs'!C66+('Model inputs'!C55-'Model inputs'!C66)*'Model inputs'!X31/12,0) -> 300
A6: Revenue | B6: =SUM('Monthly forecast and cash'!N13,'Monthly forecast and cash'!N14) -> 5940 | C6: =SUM('Model inputs'!X74,'Model inputs'!X75) -> 1980 | D6: =SUM('Model inputs'!X71,'Model inputs'!X72) -> 9900 | E6: =SUM('Model inputs'!X77,'Model inputs'!X78) -> 29700
A7: Gross margin | B7: =IFERROR('Monthly forecast and cash'!N23/'Month 12 growth scenario compar'!B6,"") -> 0.74242424 | C7: =IFERROR('Model inputs'!X49/'Month 12 growth scenario compar'!C6,"") -> 0.59090909 | D7: =IFERROR('Model inputs'!X48/'Month 12 growth scenario compar'!D6,"") -> 0.77272727 | E7: =IFERROR('Model inputs'!X50/'Month 12 growth scenario compar'!E6,"") -> 0.8030303
A8: Founder pay | B8: =SUM('Monthly forecast and cash'!N26) -> 8000 | C8: =SUM('Model inputs'!X41) -> 8000 | D8: =SUM('Model inputs'!X39) -> 8000 | E8: =SUM('Model inputs'!X43) -> 8000
A9: Operating profit | B9: ='Monthly forecast and cash'!N23-'Month 12 growth scenario compar'!B8 -> -3590 | C9: ='Model inputs'!X49-'Month 12 growth scenario compar'!C8 -> -6830 | D9: ='Model inputs'!X48-'Month 12 growth scenario compar'!D8 -> -350 | E9: ='Model inputs'!X50-'Month 12 growth scenario compar'!E8 -> 15850
A10: Cash balance | B10: ='Monthly forecast and cash'!M29+'Monthly forecast and cash'!N28 -> 3190 | C10: ='Model inputs'!W14+'Model inputs'!X58 -> -17870 | D10: ='Model inputs'!W13+'Model inputs'!X57 -> 24250 | E10: ='Model inputs'!W15+'Model inputs'!X59 -> 129550

Sheet Model inputs
A1: Model inputs
A2: Integration values are aggregated snapshots; raw source records are not included.
A4: Variables
A5: Variable / segment | B5: Value | C5: Value | D5: 2026-01 | E5: 2026-02 | F5: 2026-03 | G5: 2026-04 | H5: 2026-05 | I5: 2026-06 | J5: 2026-07 | K5: 2026-08 | L5: 2026-09 | M5: 2026-10 | N5: 2026-11 | O5: 2026-12 | P5: 2027-01 | Q5: 2027-02 | R5: 2027-03 | S5: 2027-04 | T5: 2027-05 | U5: 2027-06 | V5: 2027-07 | W5: 2027-08 | X5: 2027-09 | Y5: 2027-10 | Z5: 2027-11 | AA5: 2027-12 | AB5: 2028-01 | AC5: 2028-02 | AD5: 2028-03 | AE5: 2028-04 | AF5: 2028-05 | AG5: 2028-06 | AH5: 2028-07 | AI5: 2028-08 | AJ5: 2028-09
A6: Average investigations | B6: 0
A7: Average investigations > Free | B7: ='Unit economics by plan'!D5 -> 10
A8: Average investigations > Team | B8: ='Unit economics by plan'!D6 -> 60
A9: Average investigations | C9: 0
A10: Average investigations > Free | C10: ='Unit economics by plan'!D5 -> 10
A11: Average investigations > Team | C11: ='Unit economics by plan'!D6 -> 60
A12: Cash balance · Monthly forecast and cash · Main Scenario | D12: 0 | E12: 0 | F12: 0 | G12: 0 | H12: 0 | I12: 0 | J12: 0 | K12: 0 | L12: =IF('Model inputs'!C85="","",'Model inputs'!C85) -> 25000 | M12: ='Model inputs'!L12+'Model inputs'!M56 -> 24955 | N12: ='Model inputs'!M12+'Model inputs'!N56 -> 25315 | O12: ='Model inputs'!N12+'Model inputs'!O56 -> 26080 | P12: ='Model inputs'!O12+'Model inputs'!P56 -> 27250 | Q12: ='Model inputs'!P12+'Model inputs'!Q56 -> 28825 | R12: ='Model inputs'!Q12+'Model inputs'!R56 -> 30805 | S12: ='Model inputs'!R12+'Model inputs'!S56 -> 25190 | T12: ='Model inputs'!S12+'Model inputs'!T56 -> 19980 | ... AJ12: ='Model inputs'!AI12+'Model inputs'!AJ56 -> -8300
A13: Cash balance · AgentBisect — 100 teams at month 12 | L13: =IF('Model inputs'!C162="","",'Model inputs'!C162) -> 25000 | M13: ='Model inputs'!L13+'Model inputs'!M57 -> 25198 | N13: ='Model inputs'!M13+'Model inputs'!N57 -> 26125 | O13: ='Model inputs'!N13+'Model inputs'!O57 -> 27700 | P13: ='Model inputs'!O13+'Model inputs'!P57 -> 29923 | Q13: ='Model inputs'!P13+'Model inputs'!Q57 -> 32875 | R13: ='Model inputs'!Q13+'Model inputs'!R57 -> 36475 | S13: ='Model inputs'!R13+'Model inputs'!S57 -> 32723 | T13: ='Model inputs'!S13+'Model inputs'!T57 -> 29700 | ... X13: ='Model inputs'!W13+'Model inputs'!X57 -> 24250
A14: Cash balance · AgentBisect — 20 teams at month 12 | L14: =IF('Model inputs'!C163="","",'Model inputs'!C163) -> 25000 | M14: ='Model inputs'!L14+'Model inputs'!M58 -> 24712 | N14: ='Model inputs'!M14+'Model inputs'!N58 -> 24505 | O14: ='Model inputs'!N14+'Model inputs'!O58 -> 24460 | P14: ='Model inputs'!O14+'Model inputs'!P58 -> 24577 | Q14: ='Model inputs'!P14+'Model inputs'!Q58 -> 24775 | R14: ='Model inputs'!Q14+'Model inputs'!R58 -> 25135 | S14: ='Model inputs'!R14+'Model inputs'!S58 -> 17657 | T14: ='Model inputs'!S14+'Model inputs'!T58 -> 10260 | ... X14: ='Model inputs'!W14+'Model inputs'!X58 -> -17870
A15: Cash balance · AgentBisect — 300 teams at month 12 | L15: =IF('Model inputs'!C164="","",'Model inputs'!C164) -> 25000 | M15: ='Model inputs'!L15+'Model inputs'!M59 -> 26575 | N15: ='Model inputs'!M15+'Model inputs'!N59 -> 30175 | O15: ='Model inputs'!N15+'Model inputs'!O59 -> 35800 | P15: ='Model inputs'!O15+'Model inputs'!P59 -> 43450 | Q15: ='Model inputs'!P15+'Model inputs'!Q59 -> 53125 | R15: ='Model inputs'!Q15+'Model inputs'!R59 -> 64825 | S15: ='Model inputs'!R15+'Model inputs'!S59 -> 70550 | T15: ='Model inputs'!S15+'Model inputs'!T59 -> 78300 | ... X15: ='Model inputs'!W15+'Model inputs'!X59 -> 129550
A16: Compute cost per investigation · Unit economics by plan | B16: ='Editable assumptions'!B6 -> 0.05
A17: Compute cost per investigation · Monthly forecast and cash | C17: ='Editable assumptions'!B6 -> 0.05
A18: Compute minutes per investigation · Unit economics by plan | B18: ='Editable assumptions'!B7 -> 10
A19: Compute minutes per investigation · Monthly forecast and cash | C19: ='Editable assumptions'!B7 -> 10
A20: Contribution per repo | B20: ='Model inputs'!B79-'Model inputs'!B87 -> 0
A21: Contribution per repo > Free | B21: ='Model inputs'!B80-'Model inputs'!B88 -> -3
A22: Contribution per repo > Team | B22: ='Model inputs'!B81-'Model inputs'!B89 -> 81
A23: Contribution per repo | C23: ='Model inputs'!B79-'Model inputs'!B87 -> 0
A24: Contribution per repo > Free | C24: ='Model inputs'!B80-'Model inputs'!B88 -> -3
A25: Contribution per repo > Team | C25: ='Model inputs'!B81-'Model inputs'!B89 -> 81
A26: Fixed hosting · Monthly forecast and cash | C26: ='Editable assumptions'!B8 -> 300
A27: Fixed hosting · Runway summary | B27: ='Editable assumptions'!B8 -> 300
A28: Forecast month number · Monthly forecast and cash · Main Scenario | D28: 0 | E28: 0 | F28: 0 | G28: 0 | H28: 0 | I28: 0 | J28: 0 | K28: 0 | L28: 0 | M28: =DATEDIF('Model inputs'!C32,DATE(2026,10,1),"M")+1 -> 1 | N28: =DATEDIF('Model inputs'!C32,DATE(2026,11,1),"M")+1 -> 2 | O28: =DATEDIF('Model inputs'!C32,DATE(2026,12,1),"M")+1 -> 3 | P28: =DATEDIF('Model inputs'!C32,DATE(2027,1,1),"M")+1 -> 4 | Q28: =DATEDIF('Model inputs'!C32,DATE(2027,2,1),"M")+1 -> 5 | R28: =DATEDIF('Model inputs'!C32,DATE(2027,3,1),"M")+1 -> 6 | S28: =DATEDIF('Model inputs'!C32,DATE(2027,4,1),"M")+1 -> 7 | T28: =DATEDIF('Model inputs'!C32,DATE(2027,5,1),"M")+1 -> 8 | U28: =DATEDIF('Model inputs'!C32,DATE(2027,6,1),"M")+1 -> 9 | V28: =DATEDIF('Model inputs'!C32,DATE(2027,7,1),"M")+1 -> 10 | W28: =DATEDIF('Model inputs'!C32,DATE(2027,8,1),"M")+1 -> 11 | X28: =DATEDIF('Model inputs'!C32,DATE(2027,9,1),"M")+1 -> 12 | Y28: =DATEDIF('Model inputs'!C32,DATE(2027,10,1),"M")+1 -> 13 | Z28: =DATEDIF('Model inputs'!C32,DATE(2027,11,1),"M")+1 -> 14 | AA28: =DATEDIF('Model inputs'!C32,DATE(2027,12,1),"M")+1 -> 15 | AB28: =DATEDIF('Model inputs'!C32,DATE(2028,1,1),"M")+1 -> 16 | AC28: =DATEDIF('Model inputs'!C32,DATE(2028,2,1),"M")+1 -> 17 | AD28: =DATEDIF('Model inputs'!C32,DATE(2028,3,1),"M")+1 -> 18 | AE28: =DATEDIF('Model inputs'!C32,DATE(2028,4,1),"M")+1 -> 19 | AF28: =DATEDIF('Model inputs'!C32,DATE(2028,5,1),"M")+1 -> 20 | AG28: =DATEDIF('Model inputs'!C32,DATE(2028,6,1),"M")+1 -> 21 | AH28: =DATEDIF('Model inputs'!C32,DATE(2028,7,1),"M")+1 -> 22 | AI28: =DATEDIF('Model inputs'!C32,DATE(2028,8,1),"M")+1 -> 23 | AJ28: =DATEDIF('Model inputs'!C32,DATE(2028,9,1),"M")+1 -> 24
A29: Forecast month number · AgentBisect — 100 teams at month 12 | L29: 0 | M29: =DATEDIF('Model inputs'!C121,DATE(2026,10,1),"M")+1 -> 1 | N29: =DATEDIF('Model inputs'!C121,DATE(2026,11,1),"M")+1 -> 2 | O29: =DATEDIF('Model inputs'!C121,DATE(2026,12,1),"M")+1 -> 3 | P29: =DATEDIF('Model inputs'!C121,DATE(2027,1,1),"M")+1 -> 4 | Q29: =DATEDIF('Model inputs'!C121,DATE(2027,2,1),"M")+1 -> 5 | R29: =DATEDIF('Model inputs'!C121,DATE(2027,3,1),"M")+1 -> 6 | S29: =DATEDIF('Model inputs'!C121,DATE(2027,4,1),"M")+1 -> 7 | T29: =DATEDIF('Model inputs'!C121,DATE(2027,5,1),"M")+1 -> 8 | U29: =DATEDIF('Model inputs'!C121,DATE(2027,6,1),"M")+1 -> 9 | V29: =DATEDIF('Model inputs'!C121,DATE(2027,7,1),"M")+1 -> 10 | W29: =DATEDIF('Model inputs'!C121,DATE(2027,8,1),"M")+1 -> 11 | X29: =DATEDIF('Model inputs'!C121,DATE(2027,9,1),"M")+1 -> 12
A30: Forecast month number · AgentBisect — 20 teams at month 12 | L30: 0 | M30: =DATEDIF('Model inputs'!C122,DATE(2026,10,1),"M")+1 -> 1 | N30: =DATEDIF('Model inputs'!C122,DATE(2026,11,1),"M")+1 -> 2 | O30: =DATEDIF('Model inputs'!C122,DATE(2026,12,1),"M")+1 -> 3 | P30: =DATEDIF('Model inputs'!C122,DATE(2027,1,1),"M")+1 -> 4 | Q30: =DATEDIF('Model inputs'!C122,DATE(2027,2,1),"M")+1 -> 5 | R30: =DATEDIF('Model inputs'!C122,DATE(2027,3,1),"M")+1 -> 6 | S30: =DATEDIF('Model inputs'!C122,DATE(2027,4,1),"M")+1 -> 7 | T30: =DATEDIF('Model inputs'!C122,DATE(2027,5,1),"M")+1 -> 8 | U30: =DATEDIF('Model inputs'!C122,DATE(2027,6,1),"M")+1 -> 9 | V30: =DATEDIF('Model inputs'!C122,DATE(2027,7,1),"M")+1 -> 10 | W30: =DATEDIF('Model inputs'!C122,DATE(2027,8,1),"M")+1 -> 11 | X30: =DATEDIF('Model inputs'!C122,DATE(2027,9,1),"M")+1 -> 12
A31: Forecast month number · AgentBisect — 300 teams at month 12 | L31: 0 | M31: =DATEDIF('Model inputs'!C123,DATE(2026,10,1),"M")+1 -> 1 | N31: =DATEDIF('Model inputs'!C123,DATE(2026,11,1),"M")+1 -> 2 | O31: =DATEDIF('Model inputs'!C123,DATE(2026,12,1),"M")+1 -> 3 | P31: =DATEDIF('Model inputs'!C123,DATE(2027,1,1),"M")+1 -> 4 | Q31: =DATEDIF('Model inputs'!C123,DATE(2027,2,1),"M")+1 -> 5 | R31: =DATEDIF('Model inputs'!C123,DATE(2027,3,1),"M")+1 -> 6 | S31: =DATEDIF('Model inputs'!C123,DATE(2027,4,1),"M")+1 -> 7 | T31: =DATEDIF('Model inputs'!C123,DATE(2027,5,1),"M")+1 -> 8 | U31: =DATEDIF('Model inputs'!C123,DATE(2027,6,1),"M")+1 -> 9 | V31: =DATEDIF('Model inputs'!C123,DATE(2027,7,1),"M")+1 -> 10 | W31: =DATEDIF('Model inputs'!C123,DATE(2027,8,1),"M")+1 -> 11 | X31: =DATEDIF('Model inputs'!C123,DATE(2027,9,1),"M")+1 -> 12
A32: Forecast start · Monthly forecast and cash | C32: =DATE(2026,10,1) -> 46296
A33: Forecast start · Runway summary | B33: =DATE(2026,10,1) -> 46296
A34: Founder monthly salary · Monthly forecast and cash | C34: ='Editable assumptions'!B9 -> 8000
A35: Founder monthly salary · Runway summary | B35: ='Editable assumptions'!B9 -> 8000
A36: Founder pay | L36: =SUM('Model inputs'!L37) -> 0 | M36: =SUM('Model inputs'!M37) -> 0 | N36: =SUM('Model inputs'!N37) -> 0 | O36: =SUM('Model inputs'!O37) -> 0 | P36: =SUM('Model inputs'!P37) -> 0 | Q36: =SUM('Model inputs'!Q37) -> 0 | R36: =SUM('Model inputs'!R37) -> 0 | S36: =SUM('Model inputs'!S37) -> 8000 | ... AJ36: =SUM('Model inputs'!AJ37) -> 8000
A37: Founder pay > Founder — sole operator | L37: ='Monthly forecast and cash'!B26 -> 0 | M37: =IF(IF(IF(ISERROR('Model inputs'!M28<='Model inputs'!C86),'Model inputs'!M28<='Model inputs'!C86,IF(OR('Model inputs'!M28="",'Model inputs'!C86=""),"",'Model inputs'!M28<='Model inputs'!C86))="",FALSE,IF(ISERROR('Model inputs'!M28<='Model inputs'!C86),'Model inputs'!M28<='Model inputs'!C86,IF(OR('Model inputs'!M28="",'Model inputs'!C86=""),"",'Model inputs'!M28<='Model inputs'!C86))),0,IF('Model inputs'!C34="","",'Model inputs'!C34)) -> 0 | N37: =IF(IF(IF(ISERROR('Model inputs'!N28<='Model inputs'!C86),'Model inputs'!N28<='Model inputs'!C86,IF(OR('Model inputs'!N28="",'Model inputs'!C86=""),"",'Model inputs'!N28<='Model inputs'!C86))="",FALSE,IF(ISERROR('Model inputs'!N28<='Model inputs'!C86),'Model inputs'!N28<='Model inputs'!C86,IF(OR('Model inputs'!N28="",'Model inputs'!C86=""),"",'Model inputs'!N28<='Model inputs'!C86))),0,IF('Model inputs'!C34="","",'Model inputs'!C34)) -> 0 | O37: =IF(IF(IF(ISERROR('Model inputs'!O28<='Model inputs'!C86),'Model inputs'!O28<='Model inputs'!C86,IF(OR('Model inputs'!O28="",'Model inputs'!C86=""),"",'Model inputs'!O28<='Model inputs'!C86))="",FALSE,IF(ISERROR('Model inputs'!O28<='Model inputs'!C86),'Model inputs'!O28<='Model inputs'!C86,IF(OR('Model inputs'!O28="",'Model inputs'!C86=""),"",'Model inputs'!O28<='Model inputs'!C86))),0,IF('Model inputs'!C34="","",'Model inputs'!C34)) -> 0 | P37: =IF(IF(IF(ISERROR('Model inputs'!P28<='Model inputs'!C86),'Model inputs'!P28<='Model inputs'!C86,IF(OR('Model inputs'!P28="",'Model inputs'!C86=""),"",'Model inputs'!P28<='Model inputs'!C86))="",FALSE,IF(ISERROR('Model inputs'!P28<='Model inputs'!C86),'Model inputs'!P28<='Model inputs'!C86,IF(OR('Model inputs'!P28="",'Model inputs'!C86=""),"",'Model inputs'!P28<='Model inputs'!C86))),0,IF('Model inputs'!C34="","",'Model inputs'!C34)) -> 0 | Q37: =IF(IF(IF(ISERROR('Model inputs'!Q28<='Model inputs'!C86),'Model inputs'!Q28<='Model inputs'!C86,IF(OR('Model inputs'!Q28="",'Model inputs'!C86=""),"",'Model inputs'!Q28<='Model inputs'!C86))="",FALSE,IF(ISERROR('Model inputs'!Q28<='Model inputs'!C86),'Model inputs'!Q28<='Model inputs'!C86,IF(OR('Model inputs'!Q28="",'Model inputs'!C86=""),"",'Model inputs'!Q28<='Model inputs'!C86))),0,IF('Model inputs'!C34="","",'Model inputs'!C34)) -> 0 | R37: =IF(IF(IF(ISERROR('Model inputs'!R28<='Model inputs'!C86),'Model inputs'!R28<='Model inputs'!C86,IF(OR('Model inputs'!R28="",'Model inputs'!C86=""),"",'Model inputs'!R28<='Model inputs'!C86))="",FALSE,IF(ISERROR('Model inputs'!R28<='Model inputs'!C86),'Model inputs'!R28<='Model inputs'!C86,IF(OR('Model inputs'!R28="",'Model inputs'!C86=""),"",'Model inputs'!R28<='Model inputs'!C86))),0,IF('Model inputs'!C34="","",'Model inputs'!C34)) -> 0 | S37: =IF(IF(IF(ISERROR('Model inputs'!S28<='Model inputs'!C86),'Model inputs'!S28<='Model inputs'!C86,IF(OR('Model inputs'!S28="",'Model inputs'!C86=""),"",'Model inputs'!S28<='Model inputs'!C86))="",FALSE,IF(ISERROR('Model inputs'!S28<='Model inputs'!C86),'Model inputs'!S28<='Model inputs'!C86,IF(OR('Model inputs'!S28="",'Model inputs'!C86=""),"",'Model inputs'!S28<='Model inputs'!C86))),0,IF('Model inputs'!C34="","",'Model inputs'!C34)) -> 8000 | T37: =IF(IF(IF(ISERROR('Model inputs'!T28<='Model inputs'!C86),'Model inputs'!T28<='Model inputs'!C86,IF(OR('Model inputs'!T28="",'Model inputs'!C86=""),"",'Model inputs'!T28<='Model inputs'!C86))="",FALSE,IF(ISERROR('Model inputs'!T28<='Model inputs'!C86),'Model inputs'!T28<='Model inputs'!C86,IF(OR('Model inputs'!T28="",'Model inputs'!C86=""),"",'Model inputs'!T28<='Model inputs'!C86))),0,IF('Model inputs'!C34="","",'Model inputs'!C34)) -> 8000 | U37: =IF(IF(IF(ISERROR('Model inputs'!U28<='Model inputs'!C86),'Model inputs'!U28<='Model inputs'!C86,IF(OR('Model inputs'!U28="",'Model inputs'!C86=""),"",'Model inputs'!U28<='Model inputs'!C86))="",FALSE,IF(ISERROR('Model inputs'!U28<='Model inputs'!C86),'Model inputs'!U28<='Model inputs'!C86,IF(OR('Model inputs'!U28="",'Model inputs'!C86=""),"",'Model inputs'!U28<='Model inputs'!C86))),0,IF('Model inputs'!C34="","",'Model inputs'!C34)) -> 8000 | V37: =IF(IF(IF(ISERROR('Model inputs'!V28<='Model inputs'!C86),'Model inputs'!V28<='Model inputs'!C86,IF(OR('Model inputs'!V28="",'Model inputs'!C86=""),"",'Model inputs'!V28<='Model inputs'!C86))="",FALSE,IF(ISERROR('Model inputs'!V28<='Model inputs'!C86),'Model inputs'!V28<='Model inputs'!C86,IF(OR('Model inputs'!V28="",'Model inputs'!C86=""),"",'Model inputs'!V28<='Model inputs'!C86))),0,IF('Model inputs'!C34="","",'Model inputs'!C34)) -> 8000 | W37: =IF(IF(IF(ISERROR('Model inputs'!W28<='Model inputs'!C86),'Model inputs'!W28<='Model inputs'!C86,IF(OR('Model inputs'!W28="",'Model inputs'!C86=""),"",'Model inputs'!W28<='Model inputs'!C86))="",FALSE,IF(ISERROR('Model inputs'!W28<='Model inputs'!C86),'Model inputs'!W28<='Model inputs'!C86,IF(OR('Model inputs'!W28="",'Model inputs'!C86=""),"",'Model inputs'!W28<='Model inputs'!C86))),0,IF('Model inputs'!C34="","",'Model inputs'!C34)) -> 8000 | X37: =IF(IF(IF(ISERROR('Model inputs'!X28<='Model inputs'!C86),'Model inputs'!X28<='Model inputs'!C86,IF(OR('Model inputs'!X28="",'Model inputs'!C86=""),"",'Model inputs'!X28<='Model inputs'!C86))="",FALSE,IF(ISERROR('Model inputs'!X28<='Model inputs'!C86),'Model inputs'!X28<='Model inputs'!C86,IF(OR('Model inputs'!X28="",'Model inputs'!C86=""),"",'Model inputs'!X28<='Model inputs'!C86))),0,IF('Model inputs'!C34="","",'Model inputs'!C34)) -> 8000 | Y37: =IF(IF(IF(ISERROR('Model inputs'!Y28<='Model inputs'!C86),'Model inputs'!Y28<='Model inputs'!C86,IF(OR('Model inputs'!Y28="",'Model inputs'!C86=""),"",'Model inputs'!Y28<='Model inputs'!C86))="",FALSE,IF(ISERROR('Model inputs'!Y28<='Model inputs'!C86),'Model inputs'!Y28<='Model inputs'!C86,IF(OR('Model inputs'!Y28="",'Model inputs'!C86=""),"",'Model inputs'!Y28<='Model inputs'!C86))),0,IF('Model inputs'!C34="","",'Model inputs'!C34)) -> 8000 | Z37: =IF(IF(IF(ISERROR('Model inputs'!Z28<='Model inputs'!C86),'Model inputs'!Z28<='Model inputs'!C86,IF(OR('Model inputs'!Z28="",'Model inputs'!C86=""),"",'Model inputs'!Z28<='Model inputs'!C86))="",FALSE,IF(ISERROR('Model inputs'!Z28<='Model inputs'!C86),'Model inputs'!Z28<='Model inputs'!C86,IF(OR('Model inputs'!Z28="",'Model inputs'!C86=""),"",'Model inputs'!Z28<='Model inputs'!C86))),0,IF('Model inputs'!C34="","",'Model inputs'!C34)) -> 8000 | AA37: =IF(IF(IF(ISERROR('Model inputs'!AA28<='Model inputs'!C86),'Model inputs'!AA28<='Model inputs'!C86,IF(OR('Model inputs'!AA28="",'Model inputs'!C86=""),"",'Model inputs'!AA28<='Model inputs'!C86))="",FALSE,IF(ISERROR('Model inputs'!AA28<='Model inputs'!C86),'Model inputs'!AA28<='Model inputs'!C86,IF(OR('Model inputs'!AA28="",'Model inputs'!C86=""),"",'Model inputs'!AA28<='Model inputs'!C86))),0,IF('Model inputs'!C34="","",'Model inputs'!C34)) -> 8000 | AB37: =IF(IF(IF(ISERROR('Model inputs'!AB28<='Model inputs'!C86),'Model inputs'!AB28<='Model inputs'!C86,IF(OR('Model inputs'!AB28="",'Model inputs'!C86=""),"",'Model inputs'!AB28<='Model inputs'!C86))="",FALSE,IF(ISERROR('Model inputs'!AB28<='Model inputs'!C86),'Model inputs'!AB28<='Model inputs'!C86,IF(OR('Model inputs'!AB28="",'Model inputs'!C86=""),"",'Model inputs'!AB28<='Model inputs'!C86))),0,IF('Model inputs'!C34="","",'Model inputs'!C34)) -> 8000 | AC37: =IF(IF(IF(ISERROR('Model inputs'!AC28<='Model inputs'!C86),'Model inputs'!AC28<='Model inputs'!C86,IF(OR('Model inputs'!AC28="",'Model inputs'!C86=""),"",'Model inputs'!AC28<='Model inputs'!C86))="",FALSE,IF(ISERROR('Model inputs'!AC28<='Model inputs'!C86),'Model inputs'!AC28<='Model inputs'!C86,IF(OR('Model inputs'!AC28="",'Model inputs'!C86=""),"",'Model inputs'!AC28<='Model inputs'!C86))),0,IF('Model inputs'!C34="","",'Model inputs'!C34)) -> 8000 | AD37: =IF(IF(IF(ISERROR('Model inputs'!AD28<='Model inputs'!C86),'Model inputs'!AD28<='Model inputs'!C86,IF(OR('Model inputs'!AD28="",'Model inputs'!C86=""),"",'Model inputs'!AD28<='Model inputs'!C86))="",FALSE,IF(ISERROR('Model inputs'!AD28<='Model inputs'!C86),'Model inputs'!AD28<='Model inputs'!C86,IF(OR('Model inputs'!AD28="",'Model inputs'!C86=""),"",'Model inputs'!AD28<='Model inputs'!C86))),0,IF('Model inputs'!C34="","",'Model inputs'!C34)) -> 8000 | AE37: =IF(IF(IF(ISERROR('Model inputs'!AE28<='Model inputs'!C86),'Model inputs'!AE28<='Model inputs'!C86,IF(OR('Model inputs'!AE28="",'Model inputs'!C86=""),"",'Model inputs'!AE28<='Model inputs'!C86))="",FALSE,IF(ISERROR('Model inputs'!AE28<='Model inputs'!C86),'Model inputs'!AE28<='Model inputs'!C86,IF(OR('Model inputs'!AE28="",'Model inputs'!C86=""),"",'Model inputs'!AE28<='Model inputs'!C86))),0,IF('Model inputs'!C34="","",'Model inputs'!C34)) -> 8000 | AF37: =IF(IF(IF(ISERROR('Model inputs'!AF28<='Model inputs'!C86),'Model inputs'!AF28<='Model inputs'!C86,IF(OR('Model inputs'!AF28="",'Model inputs'!C86=""),"",'Model inputs'!AF28<='Model inputs'!C86))="",FALSE,IF(ISERROR('Model inputs'!AF28<='Model inputs'!C86),'Model inputs'!AF28<='Model inputs'!C86,IF(OR('Model inputs'!AF28="",'Model inputs'!C86=""),"",'Model inputs'!AF28<='Model inputs'!C86))),0,IF('Model inputs'!C34="","",'Model inputs'!C34)) -> 8000 | AG37: =IF(IF(IF(ISERROR('Model inputs'!AG28<='Model inputs'!C86),'Model inputs'!AG28<='Model inputs'!C86,IF(OR('Model inputs'!AG28="",'Model inputs'!C86=""),"",'Model inputs'!AG28<='Model inputs'!C86))="",FALSE,IF(ISERROR('Model inputs'!AG28<='Model inputs'!C86),'Model inputs'!AG28<='Model inputs'!C86,IF(OR('Model inputs'!AG28="",'Model inputs'!C86=""),"",'Model inputs'!AG28<='Model inputs'!C86))),0,IF('Model inputs'!C34="","",'Model inputs'!C34)) -> 8000 | AH37: =IF(IF(IF(ISERROR('Model inputs'!AH28<='Model inputs'!C86),'Model inputs'!AH28<='Model inputs'!C86,IF(OR('Model inputs'!AH28="",'Model inputs'!C86=""),"",'Model inputs'!AH28<='Model inputs'!C86))="",FALSE,IF(ISERROR('Model inputs'!AH28<='Model inputs'!C86),'Model inputs'!AH28<='Model inputs'!C86,IF(OR('Model inputs'!AH28="",'Model inputs'!C86=""),"",'Model inputs'!AH28<='Model inputs'!C86))),0,IF('Model inputs'!C34="","",'Model inputs'!C34)) -> 8000 | AI37: =IF(IF(IF(ISERROR('Model inputs'!AI28<='Model inputs'!C86),'Model inputs'!AI28<='Model inputs'!C86,IF(OR('Model inputs'!AI28="",'Model inputs'!C86=""),"",'Model inputs'!AI28<='Model inputs'!C86))="",FALSE,IF(ISERROR('Model inputs'!AI28<='Model inputs'!C86),'Model inputs'!AI28<='Model inputs'!C86,IF(OR('Model inputs'!AI28="",'Model inputs'!C86=""),"",'Model inputs'!AI28<='Model inputs'!C86))),0,IF('Model inputs'!C34="","",'Model inputs'!C34)) -> 8000 | AJ37: =IF(IF(IF(ISERROR('Model inputs'!AJ28<='Model inputs'!C86),'Model inputs'!AJ28<='Model inputs'!C86,IF(OR('Model inputs'!AJ28="",'Model inputs'!C86=""),"",'Model inputs'!AJ28<='Model inputs'!C86))="",FALSE,IF(ISERROR('Model inputs'!AJ28<='Model inputs'!C86),'Model inputs'!AJ28<='Model inputs'!C86,IF(OR('Model inputs'!AJ28="",'Model inputs'!C86=""),"",'Model inputs'!AJ28<='Model inputs'!C86))),0,IF('Model inputs'!C34="","",'Model inputs'!C34)) -> 8000
A38: Founder pay | X38: =SUM('Model inputs'!X39) -> 8000
A39: Founder pay > Founder — sole operator | X39: =IF(IF(IF(ISERROR('Model inputs'!X29<='Model inputs'!C165),'Model inputs'!X29<='Model inputs'!C165,IF(OR('Model inputs'!X29="",'Model inputs'!C165=""),"",'Model inputs'!X29<='Model inputs'!C165))="",FALSE,IF(ISERROR('Model inputs'!X29<='Model inputs'!C165),'Model inputs'!X29<='Model inputs'!C165,IF(OR('Model inputs'!X29="",'Model inputs'!C165=""),"",'Model inputs'!X29<='Model inputs'!C165))),0,IF('Model inputs'!C124="","",'Model inputs'!C124)) -> 8000
A40: Founder pay | X40: =SUM('Model inputs'!X41) -> 8000
A41: Founder pay > Founder — sole operator | X41: =IF(IF(IF(ISERROR('Model inputs'!X30<='Model inputs'!C166),'Model inputs'!X30<='Model inputs'!C166,IF(OR('Model inputs'!X30="",'Model inputs'!C166=""),"",'Model inputs'!X30<='Model inputs'!C166))="",FALSE,IF(ISERROR('Model inputs'!X30<='Model inputs'!C166),'Model inputs'!X30<='Model inputs'!C166,IF(OR('Model inputs'!X30="",'Model inputs'!C166=""),"",'Model inputs'!X30<='Model inputs'!C166))),0,IF('Model inputs'!C125="","",'Model inputs'!C125)) -> 8000
A42: Founder pay | X42: =SUM('Model inputs'!X43) -> 8000
A43: Founder pay > Founder — sole operator | X43: =IF(IF(IF(ISERROR('Model inputs'!X31<='Model inputs'!C167),'Model inputs'!X31<='Model inputs'!C167,IF(OR('Model inputs'!X31="",'Model inputs'!C167=""),"",'Model inputs'!X31<='Model inputs'!C167))="",FALSE,IF(ISERROR('Model inputs'!X31<='Model inputs'!C167),'Model inputs'!X31<='Model inputs'!C167,IF(OR('Model inputs'!X31="",'Model inputs'!C167=""),"",'Model inputs'!X31<='Model inputs'!C167))),0,IF('Model inputs'!C126="","",'Model inputs'!C126)) -> 8000
A44: Free repos · Monthly forecast and cash | C44: ='Editable assumptions'!B14 -> 50
A45: Free repos · Runway summary | B45: ='Editable assumptions'!B14 -> 50
A46: Fully funded month | D46: 0 | E46: 0 | F46: 0 | G46: 0 | H46: 0 | I46: 0 | J46: 0 | K46: 0 | L46: 0 | M46: =IF(IF(IF(ISERROR('Model inputs'!B1205>0),'Model inputs'!B1205>0,IF('Model inputs'!B1205="","",'Model inputs'!B1205>0))="",FALSE,IF(ISERROR('Model inputs'!B1205>0),'Model inputs'!B1205>0,IF('Model inputs'!B1205="","",'Model inputs'!B1205>0))),1,0) -> 1 | N46: =IF(IF(IF(ISERROR('Model inputs'!B1239>0),'Model inputs'!B1239>0,IF('Model inputs'!B1239="","",'Model inputs'!B1239>0))="",FALSE,IF(ISERROR('Model inputs'!B1239>0),'Model inputs'!B1239>0,IF('Model inputs'!B1239="","",'Model inputs'!B1239>0))),1,0) -> 1 | O46: =IF(IF(IF(ISERROR('Model inputs'!B1273>0),'Model inputs'!B1273>0,IF('Model inputs'!B1273="","",'Model inputs'!B1273>0))="",FALSE,IF(ISERROR('Model inputs'!B1273>0),'Model inputs'!B1273>0,IF('Model inputs'!B1273="","",'Model inputs'!B1273>0))),1,0) -> 1 | P46: =IF(IF(IF(ISERROR('Model inputs'!B1307>0),'Model inputs'!B1307>0,IF('Model inputs'!B1307="","",'Model inputs'!B1307>0))="",FALSE,IF(ISERROR('Model inputs'!B1307>0),'Model inputs'!B1307>0,IF('Model inputs'!B1307="","",'Model inputs'!B1307>0))),1,0) -> 1 | Q46: =IF(IF(IF(ISERROR('Model inputs'!B1341>0),'Model inputs'!B1341>0,IF('Model inputs'!B1341="","",'Model inputs'!B1341>0))="",FALSE,IF(ISERROR('Model inputs'!B1341>0),'Model inputs'!B1341>0,IF('Model inputs'!B1341="","",'Model inputs'!B1341>0))),1,0) -> 1 | R46: =IF(IF(IF(ISERROR('Model inputs'!B1375>0),'Model inputs'!B1375>0,IF('Model inputs'!B1375="","",'Model inputs'!B1375>0))="",FALSE,IF(ISERROR('Model inputs'!B1375>0),'Model inputs'!B1375>0,IF('Model inputs'!B1375="","",'Model inputs'!B1375>0))),1,0) -> 1 | S46: =IF(IF(IF(ISERROR('Model inputs'!B1409>0),'Model inputs'!B1409>0,IF('Model inputs'!B1409="","",'Model inputs'!B1409>0))="",FALSE,IF(ISERROR('Model inputs'!B1409>0),'Model inputs'!B1409>0,IF('Model inputs'!B1409="","",'Model inputs'!B1409>0))),1,0) -> 1 | T46: =IF(IF(IF(ISERROR('Model inputs'!B1443>0),'Model inputs'!B1443>0,IF('Model inputs'!B1443="","",'Model inputs'!B1443>0))="",FALSE,IF(ISERROR('Model inputs'!B1443>0),'Model inputs'!B1443>0,IF('Model inputs'!B1443="","",'Model inputs'!B1443>0))),1,0) -> 1 | U46: =IF(IF(IF(ISERROR('Model inputs'!B1477>0),'Model inputs'!B1477>0,IF('Model inputs'!B1477="","",'Model inputs'!B1477>0))="",FALSE,IF(ISERROR('Model inputs'!B1477>0),'Model inputs'!B1477>0,IF('Model inputs'!B1477="","",'Model inputs'!B1477>0))),1,0) -> 1 | V46: =IF(IF(IF(ISERROR('Model inputs'!B1511>0),'Model inputs'!B1511>0,IF('Model inputs'!B1511="","",'Model inputs'!B1511>0))="",FALSE,IF(ISERROR('Model inputs'!B1511>0),'Model inputs'!B1511>0,IF('Model inputs'!B1511="","",'Model inputs'!B1511>0))),1,0) -> 1 | W46: =IF(IF(IF(ISERROR('Model inputs'!B1545>0),'Model inputs'!B1545>0,IF('Model inputs'!B1545="","",'Model inputs'!B1545>0))="",FALSE,IF(ISERROR('Model inputs'!B1545>0),'Model inputs'!B1545>0,IF('Model inputs'!B1545="","",'Model inputs'!B1545>0))),1,0) -> 1 | X46: =IF(IF(IF(ISERROR('Model inputs'!B1579>0),'Model inputs'!B1579>0,IF('Model inputs'!B1579="","",'Model inputs'!B1579>0))="",FALSE,IF(ISERROR('Model inputs'!B1579>0),'Model inputs'!B1579>0,IF('Model inputs'!B1579="","",'Model inputs'!B1579>0))),1,0) -> 1 | Y46: =IF(IF(IF(ISERROR('Model inputs'!B1613>0),'Model inputs'!B1613>0,IF('Model inputs'!B1613="","",'Model inputs'!B1613>0))="",FALSE,IF(ISERROR('Model inputs'!B1613>0),'Model inputs'!B1613>0,IF('Model inputs'!B1613="","",'Model inputs'!B1613>0))),1,0) -> 1 | Z46: =IF(IF(IF(ISERROR('Model inputs'!B1647>0),'Model inputs'!B1647>0,IF('Model inputs'!B1647="","",'Model inputs'!B1647>0))="",FALSE,IF(ISERROR('Model inputs'!B1647>0),'Model inputs'!B1647>0,IF('Model inputs'!B1647="","",'Model inputs'!B1647>0))),1,0) -> 0 | AA46: =IF(IF(IF(ISERROR('Model inputs'!B1681>0),'Model inputs'!B1681>0,IF('Model inputs'!B1681="","",'Model inputs'!B1681>0))="",FALSE,IF(ISERROR('Model inputs'!B1681>0),'Model inputs'!B1681>0,IF('Model inputs'!B1681="","",'Model inputs'!B1681>0))),1,0) -> 0 | AB46: =IF(IF(IF(ISERROR('Model inputs'!B1715>0),'Model inputs'!B1715>0,IF('Model inputs'!B1715="","",'Model inputs'!B1715>0))="",FALSE,IF(ISERROR('Model inputs'!B1715>0),'Model inputs'!B1715>0,IF('Model inputs'!B1715="","",'Model inputs'!B1715>0))),1,0) -> 0 | AC46: =IF(IF(IF(ISERROR('Model inputs'!B1749>0),'Model inputs'!B1749>0,IF('Model inputs'!B1749="","",'Model inputs'!B1749>0))="",FALSE,IF(ISERROR('Model inputs'!B1749>0),'Model inputs'!B1749>0,IF('Model inputs'!B1749="","",'Model inputs'!B1749>0))),1,0) -> 0 | AD46: =IF(IF(IF(ISERROR('Model inputs'!B1783>0),'Model inputs'!B1783>0,IF('Model inputs'!B1783="","",'Model inputs'!B1783>0))="",FALSE,IF(ISERROR('Model inputs'!B1783>0),'Model inputs'!B1783>0,IF('Model inputs'!B1783="","",'Model inputs'!B1783>0))),1,0) -> 0 | AE46: =IF(IF(IF(ISERROR('Model inputs'!B1817>0),'Model inputs'!B1817>0,IF('Model inputs'!B1817="","",'Model inputs'!B1817>0))="",FALSE,IF(ISERROR('Model inputs'!B1817>0),'Model inputs'!B1817>0,IF('Model inputs'!B1817="","",'Model inputs'!B1817>0))),1,0) -> 0 | AF46: =IF(IF(IF(ISERROR('Model inputs'!B1851>0),'Model inputs'!B1851>0,IF('Model inputs'!B1851="","",'Model inputs'!B1851>0))="",FALSE,IF(ISERROR('Model inputs'!B1851>0),'Model inputs'!B1851>0,IF('Model inputs'!B1851="","",'Model inputs'!B1851>0))),1,0) -> 0 | AG46: =IF(IF(IF(ISERROR('Model inputs'!B1885>0),'Model inputs'!B1885>0,IF('Model inputs'!B1885="","",'Model inputs'!B1885>0))="",FALSE,IF(ISERROR('Model inputs'!B1885>0),'Model inputs'!B1885>0,IF('Model inputs'!B1885="","",'Model inputs'!B1885>0))),1,0) -> 0 | AH46: =IF(IF(IF(ISERROR('Model inputs'!B1919>0),'Model inputs'!B1919>0,IF('Model inputs'!B1919="","",'Model inputs'!B1919>0))="",FALSE,IF(ISERROR('Model inputs'!B1919>0),'Model inputs'!B1919>0,IF('Model inputs'!B1919="","",'Model inputs'!B1919>0))),1,0) -> 0 | AI46: =IF(IF(IF(ISERROR('Model inputs'!B1953>0),'Model inputs'!B1953>0,IF('Model inputs'!B1953="","",'Model inputs'!B1953>0))="",FALSE,IF(ISERROR('Model inputs'!B1953>0),'Model inputs'!B1953>0,IF('Model inputs'!B1953="","",'Model inputs'!B1953>0))),1,0) -> 0 | AJ46: =IF(IF(IF(ISERROR('Model inputs'!B1987>0),'Model inputs'!B1987>0,IF('Model inputs'!B1987="","",'Model inputs'!B1987>0))="",FALSE,IF(ISERROR('Model inputs'!B1987>0),'Model inputs'!B1987>0,IF('Model inputs'!B1987="","",'Model inputs'!B1987>0))),1,0) -> 0
A47: Gross profit · Monthly forecast and cash · Main Scenario | D47: 0 | E47: 0 | F47: 0 | G47: 0 | H47: 0 | I47: 0 | J47: 0 | K47: 0 | L47: 0 | M47: ='Model inputs'!M67-'Model inputs'!M104 -> -45 | N47: ='Model inputs'!N67-'Model inputs'!N104 -> 360 | O47: ='Model inputs'!O67-'Model inputs'!O104 -> 765 | P47: ='Model inputs'!P67-'Model inputs'!P104 -> 1170 | Q47: ='Model inputs'!Q67-'Model inputs'!Q104 -> 1575 | R47: ='Model inputs'!R67-'Model inputs'!R104 -> 1980 | S47: ='Model inputs'!S67-'Model inputs'!S104 -> 2385 | T47: ='Model inputs'!T67-'Model inputs'!T104 -> 2790 | ... AJ47: ='Model inputs'!AJ67-'Model inputs'!AJ104 -> 9270
A48: Gross profit · AgentBisect — 100 teams at month 12 | L48: 0 | M48: ='Model inputs'!M144-'Model inputs'!M118 -> 198 | N48: ='Model inputs'!N144-'Model inputs'!N118 -> 927 | O48: ='Model inputs'!O144-'Model inputs'!O118 -> 1575 | P48: ='Model inputs'!P144-'Model inputs'!P118 -> 2223 | Q48: ='Model inputs'!Q144-'Model inputs'!Q118 -> 2952 | R48: ='Model inputs'!R144-'Model inputs'!R118 -> 3600 | S48: ='Model inputs'!S144-'Model inputs'!S118 -> 4248 | T48: ='Model inputs'!T144-'Model inputs'!T118 -> 4977 | ... W48: ='Model inputs'!W144-'Model inputs'!W118 -> 7002 | X48: ='Model inputs'!X70-'Model inputs'!X118 -> 7650
A49: Gross profit · AgentBisect — 20 teams at month 12 | L49: 0 | M49: ='Model inputs'!M147-'Model inputs'!M119 -> -288 | N49: ='Model inputs'!N147-'Model inputs'!N119 -> -207 | O49: ='Model inputs'!O147-'Model inputs'!O119 -> -45 | P49: ='Model inputs'!P147-'Model inputs'!P119 -> 117 | Q49: ='Model inputs'!Q147-'Model inputs'!Q119 -> 198 | R49: ='Model inputs'!R147-'Model inputs'!R119 -> 360 | S49: ='Model inputs'!S147-'Model inputs'!S119 -> 522 | T49: ='Model inputs'!T147-'Model inputs'!T119 -> 603 | ... W49: ='Model inputs'!W147-'Model inputs'!W119 -> 1008 | X49: ='Model inputs'!X73-'Model inputs'!X119 -> 1170
A50: Gross profit · AgentBisect — 300 teams at month 12 | L50: 0 | M50: ='Model inputs'!M150-'Model inputs'!M120 -> 1575 | N50: ='Model inputs'!N150-'Model inputs'!N120 -> 3600 | O50: ='Model inputs'!O150-'Model inputs'!O120 -> 5625 | P50: ='Model inputs'!P150-'Model inputs'!P120 -> 7650 | Q50: ='Model inputs'!Q150-'Model inputs'!Q120 -> 9675 | R50: ='Model inputs'!R150-'Model inputs'!R120 -> 11700 | S50: ='Model inputs'!S150-'Model inputs'!S120 -> 13725 | T50: ='Model inputs'!T150-'Model inputs'!T120 -> 15750 | ... W50: ='Model inputs'!W150-'Model inputs'!W120 -> 21825 | X50: ='Model inputs'!X76-'Model inputs'!X120 -> 23850
A51: Model cost per investigation · Unit economics by plan | B51: ='Editable assumptions'!B5 -> 0.25
A52: Model cost per investigation · Monthly forecast and cash | C52: ='Editable assumptions'!B5 -> 0.25
A53: Month 12 paying team target · AgentBisect — 100 teams at month 12 | C53: =100 -> 100
A54: Month 12 paying team target · AgentBisect — 20 teams at month 12 | C54: =20 -> 20
A55: Month 12 paying team target · AgentBisect — 300 teams at month 12 | C55: =300 -> 300
A56: Net cash flow · Monthly forecast and cash · Main Scenario | D56: 0 | E56: 0 | F56: 0 | G56: 0 | H56: 0 | I56: 0 | J56: 0 | K56: 0 | L56: 0 | M56: =IF('Model inputs'!M103="","",'Model inputs'!M103) -> -45 | N56: =IF('Model inputs'!N103="","",'Model inputs'!N103) -> 360 | O56: =IF('Model inputs'!O103="","",'Model inputs'!O103) -> 765 | P56: =IF('Model inputs'!P103="","",'Model inputs'!P103) -> 1170 | Q56: =IF('Model inputs'!Q103="","",'Model inputs'!Q103) -> 1575 | R56: =IF('Model inputs'!R103="","",'Model inputs'!R103) -> 1980 | S56: =IF('Model inputs'!S103="","",'Model inputs'!S103) -> -5615 | T56: =IF('Model inputs'!T103="","",'Model inputs'!T103) -> -5210 | ... AJ56: =IF('Model inputs'!AJ103="","",'Model inputs'!AJ103) -> 1270
A57: Net cash flow · AgentBisect — 100 teams at month 12 | L57: 0 | M57: =IF('Model inputs'!M135="","",'Model inputs'!M135) -> 198 | N57: =IF('Model inputs'!N135="","",'Model inputs'!N135) -> 927 | O57: =IF('Model inputs'!O135="","",'Model inputs'!O135) -> 1575 | P57: =IF('Model inputs'!P135="","",'Model inputs'!P135) -> 2223 | Q57: =IF('Model inputs'!Q135="","",'Model inputs'!Q135) -> 2952 | R57: =IF('Model inputs'!R135="","",'Model inputs'!R135) -> 3600 | S57: =IF('Model inputs'!S135="","",'Model inputs'!S135) -> -3752 | T57: =IF('Model inputs'!T135="","",'Model inputs'!T135) -> -3023 | ... X57: =IF('Model inputs'!X135="","",'Model inputs'!X135) -> -350
A58: Net cash flow · AgentBisect — 20 teams at month 12 | L58: 0 | M58: =IF('Model inputs'!M136="","",'Model inputs'!M136) -> -288 | N58: =IF('Model inputs'!N136="","",'Model inputs'!N136) -> -207 | O58: =IF('Model inputs'!O136="","",'Model inputs'!O136) -> -45 | P58: =IF('Model inputs'!P136="","",'Model inputs'!P136) -> 117 | Q58: =IF('Model inputs'!Q136="","",'Model inputs'!Q136) -> 198 | R58: =IF('Model inputs'!R136="","",'Model inputs'!R136) -> 360 | S58: =IF('Model inputs'!S136="","",'Model inputs'!S136) -> -7478 | T58: =IF('Model inputs'!T136="","",'Model inputs'!T136) -> -7397 | ... X58: =IF('Model inputs'!X136="","",'Model inputs'!X136) -> -6830
A59: Net cash flow · AgentBisect — 300 teams at month 12 | L59: 0 | M59: =IF('Model inputs'!M137="","",'Model inputs'!M137) -> 1575 | N59: =IF('Model inputs'!N137="","",'Model inputs'!N137) -> 3600 | O59: =IF('Model inputs'!O137="","",'Model inputs'!O137) -> 5625 | P59: =IF('Model inputs'!P137="","",'Model inputs'!P137) -> 7650 | Q59: =IF('Model inputs'!Q137="","",'Model inputs'!Q137) -> 9675 | R59: =IF('Model inputs'!R137="","",'Model inputs'!R137) -> 11700 | S59: =IF('Model inputs'!S137="","",'Model inputs'!S137) -> 5725 | T59: =IF('Model inputs'!T137="","",'Model inputs'!T137) -> 7750 | ... X59: =IF('Model inputs'!X137="","",'Model inputs'!X137) -> 15850
A60: Net new teams per month · Editable assumptions | B60: ='Editable assumptions'!B13 -> 5
A61: Net new teams per month · Monthly forecast and cash | C61: ='Editable assumptions'!B13 -> 5
A62: Opening paying teams · Editable assumptions · Main Scenario | B62: ='Editable assumptions'!B12 -> 0
A63: Opening paying teams · Monthly forecast and cash · Main Scenario | C63: ='Editable assumptions'!B12 -> 0
A64: Opening paying teams · AgentBisect — 100 teams at month 12 | C64: ='Editable assumptions'!B12 -> 0
A65: Opening paying teams · AgentBisect — 20 teams at month 12 | C65: ='Editable assumptions'!B12 -> 0
A66: Opening paying teams · AgentBisect — 300 teams at month 12 | C66: ='Editable assumptions'!B12 -> 0
A67: Revenue | L67: =SUM('Model inputs'!L68,'Model inputs'!L69) -> 0 | M67: =SUM('Model inputs'!M68,'Model inputs'!M69) -> 495 | N67: =SUM('Model inputs'!N68,'Model inputs'!N69) -> 990 | O67: =SUM('Model inputs'!O68,'Model inputs'!O69) -> 1485 | P67: =SUM('Model inputs'!P68,'Model inputs'!P69) -> 1980 | Q67: =SUM('Model inputs'!Q68,'Model inputs'!Q69) -> 2475 | R67: =SUM('Model inputs'!R68,'Model inputs'!R69) -> 2970 | S67: =SUM('Model inputs'!S68,'Model inputs'!S69) -> 3465 | ... AJ67: =SUM('Model inputs'!AJ68,'Model inputs'!AJ69) -> 11880
A68: Revenue > Free | L68: ='Monthly forecast and cash'!B13 -> 0 | M68: =IF(IF(EXACT("Free","Team"),IF('Model inputs'!M113="","",'Model inputs'!M113),IF('Model inputs'!M105="","",'Model inputs'!M105))="",0,IF(EXACT("Free","Team"),IF('Model inputs'!M113="","",'Model inputs'!M113),IF('Model inputs'!M105="","",'Model inputs'!M105)))*'Model inputs'!B80 -> 0 | N68: =IF(IF(EXACT("Free","Team"),IF('Model inputs'!N113="","",'Model inputs'!N113),IF('Model inputs'!N105="","",'Model inputs'!N105))="",0,IF(EXACT("Free","Team"),IF('Model inputs'!N113="","",'Model inputs'!N113),IF('Model inputs'!N105="","",'Model inputs'!N105)))*'Model inputs'!B80 -> 0 | O68: =IF(IF(EXACT("Free","Team"),IF('Model inputs'!O113="","",'Model inputs'!O113),IF('Model inputs'!O105="","",'Model inputs'!O105))="",0,IF(EXACT("Free","Team"),IF('Model inputs'!O113="","",'Model inputs'!O113),IF('Model inputs'!O105="","",'Model inputs'!O105)))*'Model inputs'!B80 -> 0 | P68: =IF(IF(EXACT("Free","Team"),IF('Model inputs'!P113="","",'Model inputs'!P113),IF('Model inputs'!P105="","",'Model inputs'!P105))="",0,IF(EXACT("Free","Team"),IF('Model inputs'!P113="","",'Model inputs'!P113),IF('Model inputs'!P105="","",'Model inputs'!P105)))*'Model inputs'!B80 -> 0 | Q68: =IF(IF(EXACT("Free","Team"),IF('Model inputs'!Q113="","",'Model inputs'!Q113),IF('Model inputs'!Q105="","",'Model inputs'!Q105))="",0,IF(EXACT("Free","Team"),IF('Model inputs'!Q113="","",'Model inputs'!Q113),IF('Model inputs'!Q105="","",'Model inputs'!Q105)))*'Model inputs'!B80 -> 0 | R68: =IF(IF(EXACT("Free","Team"),IF('Model inputs'!R113="","",'Model inputs'!R113),IF('Model inputs'!R105="","",'Model inputs'!R105))="",0,IF(EXACT("Free","Team"),IF('Model inputs'!R113="","",'Model inputs'!R113),IF('Model inputs'!R105="","",'Model inputs'!R105)))*'Model inputs'!B80 -> 0 | S68: =IF(IF(EXACT("Free","Team"),IF('Model inputs'!S113="","",'Model inputs'!S113),IF('Model inputs'!S105="","",'Model inputs'!S105))="",0,IF(EXACT("Free","Team"),IF('Model inputs'!S113="","",'Model inputs'!S113),IF('Model inputs'!S105="","",'Model inputs'!S105)))*'Model inputs'!B80 -> 0 | T68: =IF(IF(EXACT("Free","Team"),IF('Model inputs'!T113="","",'Model inputs'!T113),IF('Model inputs'!T105="","",'Model inputs'!T105))="",0,IF(EXACT("Free","Team"),IF('Model inputs'!T113="","",'Model inputs'!T113),IF('Model inputs'!T105="","",'Model inputs'!T105)))*'Model inputs'!B80 -> 0 | U68: =IF(IF(EXACT("Free","Team"),IF('Model inputs'!U113="","",'Model inputs'!U113),IF('Model inputs'!U105="","",'Model inputs'!U105))="",0,IF(EXACT("Free","Team"),IF('Model inputs'!U113="","",'Model inputs'!U113),IF('Model inputs'!U105="","",'Model inputs'!U105)))*'Model inputs'!B80 -> 0 | V68: =IF(IF(EXACT("Free","Team"),IF('Model inputs'!V113="","",'Model inputs'!V113),IF('Model inputs'!V105="","",'Model inputs'!V105))="",0,IF(EXACT("Free","Team"),IF('Model inputs'!V113="","",'Model inputs'!V113),IF('Model inputs'!V105="","",'Model inputs'!V105)))*'Model inputs'!B80 -> 0 | W68: =IF(IF(EXACT("Free","Team"),IF('Model inputs'!W113="","",'Model inputs'!W113),IF('Model inputs'!W105="","",'Model inputs'!W105))="",0,IF(EXACT("Free","Team"),IF('Model inputs'!W113="","",'Model inputs'!W113),IF('Model inputs'!W105="","",'Model inputs'!W105)))*'Model inputs'!B80 -> 0 | X68: =IF(IF(EXACT("Free","Team"),IF('Model inputs'!X113="","",'Model inputs'!X113),IF('Model inputs'!X105="","",'Model inputs'!X105))="",0,IF(EXACT("Free","Team"),IF('Model inputs'!X113="","",'Model inputs'!X113),IF('Model inputs'!X105="","",'Model inputs'!X105)))*'Model inputs'!B80 -> 0 | Y68: =IF(IF(EXACT("Free","Team"),IF('Model inputs'!Y113="","",'Model inputs'!Y113),IF('Model inputs'!Y105="","",'Model inputs'!Y105))="",0,IF(EXACT("Free","Team"),IF('Model inputs'!Y113="","",'Model inputs'!Y113),IF('Model inputs'!Y105="","",'Model inputs'!Y105)))*'Model inputs'!B80 -> 0 | Z68: =IF(IF(EXACT("Free","Team"),IF('Model inputs'!Z113="","",'Model inputs'!Z113),IF('Model inputs'!Z105="","",'Model inputs'!Z105))="",0,IF(EXACT("Free","Team"),IF('Model inputs'!Z113="","",'Model inputs'!Z113),IF('Model inputs'!Z105="","",'Model inputs'!Z105)))*'Model inputs'!B80 -> 0 | AA68: =IF(IF(EXACT("Free","Team"),IF('Model inputs'!AA113="","",'Model inputs'!AA113),IF('Model inputs'!AA105="","",'Model inputs'!AA105))="",0,IF(EXACT("Free","Team"),IF('Model inputs'!AA113="","",'Model inputs'!AA113),IF('Model inputs'!AA105="","",'Model inputs'!AA105)))*'Model inputs'!B80 -> 0 | AB68: =IF(IF(EXACT("Free","Team"),IF('Model inputs'!AB113="","",'Model inputs'!AB113),IF('Model inputs'!AB105="","",'Model inputs'!AB105))="",0,IF(EXACT("Free","Team"),IF('Model inputs'!AB113="","",'Model inputs'!AB113),IF('Model inputs'!AB105="","",'Model inputs'!AB105)))*'Model inputs'!B80 -> 0 | AC68: =IF(IF(EXACT("Free","Team"),IF('Model inputs'!AC113="","",'Model inputs'!AC113),IF('Model inputs'!AC105="","",'Model inputs'!AC105))="",0,IF(EXACT("Free","Team"),IF('Model inputs'!AC113="","",'Model inputs'!AC113),IF('Model inputs'!AC105="","",'Model inputs'!AC105)))*'Model inputs'!B80 -> 0 | AD68: =IF(IF(EXACT("Free","Team"),IF('Model inputs'!AD113="","",'Model inputs'!AD113),IF('Model inputs'!AD105="","",'Model inputs'!AD105))="",0,IF(EXACT("Free","Team"),IF('Model inputs'!AD113="","",'Model inputs'!AD113),IF('Model inputs'!AD105="","",'Model inputs'!AD105)))*'Model inputs'!B80 -> 0 | AE68: =IF(IF(EXACT("Free","Team"),IF('Model inputs'!AE113="","",'Model inputs'!AE113),IF('Model inputs'!AE105="","",'Model inputs'!AE105))="",0,IF(EXACT("Free","Team"),IF('Model inputs'!AE113="","",'Model inputs'!AE113),IF('Model inputs'!AE105="","",'Model inputs'!AE105)))*'Model inputs'!B80 -> 0 | AF68: =IF(IF(EXACT("Free","Team"),IF('Model inputs'!AF113="","",'Model inputs'!AF113),IF('Model inputs'!AF105="","",'Model inputs'!AF105))="",0,IF(EXACT("Free","Team"),IF('Model inputs'!AF113="","",'Model inputs'!AF113),IF('Model inputs'!AF105="","",'Model inputs'!AF105)))*'Model inputs'!B80 -> 0 | AG68: =IF(IF(EXACT("Free","Team"),IF('Model inputs'!AG113="","",'Model inputs'!AG113),IF('Model inputs'!AG105="","",'Model inputs'!AG105))="",0,IF(EXACT("Free","Team"),IF('Model inputs'!AG113="","",'Model inputs'!AG113),IF('Model inputs'!AG105="","",'Model inputs'!AG105)))*'Model inputs'!B80 -> 0 | AH68: =IF(IF(EXACT("Free","Team"),IF('Model inputs'!AH113="","",'Model inputs'!AH113),IF('Model inputs'!AH105="","",'Model inputs'!AH105))="",0,IF(EXACT("Free","Team"),IF('Model inputs'!AH113="","",'Model inputs'!AH113),IF('Model inputs'!AH105="","",'Model inputs'!AH105)))*'Model inputs'!B80 -> 0 | AI68: =IF(IF(EXACT("Free","Team"),IF('Model inputs'!AI113="","",'Model inputs'!AI113),IF('Model inputs'!AI105="","",'Model inputs'!AI105))="",0,IF(EXACT("Free","Team"),IF('Model inputs'!AI113="","",'Model inputs'!AI113),IF('Model inputs'!AI105="","",'Model inputs'!AI105)))*'Model inputs'!B80 -> 0 | AJ68: =IF(IF(EXACT("Free","Team"),IF('Model inputs'!AJ113="","",'Model inputs'!AJ113),IF('Model inputs'!AJ105="","",'Model inputs'!AJ105))="",0,IF(EXACT("Free","Team"),IF('Model inputs'!AJ113="","",'Model inputs'!AJ113),IF('Model inputs'!AJ105="","",'Model inputs'!AJ105)))*'Model inputs'!B80 -> 0
A69: Revenue > Team | L69: ='Monthly forecast and cash'!B14 -> 0 | M69: =IF(IF(EXACT("Team","Team"),IF('Model inputs'!M113="","",'Model inputs'!M113),IF('Model inputs'!M105="","",'Model inputs'!M105))="",0,IF(EXACT("Team","Team"),IF('Model inputs'!M113="","",'Model inputs'!M113),IF('Model inputs'!M105="","",'Model inputs'!M105)))*'Model inputs'!B81 -> 495 | N69: =IF(IF(EXACT("Team","Team"),IF('Model inputs'!N113="","",'Model inputs'!N113),IF('Model inputs'!N105="","",'Model inputs'!N105))="",0,IF(EXACT("Team","Team"),IF('Model inputs'!N113="","",'Model inputs'!N113),IF('Model inputs'!N105="","",'Model inputs'!N105)))*'Model inputs'!B81 -> 990 | O69: =IF(IF(EXACT("Team","Team"),IF('Model inputs'!O113="","",'Model inputs'!O113),IF('Model inputs'!O105="","",'Model inputs'!O105))="",0,IF(EXACT("Team","Team"),IF('Model inputs'!O113="","",'Model inputs'!O113),IF('Model inputs'!O105="","",'Model inputs'!O105)))*'Model inputs'!B81 -> 1485 | P69: =IF(IF(EXACT("Team","Team"),IF('Model inputs'!P113="","",'Model inputs'!P113),IF('Model inputs'!P105="","",'Model inputs'!P105))="",0,IF(EXACT("Team","Team"),IF('Model inputs'!P113="","",'Model inputs'!P113),IF('Model inputs'!P105="","",'Model inputs'!P105)))*'Model inputs'!B81 -> 1980 | Q69: =IF(IF(EXACT("Team","Team"),IF('Model inputs'!Q113="","",'Model inputs'!Q113),IF('Model inputs'!Q105="","",'Model inputs'!Q105))="",0,IF(EXACT("Team","Team"),IF('Model inputs'!Q113="","",'Model inputs'!Q113),IF('Model inputs'!Q105="","",'Model inputs'!Q105)))*'Model inputs'!B81 -> 2475 | R69: =IF(IF(EXACT("Team","Team"),IF('Model inputs'!R113="","",'Model inputs'!R113),IF('Model inputs'!R105="","",'Model inputs'!R105))="",0,IF(EXACT("Team","Team"),IF('Model inputs'!R113="","",'Model inputs'!R113),IF('Model inputs'!R105="","",'Model inputs'!R105)))*'Model inputs'!B81 -> 2970 | S69: =IF(IF(EXACT("Team","Team"),IF('Model inputs'!S113="","",'Model inputs'!S113),IF('Model inputs'!S105="","",'Model inputs'!S105))="",0,IF(EXACT("Team","Team"),IF('Model inputs'!S113="","",'Model inputs'!S113),IF('Model inputs'!S105="","",'Model inputs'!S105)))*'Model inputs'!B81 -> 3465 | T69: =IF(IF(EXACT("Team","Team"),IF('Model inputs'!T113="","",'Model inputs'!T113),IF('Model inputs'!T105="","",'Model inputs'!T105))="",0,IF(EXACT("Team","Team"),IF('Model inputs'!T113="","",'Model inputs'!T113),IF('Model inputs'!T105="","",'Model inputs'!T105)))*'Model inputs'!B81 -> 3960 | U69: =IF(IF(EXACT("Team","Team"),IF('Model inputs'!U113="","",'Model inputs'!U113),IF('Model inputs'!U105="","",'Model inputs'!U105))="",0,IF(EXACT("Team","Team"),IF('Model inputs'!U113="","",'Model inputs'!U113),IF('Model inputs'!U105="","",'Model inputs'!U105)))*'Model inputs'!B81 -> 4455 | V69: =IF(IF(EXACT("Team","Team"),IF('Model inputs'!V113="","",'Model inputs'!V113),IF('Model inputs'!V105="","",'Model inputs'!V105))="",0,IF(EXACT("Team","Team"),IF('Model inputs'!V113="","",'Model inputs'!V113),IF('Model inputs'!V105="","",'Model inputs'!V105)))*'Model inputs'!B81 -> 4950 | W69: =IF(IF(EXACT("Team","Team"),IF('Model inputs'!W113="","",'Model inputs'!W113),IF('Model inputs'!W105="","",'Model inputs'!W105))="",0,IF(EXACT("Team","Team"),IF('Model inputs'!W113="","",'Model inputs'!W113),IF('Model inputs'!W105="","",'Model inputs'!W105)))*'Model inputs'!B81 -> 5445 | X69: =IF(IF(EXACT("Team","Team"),IF('Model inputs'!X113="","",'Model inputs'!X113),IF('Model inputs'!X105="","",'Model inputs'!X105))="",0,IF(EXACT("Team","Team"),IF('Model inputs'!X113="","",'Model inputs'!X113),IF('Model inputs'!X105="","",'Model inputs'!X105)))*'Model inputs'!B81 -> 5940 | Y69: =IF(IF(EXACT("Team","Team"),IF('Model inputs'!Y113="","",'Model inputs'!Y113),IF('Model inputs'!Y105="","",'Model inputs'!Y105))="",0,IF(EXACT("Team","Team"),IF('Model inputs'!Y113="","",'Model inputs'!Y113),IF('Model inputs'!Y105="","",'Model inputs'!Y105)))*'Model inputs'!B81 -> 6435 | Z69: =IF(IF(EXACT("Team","Team"),IF('Model inputs'!Z113="","",'Model inputs'!Z113),IF('Model inputs'!Z105="","",'Model inputs'!Z105))="",0,IF(EXACT("Team","Team"),IF('Model inputs'!Z113="","",'Model inputs'!Z113),IF('Model inputs'!Z105="","",'Model inputs'!Z105)))*'Model inputs'!B81 -> 6930 | AA69: =IF(IF(EXACT("Team","Team"),IF('Model inputs'!AA113="","",'Model inputs'!AA113),IF('Model inputs'!AA105="","",'Model inputs'!AA105))="",0,IF(EXACT("Team","Team"),IF('Model inputs'!AA113="","",'Model inputs'!AA113),IF('Model inputs'!AA105="","",'Model inputs'!AA105)))*'Model inputs'!B81 -> 7425 | AB69: =IF(IF(EXACT("Team","Team"),IF('Model inputs'!AB113="","",'Model inputs'!AB113),IF('Model inputs'!AB105="","",'Model inputs'!AB105))="",0,IF(EXACT("Team","Team"),IF('Model inputs'!AB113="","",'Model inputs'!AB113),IF('Model inputs'!AB105="","",'Model inputs'!AB105)))*'Model inputs'!B81 -> 7920 | AC69: =IF(IF(EXACT("Team","Team"),IF('Model inputs'!AC113="","",'Model inputs'!AC113),IF('Model inputs'!AC105="","",'Model inputs'!AC105))="",0,IF(EXACT("Team","Team"),IF('Model inputs'!AC113="","",'Model inputs'!AC113),IF('Model inputs'!AC105="","",'Model inputs'!AC105)))*'Model inputs'!B81 -> 8415 | AD69: =IF(IF(EXACT("Team","Team"),IF('Model inputs'!AD113="","",'Model inputs'!AD113),IF('Model inputs'!AD105="","",'Model inputs'!AD105))="",0,IF(EXACT("Team","Team"),IF('Model inputs'!AD113="","",'Model inputs'!AD113),IF('Model inputs'!AD105="","",'Model inputs'!AD105)))*'Model inputs'!B81 -> 8910 | AE69: =IF(IF(EXACT("Team","Team"),IF('Model inputs'!AE113="","",'Model inputs'!AE113),IF('Model inputs'!AE105="","",'Model inputs'!AE105))="",0,IF(EXACT("Team","Team"),IF('Model inputs'!AE113="","",'Model inputs'!AE113),IF('Model inputs'!AE105="","",'Model inputs'!AE105)))*'Model inputs'!B81 -> 9405 | AF69: =IF(IF(EXACT("Team","Team"),IF('Model inputs'!AF113="","",'Model inputs'!AF113),IF('Model inputs'!AF105="","",'Model inputs'!AF105))="",0,IF(EXACT("Team","Team"),IF('Model inputs'!AF113="","",'Model inputs'!AF113),IF('Model inputs'!AF105="","",'Model inputs'!AF105)))*'Model inputs'!B81 -> 9900 | AG69: =IF(IF(EXACT("Team","Team"),IF('Model inputs'!AG113="","",'Model inputs'!AG113),IF('Model inputs'!AG105="","",'Model inputs'!AG105))="",0,IF(EXACT("Team","Team"),IF('Model inputs'!AG113="","",'Model inputs'!AG113),IF('Model inputs'!AG105="","",'Model inputs'!AG105)))*'Model inputs'!B81 -> 10395 | AH69: =IF(IF(EXACT("Team","Team"),IF('Model inputs'!AH113="","",'Model inputs'!AH113),IF('Model inputs'!AH105="","",'Model inputs'!AH105))="",0,IF(EXACT("Team","Team"),IF('Model inputs'!AH113="","",'Model inputs'!AH113),IF('Model inputs'!AH105="","",'Model inputs'!AH105)))*'Model inputs'!B81 -> 10890 | AI69: =IF(IF(EXACT("Team","Team"),IF('Model inputs'!AI113="","",'Model inputs'!AI113),IF('Model inputs'!AI105="","",'Model inputs'!AI105))="",0,IF(EXACT("Team","Team"),IF('Model inputs'!AI113="","",'Model inputs'!AI113),IF('Model inputs'!AI105="","",'Model inputs'!AI105)))*'Model inputs'!B81 -> 11385 | AJ69: =IF(IF(EXACT("Team","Team"),IF('Model inputs'!AJ113="","",'Model inputs'!AJ113),IF('Model inputs'!AJ105="","",'Model inputs'!AJ105))="",0,IF(EXACT("Team","Team"),IF('Model inputs'!AJ113="","",'Model inputs'!AJ113),IF('Model inputs'!AJ105="","",'Model inputs'!AJ105)))*'Model inputs'!B81 -> 11880
A70: Revenue | X70: =SUM('Model inputs'!X71,'Model inputs'!X72) -> 9900
A71: Revenue > Free | X71: =IF(IF(EXACT("Free","Team"),IF('Model inputs'!X138="","",'Model inputs'!X138),IF('Model inputs'!X168="","",'Model inputs'!X168))="",0,IF(EXACT("Free","Team"),IF('Model inputs'!X138="","",'Model inputs'!X138),IF('Model inputs'!X168="","",'Model inputs'!X168)))*'Model inputs'!C154 -> 0
A72: Revenue > Team | X72: =IF(IF(EXACT("Team","Team"),IF('Model inputs'!X138="","",'Model inputs'!X138),IF('Model inputs'!X168="","",'Model inputs'!X168))="",0,IF(EXACT("Team","Team"),IF('Model inputs'!X138="","",'Model inputs'!X138),IF('Model inputs'!X168="","",'Model inputs'!X168)))*'Model inputs'!C155 -> 9900
A73: Revenue | X73: =SUM('Model inputs'!X74,'Model inputs'!X75) -> 1980
A74: Revenue > Free | X74: =IF(IF(EXACT("Free","Team"),IF('Model inputs'!X139="","",'Model inputs'!X139),IF('Model inputs'!X169="","",'Model inputs'!X169))="",0,IF(EXACT("Free","Team"),IF('Model inputs'!X139="","",'Model inputs'!X139),IF('Model inputs'!X169="","",'Model inputs'!X169)))*'Model inputs'!C157 -> 0
A75: Revenue > Team | X75: =IF(IF(EXACT("Team","Team"),IF('Model inputs'!X139="","",'Model inputs'!X139),IF('Model inputs'!X169="","",'Model inputs'!X169))="",0,IF(EXACT("Team","Team"),IF('Model inputs'!X139="","",'Model inputs'!X139),IF('Model inputs'!X169="","",'Model inputs'!X169)))*'Model inputs'!C158 -> 1980
A76: Revenue | X76: =SUM('Model inputs'!X77,'Model inputs'!X78) -> 29700
A77: Revenue > Free | X77: =IF(IF(EXACT("Free","Team"),IF('Model inputs'!X140="","",'Model inputs'!X140),IF('Model inputs'!X170="","",'Model inputs'!X170))="",0,IF(EXACT("Free","Team"),IF('Model inputs'!X140="","",'Model inputs'!X140),IF('Model inputs'!X170="","",'Model inputs'!X170)))*'Model inputs'!C160 -> 0
A78: Revenue > Team | X78: =IF(IF(EXACT("Team","Team"),IF('Model inputs'!X140="","",'Model inputs'!X140),IF('Model inputs'!X170="","",'Model inputs'!X170))="",0,IF(EXACT("Team","Team"),IF('Model inputs'!X140="","",'Model inputs'!X140),IF('Model inputs'!X170="","",'Model inputs'!X170)))*'Model inputs'!C161 -> 29700
A79: Revenue per repo | B79: ='Model inputs'!B97+MAX('Model inputs'!B6-'Model inputs'!B93,0)*'Model inputs'!B100 -> 0
A80: Revenue per repo > Free | B80: ='Model inputs'!B98+MAX('Model inputs'!B7-'Model inputs'!B94,0)*'Model inputs'!B101 -> 0
A81: Revenue per repo > Team | B81: ='Model inputs'!B99+MAX('Model inputs'!B8-'Model inputs'!B95,0)*'Model inputs'!B102 -> 99
A82: Revenue per repo | C82: ='Model inputs'!B97+MAX('Model inputs'!B6-'Model inputs'!B93,0)*'Model inputs'!B100 -> 0
A83: Revenue per repo > Free | C83: ='Model inputs'!B98+MAX('Model inputs'!B7-'Model inputs'!B94,0)*'Model inputs'!B101 -> 0
A84: Revenue per repo > Team | C84: ='Model inputs'!B99+MAX('Model inputs'!B8-'Model inputs'!B95,0)*'Model inputs'!B102 -> 99
A85: Starting cash · Monthly forecast and cash | C85: ='Editable assumptions'!B11 -> 25000
A86: Unpaid founder months · Monthly forecast and cash | C86: ='Editable assumptions'!B10 -> 6
A87: Variable cost per repo | B87: ='Model inputs'!B6*'Model inputs'!B96 -> 0
A88: Variable cost per repo > Free | B88: ='Model inputs'!B7*'Unit economics by plan'!G5 -> 3
A89: Variable cost per repo > Team | B89: ='Model inputs'!B8*'Unit economics by plan'!G6 -> 18
A90: Variable cost per repo | C90: ='Model inputs'!B6*'Model inputs'!B96 -> 0
A91: Variable cost per repo > Free | C91: ='Model inputs'!B7*'Unit economics by plan'!G5 -> 3
A92: Variable cost per repo > Team | C92: ='Model inputs'!B8*'Unit economics by plan'!G6 -> 18
A93: Included investigations | B93: 0
A94: Included investigations > Free | B94: ='Unit economics by plan'!C5 -> 10
A95: Included investigations > Team | B95: ='Unit economics by plan'!C6 -> 100
A96: Investigation unit cost · Unit economics by plan | B96: ='Model inputs'!B51+'Model inputs'!B16 -> 0.3
A97: Monthly price per repo | B97: 0
A98: Monthly price per repo > Free | B98: ='Unit economics by plan'!B5 -> 0
A99: Monthly price per repo > Team | B99: ='Unit economics by plan'!B6 -> 99
A100: Overage price | B100: 0
A101: Overage price > Free | B101: ='Unit economics by plan'!E5 -> 0
...
